Workbook

Sheet PRODUTOS
A1: Despesas | C1: 0.2 | D1: Data Atualização | H1: Despesas Fixas | J1: 4100 | L1: PV | M1: =IF(N2=1,N5,IF(N2=2,M5,"ERRO")) -> 8000 | N1: 1-Digitado, 2- V Desejo
A2: LUCRO DESEJADO | C2: 0.5 | D2: 44306 | H2: Ponto de equlibrio | J2: =J1/J3 -> 5987.5012 | L2: Desp F | M2: =-J1 -> -4100 | N2: 1
A3: Taxas | B3: Aplicativos | C3: Taxa | D3: Online | E3: cartão | F3: TOTAL | H3: % IMC | J3: =I6 -> 0.68475977 | L3: Cutsos V | M3: =-(1-J3)*M1 -> -2521.9218 | N3: =IF(N2=1,"Ponto E",IF(N2=2,"V Desejo")) -> Ponto E
B4: Vendas Presencial | C4: 0 | D4: 0 | E4: 0.0494 | F4: =SUM(C4:E4) -> 0.0494 | L4: LUCRO | M4: =SUM(M1:M3) -> 1378.0782 | N4: =M4/M1 -> 0.17225977
B5: Ifood | C5: 0.12 | D5: 0.035 | E5: 0 | F5: 0.171 | L5: desejado | M5: =-M2/(1-C2-F8) -> 27107.438 | N5: 8000 | O5: Digite Vendas Totais/Mês
B6: Quero Delivery | C6: 0.08 | D6: 0.0499 | E6: 0 | F6: 0.13 | G6: =AVERAGE(G8:G166) -> 77.787933 | H6: =AVERAGE(H8:H166) -> 53.266048 | I6: =H6/G6 -> 0.68475977 | J6: =AVERAGE(J8:J166) -> 37.708461 | K6: =J6/G6 -> 0.48475977
A7: CÓDIGO | B7: Nome do Produto | C7: Custo unit | D7: Qt | E7: preço Cient | F7: % Custo | G7: PV-Prática | H7: MC | I7: %MC | J7: lucro prat | K7: % Lucro Prat | M7: MARKUP
A8: 501 | B8: P A S T E L | C8: =C10 -> 4.7896 | D8: 1 | E8: =C8/(1-$C$1-$C$2-$F$4) -> 19.11253 | F8: =IFERROR(C8/G8,"")+$F$4 -> 0.34875 | G8: 16 | H8: =IF(G8="","",G8-C8-($F$4)*G8) -> 10.42 | I8: =IF(G8="","",H8/G8) -> 0.65125 | J8: =IF(G8="","",H8-G8*($C$1)) -> 7.22 | K8: =IFERROR(J8/G8,"") -> 0.45125
A9: =A8+200 -> 701 | B9: BROWNIE NO POTE Ifood | C9: =C10 -> 4.7896 | D9: 1 | E9: =(E8/(1-$F$5)) -> 23.054922 | F9: =IFERROR(C9/G9,"")+$F$5 -> 0.3787474 | G9: =E9 -> 23.054922 | H9: =IF(G9="","",G9-C9-($F$5)*G9) -> 14.32293 | I9: =IF(G9="","",H9/G9) -> 0.6212526 | J9: =IF(G9="","",H9-G9*$C$1) -> 9.7119456 | K9: =IFERROR(J9/G9,"") -> 0.4212526 | L9: 1 | M9: 1
A10: =A8+400 -> 901 | B10: BROWNIE NO POTE Quero | C10: =Violino!C3:D3 -> 4.7896 | D10: 1 | E10: =E8/(1-$F$6) -> 21.968425 | F10: =IFERROR(C10/G10,"")+$F$6 -> 0.348022 | G10: =E10 -> 21.968425 | H10: =IF(G10="","",G10-C10-($F$6)*G10) -> 14.32293 | I10: =IF(G10="","",H10/G10) -> 0.651978 | J10: =IF(G10="","",H10-G10*$C$1) -> 9.9292449 | K10: =IFERROR(J10/G10,"") -> 0.451978 | L10: 0.87 | M10: 0.829
A11: =A8+1 -> 502 | B11: BOLO GELADO ABACAXI | C11: ='BOLO GELADO ABACAXI'!C3:D3 -> 99.690995 | D11: 1 | E11: =C11/(1-$C$1-$C$2-$F$4) -> 397.80924 | F11: =IFERROR(C11/G11,"")+$F$4 -> 6.6954663 | G11: 15 | H11: =IF(G11="","",G11-C11-($F$4)*G11) -> -85.431995 | I11: =IF(G11="","",H11/G11) -> -5.6954663 | J11: =IF(G11="","",H11-G11*$C$1) -> -88.431995 | K11: =IFERROR(J11/G11,"") -> -5.8954663 | L11: =L10-L9 -> -0.13 | M11: =M10-M9 -> -0.171
A12: =A11+200 -> 702 | B12: BOLO GELADO ABACAXI ifood | C12: =C11 -> 99.690995 | D12: 1 | E12: =C12/(1-$C$1-$C$2-$F$5) -> 772.79841 | F12: =IFERROR(C12/G12,"")+$F$5 -> 0.3 | G12: =E12 -> 772.79841 | H12: =IF(G12="","",G12-C12-($F$5)*G12) -> 540.95888 | I12: =IF(G12="","",H12/G12) -> 0.7 | J12: =IF(G12="","",H12-G12*$C$1) -> 386.3992 | K12: =IFERROR(J12/G12,"") -> 0.5
A13: =A11+400 -> 902 | B13: BOLO GELADO ABACAXI Quero | C13: =C11 -> 99.690995 | D13: 1 | E13: =C13/(1-$C$1-$C$2-$F$6) -> 586.41761 | F13: =IFERROR(C13/G13,"")+$F$6 -> 0.3 | G13: =E13 -> 586.41761 | H13: =IF(G13="","",G13-C13-($F$6)*G13) -> 410.49233 | I13: =IF(G13="","",H13/G13) -> 0.7 | J13: =IF(G13="","",H13-G13*$C$1) -> 293.20881 | K13: =IFERROR(J13/G13,"") -> 0.5
A14: =A11+1 -> 503 | B14: BRIGADEIRO DUO | C14: ='BRIG COLHER'!C3:D3 -> 4.5661438 | D14: 1 | E14: =C14/(1-$C$1-$C$2-$F$4) -> 18.220845 | F14: =IFERROR(C14/G14,"")+$F$4 -> 0.3 | G14: =E14 -> 18.220845 | H14: =IF(G14="","",G14-C14-($F$4)*G14) -> 12.754592 | I14: =IF(G14="","",H14/G14) -> 0.7 | J14: =IF(G14="","",H14-G14*$C$1) -> 9.1104226 | K14: =IFERROR(J14/G14,"") -> 0.5
A15: =A14+200 -> 703 | B15: BRIGADEIRO DUO ifood | C15: =C14 -> 4.5661438 | D15: 1 | E15: =C15/(1-$C$1-$C$2-$F$5) -> 35.396463 | F15: =IFERROR(C15/G15,"")+$F$5 -> 0.3 | G15: =E15 -> 35.396463 | H15: =IF(G15="","",G15-C15-($F$5)*G15) -> 24.777524 | I15: =IF(G15="","",H15/G15) -> 0.7 | J15: =IF(G15="","",H15-G15*$C$1) -> 17.698232 | K15: =IFERROR(J15/G15,"") -> 0.5
A16: =A14+400 -> 903 | B16: BRIGADEIRO DUO Quero | C16: =C14 -> 4.5661438 | D16: 1 | E16: =C16/(1-$C$1-$C$2-$F$6) -> 26.859669 | F16: =IFERROR(C16/G16,"")+$F$6 -> 0.3 | G16: =E16 -> 26.859669 | H16: =IF(G16="","",G16-C16-($F$6)*G16) -> 18.801769 | I16: =IF(G16="","",H16/G16) -> 0.7 | J16: =IF(G16="","",H16-G16*$C$1) -> 13.429835 | K16: =IFERROR(J16/G16,"") -> 0.5
A17: =A14+1 -> 504 | B17: BRIGADEIRO DE COLHER | C17: ='BRIG COLHER'!C4:D4 -> 9 | D17: 1 | E17: =C17/(1-$C$1-$C$2-$F$4) -> 35.913807 | F17: =IFERROR(C17/G17,"")+$F$4 -> 0.3 | G17: =E17 -> 35.913807 | H17: =IF(G17="","",G17-C17-($F$4)*G17) -> 25.139665 | I17: =IF(G17="","",H17/G17) -> 0.7 | J17: =IF(G17="","",H17-G17*$C$1) -> 17.956903 | K17: =IFERROR(J17/G17,"") -> 0.5
A18: =A17+200 -> 704 | B18: BRIGADEIRO DE COLHER ifood | C18: =C17 -> 9 | D18: 1 | E18: =C18/(1-$C$1-$C$2-$F$5) -> 69.767442 | F18: =IFERROR(C18/G18,"")+$F$5 -> 0.3 | G18: =E18 -> 69.767442 | H18: =IF(G18="","",G18-C18-($F$5)*G18) -> 48.837209 | I18: =IF(G18="","",H18/G18) -> 0.7 | J18: =IF(G18="","",H18-G18*$C$1) -> 34.883721 | K18: =IFERROR(J18/G18,"") -> 0.5
A19: =A17+400 -> 904 | B19: BRIGADEIRO DE COLHER Quero | C19: =C17 -> 9 | D19: 1 | E19: =C19/(1-$C$1-$C$2-$F$6) -> 52.941176 | F19: =IFERROR(C19/G19,"")+$F$6 -> 0.3 | G19: =E19 -> 52.941176 | H19: =IF(G19="","",G19-C19-($F$6)*G19) -> 37.058824 | I19: =IF(G19="","",H19/G19) -> 0.7 | J19: =IF(G19="","",H19-G19*$C$1) -> 26.470588 | K19: =IFERROR(J19/G19,"") -> 0.5
A20: =A17+1 -> 505 | B20: BRIGADEIRO UNITÁRIO | C20: ='BRIG UNITARIO'!C3:D3 -> 2.5251275 | D20: 1 | E20: =C20/(1-$C$1-$C$2-$F$4) -> 10.076327 | F20: =IFERROR(C20/G20,"")+$F$4 -> 0.3 | G20: =E20 -> 10.076327 | H20: =IF(G20="","",G20-C20-($F$4)*G20) -> 7.0534286 | I20: =IF(G20="","",H20/G20) -> 0.7 | J20: =IF(G20="","",H20-G20*$C$1) -> 5.0381633 | K20: =IFERROR(J20/G20,"") -> 0.5
A21: =A20+200 -> 705 | B21: BRIGADEIRO UNITÁRIO ifood | C21: =C20 -> 2.5251275 | D21: 1 | E21: =C21/(1-$C$1-$C$2-$F$5) -> 19.574631 | F21: =IFERROR(C21/G21,"")+$F$5 -> 0.3 | G21: =E21 -> 19.574631 | H21: =IF(G21="","",G21-C21-($F$5)*G21) -> 13.702242 | I21: =IF(G21="","",H21/G21) -> 0.7 | J21: =IF(G21="","",H21-G21*$C$1) -> 9.7873157 | K21: =IFERROR(J21/G21,"") -> 0.5
A22: =A20+400 -> 905 | B22: BRIGADEIRO UNITÁRIO Quero | C22: =C20 -> 2.5251275 | D22: 1 | E22: =C22/(1-$C$1-$C$2-$F$6) -> 14.853691 | F22: =IFERROR(C22/G22,"")+$F$6 -> 0.3 | G22: =E22 -> 14.853691 | H22: =IF(G22="","",G22-C22-($F$6)*G22) -> 10.397584 | I22: =IF(G22="","",H22/G22) -> 0.7 | J22: =IF(G22="","",H22-G22*$C$1) -> 7.4268454 | K22: =IFERROR(J22/G22,"") -> 0.5
A23: =A20+1 -> 506 | B23: CAJUZINHO | D23: 1 | E23: =C23/(1-$C$1-$C$2-$F$4) -> 0 | F23: =IFERROR(C23/G23,"")+$F$4 -> #VALUE! | G23: =E23 -> 0 | H23: =IF(G23="","",G23-C23-($F$4)*G23) -> 0 | I23: =IF(G23="","",H23/G23) -> #DIV/0! | J23: =IF(G23="","",H23-G23*$C$1) -> 0 | K23: =IFERROR(J23/G23,"")
A24: =A23+200 -> 706 | B24: CAJUZINHO ifood | C24: =C23 -> 0 | D24: 1 | E24: =C24/(1-$C$1-$C$2-$F$5) -> 0 | F24: =IFERROR(C24/G24,"")+$F$5 -> #VALUE! | G24: =E24 -> 0 | H24: =IF(G24="","",G24-C24-($F$5)*G24) -> 0 | I24: =IF(G24="","",H24/G24) -> #DIV/0! | J24: =IF(G24="","",H24-G24*$C$1) -> 0 | K24: =IFERROR(J24/G24,"")
A25: =A23+400 -> 906 | B25: CAJUZINHO Quero | C25: =C23 -> 0 | D25: 1 | E25: =C25/(1-$C$1-$C$2-$F$6) -> 0 | F25: =IFERROR(C25/G25,"")+$F$6 -> #VALUE! | G25: =E25 -> 0 | H25: =IF(G25="","",G25-C25-($F$6)*G25) -> 0 | I25: =IF(G25="","",H25/G25) -> #DIV/0! | J25: =IF(G25="","",H25-G25*$C$1) -> 0 | K25: =IFERROR(J25/G25,"")
A26: =A23+1 -> 507 | B26: BEIJINHO | C26: =BEIJINHO!C4 -> 13 | D26: 1 | E26: =C26/(1-$C$1-$C$2-$F$4) -> 51.875499 | F26: =IFERROR(C26/G26,"")+$F$4 -> 0.3 | G26: =E26 -> 51.875499 | H26: =IF(G26="","",G26-C26-($F$4)*G26) -> 36.312849 | I26: =IF(G26="","",H26/G26) -> 0.7 | J26: =IF(G26="","",H26-G26*$C$1) -> 25.937749 | K26: =IFERROR(J26/G26,"") -> 0.5
A27: =A26+200 -> 707 | B27: BEIJINHO ifood | C27: =C26 -> 13 | D27: 1 | E27: =C27/(1-$C$1-$C$2-$F$5) -> 100.77519 | F27: =IFERROR(C27/G27,"")+$F$5 -> 0.3 | G27: =E27 -> 100.77519 | H27: =IF(G27="","",G27-C27-($F$5)*G27) -> 70.542636 | I27: =IF(G27="","",H27/G27) -> 0.7 | J27: =IF(G27="","",H27-G27*$C$1) -> 50.387597 | K27: =IFERROR(J27/G27,"") -> 0.5
A28: =A26+400 -> 907 | B28: BEIJINHO Quero | C28: =C26 -> 13 | D28: 1 | E28: =C28/(1-$C$1-$C$2-$F$6) -> 76.470588 | F28: =IFERROR(C28/G28,"")+$F$6 -> 0.3 | G28: =E28 -> 76.470588 | H28: =IF(G28="","",G28-C28-($F$6)*G28) -> 53.529412 | I28: =IF(G28="","",H28/G28) -> 0.7 | J28: =IF(G28="","",H28-G28*$C$1) -> 38.235294 | K28: =IFERROR(J28/G28,"") -> 0.5
A29: =A26+1 -> 508 | B29: ALFAJOR | C29: =ALFAJOR!C4 -> 13 | D29: 1 | E29: =C29/(1-$C$1-$C$2-$F$4) -> 51.875499 | F29: =IFERROR(C29/G29,"")+$F$4 -> 0.3 | G29: =E29 -> 51.875499 | H29: =IF(G29="","",G29-C29-($F$4)*G29) -> 36.312849 | I29: =IF(G29="","",H29/G29) -> 0.7 | J29: =IF(G29="","",H29-G29*$C$1) -> 25.937749 | K29: =IFERROR(J29/G29,"") -> 0.5
A30: =A29+200 -> 708 | B30: ALFAJOR ifood | C30: =C29 -> 13 | D30: 1 | E30: =C30/(1-$C$1-$C$2-$F$5) -> 100.77519 | F30: =IFERROR(C30/G30,"")+$F$5 -> 0.3 | G30: =E30 -> 100.77519 | H30: =IF(G30="","",G30-C30-($F$5)*G30) -> 70.542636 | I30: =IF(G30="","",H30/G30) -> 0.7 | J30: =IF(G30="","",H30-G30*$C$1) -> 50.387597 | K30: =IFERROR(J30/G30,"") -> 0.5
A31: =A29+400 -> 908 | B31: ALFAJOR Quero | C31: =C29 -> 13 | D31: 1 | E31: =C31/(1-$C$1-$C$2-$F$6) -> 76.470588 | F31: =IFERROR(C31/G31,"")+$F$6 -> 0.3 | G31: =E31 -> 76.470588 | H31: =IF(G31="","",G31-C31-($F$6)*G31) -> 53.529412 | I31: =IF(G31="","",H31/G31) -> 0.7 | J31: =IF(G31="","",H31-G31*$C$1) -> 38.235294 | K31: =IFERROR(J31/G31,"") -> 0.5
A32: =A29+1 -> 509 | B32: PALHA ITALIANA | C32: ='PALHA ITALIANNA'!C4 -> 13 | D32: 1 | E32: =C32/(1-$C$1-$C$2-$F$4) -> 51.875499 | F32: =IFERROR(C32/G32,"")+$F$4 -> 0.3 | G32: =E32 -> 51.875499 | H32: =IF(G32="","",G32-C32-($F$4)*G32) -> 36.312849 | I32: =IF(G32="","",H32/G32) -> 0.7 | J32: =IF(G32="","",H32-G32*$C$1) -> 25.937749 | K32: =IFERROR(J32/G32,"") -> 0.5
A33: =A32+200 -> 709 | B33: PALHA ITALIANA ifood | C33: =C32 -> 13 | D33: 1 | E33: =C33/(1-$C$1-$C$2-$F$5) -> 100.77519 | F33: =IFERROR(C33/G33,"")+$F$5 -> 0.3 | G33: =E33 -> 100.77519 | H33: =IF(G33="","",G33-C33-($F$5)*G33) -> 70.542636 | I33: =IF(G33="","",H33/G33) -> 0.7 | J33: =IF(G33="","",H33-G33*$C$1) -> 50.387597 | K33: =IFERROR(J33/G33,"") -> 0.5
A34: =A32+400 -> 909 | B34: PALHA ITALIANA Quero | C34: =C32 -> 13 | D34: 1 | E34: =C34/(1-$C$1-$C$2-$F$6) -> 76.470588 | F34: =IFERROR(C34/G34,"")+$F$6 -> 0.3 | G34: =E34 -> 76.470588 | H34: =IF(G34="","",G34-C34-($F$6)*G34) -> 53.529412 | I34: =IF(G34="","",H34/G34) -> 0.7 | J34: =IF(G34="","",H34-G34*$C$1) -> 38.235294 | K34: =IFERROR(J34/G34,"") -> 0.5
A35: =A32+1 -> 510 | B35: EMPADA DE FRANGO | C35: ='EMPADA DE FRANGO'!C4:D4 -> 13 | D35: 1 | E35: =C35/(1-$C$1-$C$2-$F$4) -> 51.875499 | F35: =IFERROR(C35/G35,"")+$F$4 -> 0.3 | G35: =E35 -> 51.875499 | H35: =IF(G35="","",G35-C35-($F$4)*G35) -> 36.312849 | I35: =IF(G35="","",H35/G35) -> 0.7 | J35: =IF(G35="","",H35-G35*$C$1) -> 25.937749 | K35: =IFERROR(J35/G35,"") -> 0.5
A36: =A35+200 -> 710 | B36: EMPADA DE FRANGO ifood | C36: =C35 -> 13 | D36: 1 | E36: =C36/(1-$C$1-$C$2-$F$5) -> 100.77519 | F36: =IFERROR(C36/G36,"")+$F$5 -> 0.3 | G36: =E36 -> 100.77519 | H36: =IF(G36="","",G36-C36-($F$5)*G36) -> 70.542636 | I36: =IF(G36="","",H36/G36) -> 0.7 | J36: =IF(G36="","",H36-G36*$C$1) -> 50.387597 | K36: =IFERROR(J36/G36,"") -> 0.5
A37: =A35+400 -> 910 | B37: EMPADA DE FRANGO Quero | C37: =C35 -> 13 | D37: 1 | E37: =C37/(1-$C$1-$C$2-$F$6) -> 76.470588 | F37: =IFERROR(C37/G37,"")+$F$6 -> 0.3 | G37: =E37 -> 76.470588 | H37: =IF(G37="","",G37-C37-($F$6)*G37) -> 53.529412 | I37: =IF(G37="","",H37/G37) -> 0.7 | J37: =IF(G37="","",H37-G37*$C$1) -> 38.235294 | K37: =IFERROR(J37/G37,"") -> 0.5
A38: =A35+1 -> 511 | B38: QUICHE DE FRANGO | C38: ='QUICHE DE FRANGO'!C4:D4 -> 13 | D38: 1 | E38: =C38/(1-$C$1-$C$2-$F$4) -> 51.875499 | F38: =IFERROR(C38/G38,"")+$F$4 -> 0.3 | G38: =E38 -> 51.875499 | H38: =IF(G38="","",G38-C38-($F$4)*G38) -> 36.312849 | I38: =IF(G38="","",H38/G38) -> 0.7 | J38: =IF(G38="","",H38-G38*$C$1) -> 25.937749 | K38: =IFERROR(J38/G38,"") -> 0.5
A39: =A38+200 -> 711 | B39: QUICHE DE FRANGO ifood | C39: =C38 -> 13 | D39: 1 | E39: =C39/(1-$C$1-$C$2-$F$5) -> 100.77519 | F39: =IFERROR(C39/G39,"")+$F$5 -> 0.3 | G39: =E39 -> 100.77519 | H39: =IF(G39="","",G39-C39-($F$5)*G39) -> 70.542636 | I39: =IF(G39="","",H39/G39) -> 0.7 | J39: =IF(G39="","",H39-G39*$C$1) -> 50.387597 | K39: =IFERROR(J39/G39,"") -> 0.5
A40: =A38+400 -> 911 | B40: QUICHE DE FRANGO Quero | C40: =C38 -> 13 | D40: 1 | E40: =C40/(1-$C$1-$C$2-$F$6) -> 76.470588 | F40: =IFERROR(C40/G40,"")+$F$6 -> 0.3 | G40: =E40 -> 76.470588 | H40: =IF(G40="","",G40-C40-($F$6)*G40) -> 53.529412 | I40: =IF(G40="","",H40/G40) -> 0.7 | J40: =IF(G40="","",H40-G40*$C$1) -> 38.235294 | K40: =IFERROR(J40/G40,"") -> 0.5
A41: =A38+1 -> 512 | B41: QUICHE DE BACON | C41: ='QUICHE BACON'!C4:D4 -> 13 | D41: 1 | E41: =C41/(1-$C$1-$C$2-$F$4) -> 51.875499 | F41: =IFERROR(C41/G41,"")+$F$4 -> 0.3 | G41: =E41 -> 51.875499 | H41: =IF(G41="","",G41-C41-($F$4)*G41) -> 36.312849 | I41: =IF(G41="","",H41/G41) -> 0.7 | J41: =IF(G41="","",H41-G41*$C$1) -> 25.937749 | K41: =IFERROR(J41/G41,"") -> 0.5
A42: =A41+200 -> 712 | B42: QUICHE DE BACON ifood | C42: =C41 -> 13 | D42: 1 | E42: =C42/(1-$C$1-$C$2-$F$5) -> 100.77519 | F42: =IFERROR(C42/G42,"")+$F$5 -> 0.3 | G42: =E42 -> 100.77519 | H42: =IF(G42="","",G42-C42-($F$5)*G42) -> 70.542636 | I42: =IF(G42="","",H42/G42) -> 0.7 | J42: =IF(G42="","",H42-G42*$C$1) -> 50.387597 | K42: =IFERROR(J42/G42,"") -> 0.5
A43: =A41+400 -> 912 | B43: QUICHE DE BACON Quero | C43: =C41 -> 13 | D43: 1 | E43: =C43/(1-$C$1-$C$2-$F$6) -> 76.470588 | F43: =IFERROR(C43/G43,"")+$F$6 -> 0.3 | G43: =E43 -> 76.470588 | H43: =IF(G43="","",G43-C43-($F$6)*G43) -> 53.529412 | I43: =IF(G43="","",H43/G43) -> 0.7 | J43: =IF(G43="","",H43-G43*$C$1) -> 38.235294 | K43: =IFERROR(J43/G43,"") -> 0.5
A44: =A41+1 -> 513 | B44: CHARGE | C44: =CHARGE!C4 -> 13 | D44: 1 | E44: =C44/(1-$C$1-$C$2-$F$4) -> 51.875499 | F44: =IFERROR(C44/G44,"")+$F$4 -> 0.3 | G44: =E44 -> 51.875499 | H44: =IF(G44="","",G44-C44-($F$4)*G44) -> 36.312849 | I44: =IF(G44="","",H44/G44) -> 0.7 | J44: =IF(G44="","",H44-G44*$C$1) -> 25.937749 | K44: =IFERROR(J44/G44,"") -> 0.5
A45: =A44+200 -> 713 | B45: CHARGE ifood | C45: =C44 -> 13 | D45: 1 | E45: =C45/(1-$C$1-$C$2-$F$5) -> 100.77519 | F45: =IFERROR(C45/G45,"")+$F$5 -> 0.3 | G45: =E45 -> 100.77519 | H45: =IF(G45="","",G45-C45-($F$5)*G45) -> 70.542636 | I45: =IF(G45="","",H45/G45) -> 0.7 | J45: =IF(G45="","",H45-G45*$C$1) -> 50.387597 | K45: =IFERROR(J45/G45,"") -> 0.5
A46: =A44+400 -> 913 | B46: CHARGE Quero | C46: =C45 -> 13 | D46: 1 | E46: =C46/(1-$C$1-$C$2-$F$6) -> 76.470588 | F46: =IFERROR(C46/G46,"")+$F$6 -> 0.3 | G46: =E46 -> 76.470588 | H46: =IF(G46="","",G46-C46-($F$6)*G46) -> 53.529412 | I46: =IF(G46="","",H46/G46) -> 0.7 | J46: =IF(G46="","",H46-G46*$C$1) -> 38.235294 | K46: =IFERROR(J46/G46,"") -> 0.5
A47: =A44+1 -> 514 | B47: BISCOITINHO DE COCO | C47: ='BISCOITINHO DE COCO COM CANELA'!C4:D4 -> 13 | D47: 1 | E47: =C47/(1-$C$1-$C$2-$F$4) -> 51.875499 | F47: =IFERROR(C47/G47,"")+$F$4 -> 0.3 | G47: =E47 -> 51.875499 | H47: =IF(G47="","",G47-C47-($F$4)*G47) -> 36.312849 | I47: =IF(G47="","",H47/G47) -> 0.7 | J47: =IF(G47="","",H47-G47*$C$1) -> 25.937749 | K47: =IFERROR(J47/G47,"") -> 0.5
A48: =A47+200 -> 714 | B48: BISCOITINHO COCO ifood | C48: =C47 -> 13 | D48: 1 | E48: =C48/(1-$C$1-$C$2-$F$5) -> 100.77519 | F48: =IFERROR(C48/G48,"")+$F$5 -> 0.3 | G48: =E48 -> 100.77519 | H48: =IF(G48="","",G48-C48-($F$5)*G48) -> 70.542636 | I48: =IF(G48="","",H48/G48) -> 0.7 | J48: =IF(G48="","",H48-G48*$C$1) -> 50.387597 | K48: =IFERROR(J48/G48,"") -> 0.5
A49: =A47+400 -> 914 | B49: BISCOITINHO DE COCO Quero | C49: =C48 -> 13 | D49: 1 | E49: =C49/(1-$C$1-$C$2-$F$6) -> 76.470588 | F49: =IFERROR(C49/G49,"")+$F$6 -> 0.3 | G49: =E49 -> 76.470588 | H49: =IF(G49="","",G49-C49-($F$6)*G49) -> 53.529412 | I49: =IF(G49="","",H49/G49) -> 0.7 | J49: =IF(G49="","",H49-G49*$C$1) -> 38.235294 | K49: =IFERROR(J49/G49,"") -> 0.5
A50: =A47+1 -> 515 | B50: BISCOITINHO DE LIMÃO | C50: ='BISCOITINHO DE LIMÃO'!C4:D4 -> 13 | D50: 1 | E50: =C50/(1-$C$1-$C$2-$F$4) -> 51.875499 | F50: =IFERROR(C50/G50,"")+$F$4 -> 0.3 | G50: =E50 -> 51.875499 | H50: =IF(G50="","",G50-C50-($F$4)*G50) -> 36.312849 | I50: =IF(G50="","",H50/G50) -> 0.7 | J50: =IF(G50="","",H50-G50*$C$1) -> 25.937749 | K50: =IFERROR(J50/G50,"") -> 0.5
A51: =A50+200 -> 715 | B51: BISCOITINHOLIMÃO ifood | C51: =C50 -> 13 | D51: 1 | E51: =C51/(1-$C$1-$C$2-$F$5) -> 100.77519 | F51: =IFERROR(C51/G51,"")+$F$5 -> 0.3 | G51: =E51 -> 100.77519 | H51: =IF(G51="","",G51-C51-($F$5)*G51) -> 70.542636 | I51: =IF(G51="","",H51/G51) -> 0.7 | J51: =IF(G51="","",H51-G51*$C$1) -> 50.387597 | K51: =IFERROR(J51/G51,"") -> 0.5
A52: =A50+400 -> 915 | B52: BISCOITINHO LIMÃO Quero | C52: =C50 -> 13 | D52: 1 | E52: =C52/(1-$C$1-$C$2-$F$6) -> 76.470588 | F52: =IFERROR(C52/G52,"")+$F$6 -> 0.3 | G52: =E52 -> 76.470588 | H52: =IF(G52="","",G52-C52-($F$6)*G52) -> 53.529412 | I52: =IF(G52="","",H52/G52) -> 0.7 | J52: =IF(G52="","",H52-G52*$C$1) -> 38.235294 | K52: =IFERROR(J52/G52,"") -> 0.5
A53: =A50+1 -> 516 | B53: COOKIE | C53: =COOKIES!C4 -> 13 | D53: 1 | E53: =C53/(1-$C$1-$C$2-$F$4) -> 51.875499 | F53: =IFERROR(C53/G53,"")+$F$4 -> 0.3 | G53: =E53 -> 51.875499 | H53: =IF(G53="","",G53-C53-($F$4)*G53) -> 36.312849 | I53: =IF(G53="","",H53/G53) -> 0.7 | J53: =IF(G53="","",H53-G53*$C$1) -> 25.937749 | K53: =IFERROR(J53/G53,"") -> 0.5
A54: =A53+200 -> 716 | B54: COOKIE ifood | C54: =C53 -> 13 | D54: 1 | E54: =C54/(1-$C$1-$C$2-$F$5) -> 100.77519 | F54: =IFERROR(C54/G54,"")+$F$5 -> 0.3 | G54: =E54 -> 100.77519 | H54: =IF(G54="","",G54-C54-($F$5)*G54) -> 70.542636 | I54: =IF(G54="","",H54/G54) -> 0.7 | J54: =IF(G54="","",H54-G54*$C$1) -> 50.387597 | K54: =IFERROR(J54/G54,"") -> 0.5
A55: =A53+400 -> 916 | B55: COOKIE Quero | C55: =C53 -> 13 | D55: 1 | E55: =C55/(1-$C$1-$C$2-$F$6) -> 76.470588 | F55: =IFERROR(C55/G55,"")+$F$6 -> 0.3 | G55: =E55 -> 76.470588 | H55: =IF(G55="","",G55-C55-($F$6)*G55) -> 53.529412 | I55: =IF(G55="","",H55/G55) -> 0.7 | J55: =IF(G55="","",H55-G55*$C$1) -> 38.235294 | K55: =IFERROR(J55/G55,"") -> 0.5
A56: =A53+1 -> 517 | B56: PÃO DE FORMA | C56: ='PÃO DE FORMA'!C4:D4 -> 13 | D56: 1 | E56: =C56/(1-$C$1-$C$2-$F$4) -> 51.875499 | F56: =IFERROR(C56/G56,"")+$F$4 -> 0.3 | G56: =E56 -> 51.875499 | H56: =IF(G56="","",G56-C56-($F$4)*G56) -> 36.312849 | I56: =IF(G56="","",H56/G56) -> 0.7 | J56: =IF(G56="","",H56-G56*$C$1) -> 25.937749 | K56: =IFERROR(J56/G56,"") -> 0.5
A57: =A56+200 -> 717 | B57: PÃO DE FORMA ifood | C57: =C56 -> 13 | D57: 1 | E57: =C57/(1-$C$1-$C$2-$F$5) -> 100.77519 | F57: =IFERROR(C57/G57,"")+$F$5 -> 0.3 | G57: =E57 -> 100.77519 | H57: =IF(G57="","",G57-C57-($F$5)*G57) -> 70.542636 | I57: =IF(G57="","",H57/G57) -> 0.7 | J57: =IF(G57="","",H57-G57*$C$1) -> 50.387597 | K57: =IFERROR(J57/G57,"") -> 0.5
A58: =A56+400 -> 917 | B58: PÃO DE FORMA Quero | C58: =C56 -> 13 | D58: 1 | E58: =C58/(1-$C$1-$C$2-$F$6) -> 76.470588 | F58: =IFERROR(C58/G58,"")+$F$6 -> 0.3 | G58: =E58 -> 76.470588 | H58: =IF(G58="","",G58-C58-($F$6)*G58) -> 53.529412 | I58: =IF(G58="","",H58/G58) -> 0.7 | J58: =IF(G58="","",H58-G58*$C$1) -> 38.235294 | K58: =IFERROR(J58/G58,"") -> 0.5
A59: =A56+1 -> 518 | B59: GRANOLA | C59: =GRANOLA!C4 -> 13 | D59: 1 | E59: =C59/(1-$C$1-$C$2-$F$4) -> 51.875499 | F59: =IFERROR(C59/G59,"")+$F$4 -> 0.3 | G59: =E59 -> 51.875499 | H59: =IF(G59="","",G59-C59-($F$4)*G59) -> 36.312849 | I59: =IF(G59="","",H59/G59) -> 0.7 | J59: =IF(G59="","",H59-G59*$C$1) -> 25.937749 | K59: =IFERROR(J59/G59,"") -> 0.5
A60: =A59+200 -> 718 | B60: GRANOLA ifood | C60: =C59 -> 13 | D60: 1 | E60: =C60/(1-$C$1-$C$2-$F$5) -> 100.77519 | F60: =IFERROR(C60/G60,"")+$F$5 -> 0.3 | G60: =E60 -> 100.77519 | H60: =IF(G60="","",G60-C60-($F$5)*G60) -> 70.542636 | I60: =IF(G60="","",H60/G60) -> 0.7 | J60: =IF(G60="","",H60-G60*$C$1) -> 50.387597 | K60: =IFERROR(J60/G60,"") -> 0.5
A61: =A59+400 -> 918 | B61: GRANOLA Quero | C61: =C59 -> 13 | D61: 1 | E61: =C61/(1-$C$1-$C$2-$F$6) -> 76.470588 | F61: =IFERROR(C61/G61,"")+$F$6 -> 0.3 | G61: =E61 -> 76.470588 | H61: =IF(G61="","",G61-C61-($F$6)*G61) -> 53.529412 | I61: =IF(G61="","",H61/G61) -> 0.7 | J61: =IF(G61="","",H61-G61*$C$1) -> 38.235294 | K61: =IFERROR(J61/G61,"") -> 0.5
A62: =A59+1 -> 519 | B62: TORTINHA DE FRANGO | C62: ='TORTINHA DE FRANGO'!C4:D4 -> 13 | D62: 1 | E62: =C62/(1-$C$1-$C$2-$F$4) -> 51.875499 | F62: =IFERROR(C62/G62,"")+$F$4 -> 0.3 | G62: =E62 -> 51.875499 | H62: =IF(G62="","",G62-C62-($F$4)*G62) -> 36.312849 | I62: =IF(G62="","",H62/G62) -> 0.7 | J62: =IF(G62="","",H62-G62*$C$1) -> 25.937749 | K62: =IFERROR(J62/G62,"") -> 0.5
A63: =A62+200 -> 719 | B63: TORTINHA FRANGO ifood | C63: =C62 -> 13 | D63: 1 | E63: =C63/(1-$C$1-$C$2-$F$5) -> 100.77519 | F63: =IFERROR(C63/G63,"")+$F$5 -> 0.3 | G63: =E63 -> 100.77519 | H63: =IF(G63="","",G63-C63-($F$5)*G63) -> 70.542636 | I63: =IF(G63="","",H63/G63) -> 0.7 | J63: =IF(G63="","",H63-G63*$C$1) -> 50.387597 | K63: =IFERROR(J63/G63,"") -> 0.5
A64: =A62+400 -> 919 | B64: TORTINHA DE FRANGO Quero | C64: =C62 -> 13 | D64: 1 | E64: =C64/(1-$C$1-$C$2-$F$6) -> 76.470588 | F64: =IFERROR(C64/G64,"")+$F$6 -> 0.3 | G64: =E64 -> 76.470588 | H64: =IF(G64="","",G64-C64-($F$6)*G64) -> 53.529412 | I64: =IF(G64="","",H64/G64) -> 0.7 | J64: =IF(G64="","",H64-G64*$C$1) -> 38.235294 | K64: =IFERROR(J64/G64,"") -> 0.5
A65: =A62+1 -> 520 | B65: BOLO DE PRESTIGIO | C65: ='BOLO DE PRESTIGIO'!C4:D4 -> 13 | D65: 1 | E65: =C65/(1-$C$1-$C$2-$F$4) -> 51.875499 | F65: =IFERROR(C65/G65,"")+$F$4 -> 0.3 | G65: =E65 -> 51.875499 | H65: =IF(G65="","",G65-C65-($F$4)*G65) -> 36.312849 | I65: =IF(G65="","",H65/G65) -> 0.7 | J65: =IF(G65="","",H65-G65*($C$1)) -> 25.937749 | K65: =IFERROR(J65/G65,"") -> 0.5
A66: =A65+200 -> 720 | B66: BOLO DE PRESTIGIO ifood | C66: =C65 -> 13 | D66: 1 | E66: =C66/(1-$C$1-$C$2-$F$5) -> 100.77519 | F66: =IFERROR(C66/G66,"")+$F$5 -> 0.3 | G66: =E66 -> 100.77519 | H66: =IF(G66="","",G66-C66-($F$5)*G66) -> 70.542636 | I66: =IF(G66="","",H66/G66) -> 0.7 | J66: =IF(G66="","",H66-G66*$C$1) -> 50.387597 | K66: =IFERROR(J66/G66,"") -> 0.5
A67: =A65+400 -> 920 | B67: BOLO DE PRESTIGIO Quero | C67: =C65 -> 13 | D67: 1 | E67: =C67/(1-$C$1-$C$2-$F$6) -> 76.470588 | F67: =IFERROR(C67/G67,"")+$F$6 -> 0.3 | G67: =E67 -> 76.470588 | H67: =IF(G67="","",G67-C67-($F$6)*G67) -> 53.529412 | I67: =IF(G67="","",H67/G67) -> 0.7 | J67: =IF(G67="","",H67-G67*$C$1) -> 38.235294 | K67: =IFERROR(J67/G67,"") -> 0.5
A68: =A65+1 -> 521 | B68: TORTA SONHO VALSA | C68: ='TORTA SONHO DE VALSA'!C4:D4 -> 13 | D68: 1 | E68: =C68/(1-$C$1-$C$2-$F$4) -> 51.875499 | F68: =IFERROR(C68/G68,"")+$F$4 -> 0.3 | G68: =E68 -> 51.875499 | H68: =IF(G68="","",G68-C68-($F$4)*G68) -> 36.312849 | I68: =IF(G68="","",H68/G68) -> 0.7 | J68: =IF(G68="","",H68-G68*$C$1) -> 25.937749 | K68: =IFERROR(J68/G68,"") -> 0.5
A69: =A68+200 -> 721 | B69: TORTA SONHO VALSA ifood | C69: =C68 -> 13 | D69: 1 | E69: =C69/(1-$C$1-$C$2-$F$5) -> 100.77519 | F69: =IFERROR(C69/G69,"")+$F$5 -> 0.3 | G69: =E69 -> 100.77519 | H69: =IF(G69="","",G69-C69-($F$5)*G69) -> 70.542636 | I69: =IF(G69="","",H69/G69) -> 0.7 | J69: =IF(G69="","",H69-G69*$C$1) -> 50.387597 | K69: =IFERROR(J69/G69,"") -> 0.5
A70: =A68+400 -> 921 | B70: TORTA SONHO VALSA Quero | C70: =C68 -> 13 | D70: 1 | E70: =C70/(1-$C$1-$C$2-$F$6) -> 76.470588 | F70: =IFERROR(C70/G70,"")+$F$6 -> 0.3 | G70: =E70 -> 76.470588 | H70: =IF(G70="","",G70-C70-($F$6)*G70) -> 53.529412 | I70: =IF(G70="","",H70/G70) -> 0.7 | J70: =IF(G70="","",H70-G70*$C$1) -> 38.235294 | K70: =IFERROR(J70/G70,"") -> 0.5
A71: =A68+1 -> 522 | B71: NAKED P | C71: ='NAKED P'!C4:D4 -> 13 | D71: 1 | E71: =C71/(1-$C$1-$C$2-$F$4) -> 51.875499 | F71: =IFERROR(C71/G71,"")+$F$4 -> 0.3 | G71: =E71 -> 51.875499 | H71: =IF(G71="","",G71-C71-($F$4)*G71) -> 36.312849 | I71: =IF(G71="","",H71/G71) -> 0.7 | J71: =IF(G71="","",H71-G71*$C$1) -> 25.937749 | K71: =IFERROR(J71/G71,"") -> 0.5
A72: =A71+200 -> 722 | B72: NAKED P ifood | C72: =C71 -> 13 | D72: 1 | E72: =C72/(1-$C$1-$C$2-$F$5) -> 100.77519 | F72: =IFERROR(C72/G72,"")+$F$5 -> 0.3 | G72: =E72 -> 100.77519 | H72: =IF(G72="","",G72-C72-($F$5)*G72) -> 70.542636 | I72: =IF(G72="","",H72/G72) -> 0.7 | J72: =IF(G72="","",H72-G72*$C$1) -> 50.387597 | K72: =IFERROR(J72/G72,"") -> 0.5
A73: =A71+400 -> 922 | B73: NAKED P Quero | C73: =C71 -> 13 | D73: 1 | E73: =C73/(1-$C$1-$C$2-$F$6) -> 76.470588 | F73: =IFERROR(C73/G73,"")+$F$6 -> 0.3 | G73: =E73 -> 76.470588 | H73: =IF(G73="","",G73-C73-($F$6)*G73) -> 53.529412 | I73: =IF(G73="","",H73/G73) -> 0.7 | J73: =IF(G73="","",H73-G73*$C$1) -> 38.235294 | K73: =IFERROR(J73/G73,"") -> 0.5
A74: =A71+1 -> 523 | B74: NAKED M | C74: ='NAKED M'!C4:D4 -> 13 | D74: 1 | E74: =C74/(1-$C$1-$C$2-$F$4) -> 51.875499 | F74: =IFERROR(C74/G74,"")+$F$4 -> 0.3 | G74: =E74 -> 51.875499 | H74: =IF(G74="","",G74-C74-($F$4)*G74) -> 36.312849 | I74: =IF(G74="","",H74/G74) -> 0.7 | J74: =IF(G74="","",H74-G74*$C$1) -> 25.937749 | K74: =IFERROR(J74/G74,"") -> 0.5
A75: =A74+200 -> 723 | B75: NAKED M ifood | C75: =C74 -> 13 | D75: 1 | E75: =C75/(1-$C$1-$C$2-$F$5) -> 100.77519 | F75: =IFERROR(C75/G75,"")+$F$5 -> 0.3 | G75: =E75 -> 100.77519 | H75: =IF(G75="","",G75-C75-($F$5)*G75) -> 70.542636 | I75: =IF(G75="","",H75/G75) -> 0.7 | J75: =IF(G75="","",H75-G75*$C$1) -> 50.387597 | K75: =IFERROR(J75/G75,"") -> 0.5
A76: =A74+400 -> 923 | B76: NAKED M Quero | C76: =C75 -> 13 | D76: 1 | E76: =C76/(1-$C$1-$C$2-$F$6) -> 76.470588 | F76: =IFERROR(C76/G76,"")+$F$6 -> 0.3 | G76: =E76 -> 76.470588 | H76: =IF(G76="","",G76-C76-($F$6)*G76) -> 53.529412 | I76: =IF(G76="","",H76/G76) -> 0.7 | J76: =IF(G76="","",H76-G76*$C$1) -> 38.235294 | K76: =IFERROR(J76/G76,"") -> 0.5
A77: =A74+1 -> 524 | B77: NAKED G | C77: ='NAKED M'!C4:D4 -> 13 | D77: 1 | E77: =C77/(1-$C$1-$C$2-$F$4) -> 51.875499 | F77: =IFERROR(C77/G77,"")+$F$4 -> 0.3 | G77: =E77 -> 51.875499 | H77: =IF(G77="","",G77-C77-($F$4)*G77) -> 36.312849 | I77: =IF(G77="","",H77/G77) -> 0.7 | J77: =IF(G77="","",H77-G77*$C$1) -> 25.937749 | K77: =IFERROR(J77/G77,"") -> 0.5
A78: =A77+200 -> 724 | B78: NAKED G ifood | C78: =C77 -> 13 | D78: 1 | E78: =C78/(1-$C$1-$C$2-$F$5) -> 100.77519 | F78: =IFERROR(C78/G78,"")+$F$5 -> 0.3 | G78: =E78 -> 100.77519 | H78: =IF(G78="","",G78-C78-($F$5)*G78) -> 70.542636 | I78: =IF(G78="","",H78/G78) -> 0.7 | J78: =IF(G78="","",H78-G78*$C$1) -> 50.387597 | K78: =IFERROR(J78/G78,"") -> 0.5
A79: =A77+400 -> 924 | B79: NAKED G Quero | C79: =C77 -> 13 | D79: 1 | E79: =C79/(1-$C$1-$C$2-$F$6) -> 76.470588 | F79: =IFERROR(C79/G79,"")+$F$6 -> 0.3 | G79: =E79 -> 76.470588 | H79: =IF(G79="","",G79-C79-($F$6)*G79) -> 53.529412 | I79: =IF(G79="","",H79/G79) -> 0.7 | J79: =IF(G79="","",H79-G79*$C$1) -> 38.235294 | K79: =IFERROR(J79/G79,"") -> 0.5
A80: =A77+1 -> 525 | B80: PIZZA | C80: =PIZZA!C4 -> 13 | D80: 1 | E80: =C80/(1-$C$1-$C$2-$F$4) -> 51.875499 | F80: =IFERROR(C80/G80,"")+$F$4 -> 0.3 | G80: =E80 -> 51.875499 | H80: =IF(G80="","",G80-C80-($F$4)*G80) -> 36.312849 | I80: =IF(G80="","",H80/G80) -> 0.7 | J80: =IF(G80="","",H80-G80*$C$1) -> 25.937749 | K80: =IFERROR(J80/G80,"") -> 0.5
A81: =A80+200 -> 725 | B81: PIZZA ifood | C81: =C80 -> 13 | D81: 1 | E81: =C81/(1-$C$1-$C$2-$F$5) -> 100.77519 | F81: =IFERROR(C81/G81,"")+$F$5 -> 0.3 | G81: =E81 -> 100.77519 | H81: =IF(G81="","",G81-C81-($F$5)*G81) -> 70.542636 | I81: =IF(G81="","",H81/G81) -> 0.7 | J81: =IF(G81="","",H81-G81*$C$1) -> 50.387597 | K81: =IFERROR(J81/G81,"") -> 0.5
A82: =A80+400 -> 925 | B82: PIZZA Quero | C82: =C80 -> 13 | D82: 1 | E82: =C82/(1-$C$1-$C$2-$F$6) -> 76.470588 | F82: =IFERROR(C82/G82,"")+$F$6 -> 0.3 | G82: =E82 -> 76.470588 | H82: =IF(G82="","",G82-C82-($F$6)*G82) -> 53.529412 | I82: =IF(G82="","",H82/G82) -> 0.7 | J82: =IF(G82="","",H82-G82*$C$1) -> 38.235294 | K82: =IFERROR(J82/G82,"") -> 0.5
A83: =A80+1 -> 526 | B83: TARTELETE | C83: =TARTELETE!C4 -> 13 | D83: 1 | E83: =C83/(1-$C$1-$C$2-$F$4) -> 51.875499 | F83: =IFERROR(C83/G83,"")+$F$4 -> 0.3 | G83: =E83 -> 51.875499 | H83: =IF(G83="","",G83-C83-($F$4)*G83) -> 36.312849 | I83: =IF(G83="","",H83/G83) -> 0.7 | J83: =IF(G83="","",H83-G83*$C$1) -> 25.937749 | K83: =IFERROR(J83/G83,"") -> 0.5
A84: =A83+200 -> 726 | B84: TARTELETE ifood | C84: =C83 -> 13 | D84: 1 | E84: =C84/(1-$C$1-$C$2-$F$5) -> 100.77519 | F84: =IFERROR(C84/G84,"")+$F$5 -> 0.3 | G84: =E84 -> 100.77519 | H84: =IF(G84="","",G84-C84-($F$5)*G84) -> 70.542636 | I84: =IF(G84="","",H84/G84) -> 0.7 | J84: =IF(G84="","",H84-G84*$C$1) -> 50.387597 | K84: =IFERROR(J84/G84,"") -> 0.5
A85: =A83+400 -> 926 | B85: TARTELETE Quero | C85: =C83 -> 13 | D85: 1 | E85: =C85/(1-$C$1-$C$2-$F$6) -> 76.470588 | F85: =IFERROR(C85/G85,"")+$F$6 -> 0.3 | G85: =E85 -> 76.470588 | H85: =IF(G85="","",G85-C85-($F$6)*G85) -> 53.529412 | I85: =IF(G85="","",H85/G85) -> 0.7 | J85: =IF(G85="","",H85-G85*$C$1) -> 38.235294 | K85: =IFERROR(J85/G85,"") -> 0.5
A86: =A83+1 -> 527 | B86: MINI VULCÃO | C86: ='MINI VULCÃO'!C4:D4 -> 13 | D86: 1 | E86: =C86/(1-$C$1-$C$2-$F$4) -> 51.875499 | F86: =IFERROR(C86/G86,"")+$F$4 -> 0.3 | G86: =E86 -> 51.875499 | H86: =IF(G86="","",G86-C86-($F$4)*G86) -> 36.312849 | I86: =IF(G86="","",H86/G86) -> 0.7 | J86: =IF(G86="","",H86-G86*$C$1) -> 25.937749 | K86: =IFERROR(J86/G86,"") -> 0.5
A87: =A86+200 -> 727 | B87: MINI VULCÃO ifood | C87: =C86 -> 13 | D87: 1 | E87: =C87/(1-$C$1-$C$2-$F$5) -> 100.77519 | F87: =IFERROR(C87/G87,"")+$F$5 -> 0.3 | G87: =E87 -> 100.77519 | H87: =IF(G87="","",G87-C87-($F$5)*G87) -> 70.542636 | I87: =IF(G87="","",H87/G87) -> 0.7 | J87: =IF(G87="","",H87-G87*$C$1) -> 50.387597 | K87: =IFERROR(J87/G87,"") -> 0.5
A88: =A86+400 -> 927 | B88: MINI VULCÃO Quero | C88: =C86 -> 13 | D88: 1 | E88: =C88/(1-$C$1-$C$2-$F$6) -> 76.470588 | F88: =IFERROR(C88/G88,"")+$F$6 -> 0.3 | G88: =E88 -> 76.470588 | H88: =IF(G88="","",G88-C88-($F$6)*G88) -> 53.529412 | I88: =IF(G88="","",H88/G88) -> 0.7 | J88: =IF(G88="","",H88-G88*$C$1) -> 38.235294 | K88: =IFERROR(J88/G88,"") -> 0.5
A89: 528 | B89: Barra de CHOCOLATE | C89: ='BARRA DE CHOCOLATE'!E1 -> 0.21538462 | D89: 1 | E89: =C89/(1-$C$1-$C$2-$F$4) -> 0.85947572 | F89: =IFERROR(C89/G89,"")+$F$4 -> 0.3 | G89: =E89 -> 0.85947572 | H89: =IF(G89="","",G89-C89-($F$4)*G89) -> 0.601633 | I89: =IF(G89="","",H89/G89) -> 0.7 | J89: =IF(G89="","",H89-G89*$C$1) -> 0.42973786 | K89: =IFERROR(J89/G89,"") -> 0.5
A90: =A89+200 -> 728 | B90: Barra de CHOCOLATE ifood | C90: =C89 -> 0.21538462 | D90: 1 | E90: =C90/(1-$C$1-$C$2-$F$5) -> 1.6696482 | F90: =IFERROR(C90/G90,"")+$F$5 -> 0.3 | G90: =E90 -> 1.6696482 | H90: =IF(G90="","",G90-C90-($F$5)*G90) -> 1.1687537 | I90: =IF(G90="","",H90/G90) -> 0.7 | J90: =IF(G90="","",H90-G90*$C$1) -> 0.83482409 | K90: =IFERROR(J90/G90,"") -> 0.5
A91: =A89+400 -> 928 | B91: Barra de CHOCOLATE Quero | C91: =C89 -> 0.21538462 | D91: 1 | E91: =C91/(1-$C$1-$C$2-$F$6) -> 1.2669683 | F91: =IFERROR(C91/G91,"")+$F$6 -> 0.3 | G91: =E91 -> 1.2669683 | H91: =IF(G91="","",G91-C91-($F$6)*G91) -> 0.88687783 | I91: =IF(G91="","",H91/G91) -> 0.7 | J91: =IF(G91="","",H91-G91*$C$1) -> 0.63348416 | K91: =IFERROR(J91/G91,"") -> 0.5
A92: =A89+1 -> 529 | B92: Produto NOVO | F92: =IFERROR(C92/G92,"") | H92: =IF(G92="","",G92-C92-($F$4)*G92) | I92: =IF(G92="","",H92/G92) | J92: =IF(G92="","",H92-G92*$C$1) | K92: =IFERROR(J92/G92,"")
A93: =A90+1 -> 729 | F93: =IFERROR(C93/G93,"") | H93: =IF(G93="","",G93-C93-($F$4)*G93) | I93: =IF(G93="","",H93/G93) | J93: =IF(G93="","",H93-G93*$C$1) | K93: =IFERROR(J93/G93,"")
A94: =A91+1 -> 929 | F94: =IFERROR(C94/G94,"") | H94: =IF(G94="","",G94-C94-($F$4)*G94) | I94: =IF(G94="","",H94/G94) | J94: =IF(G94="","",H94-G94*$C$1) | K94: =IFERROR(J94/G94,"")
A95: =A92+1 -> 530 | F95: =IFERROR(C95/G95,"") | H95: =IF(G95="","",G95-C95-($F$4)*G95) | I95: =IF(G95="","",H95/G95) | J95: =IF(G95="","",H95-G95*$C$1) | K95: =IFERROR(J95/G95,"")
A96: =A93+1 -> 730 | F96: =IFERROR(C96/G96,"") | H96: =IF(G96="","",G96-C96-($F$4)*G96) | I96: =IF(G96="","",H96/G96) | J96: =IF(G96="","",H96-G96*$C$1) | K96: =IFERROR(J96/G96,"")
A97: =A94+1 -> 930 | F97: =IFERROR(C97/G97,"") | H97: =IF(G97="","",G97-C97-($F$4)*G97) | I97: =IF(G97="","",H97/G97) | J97: =IF(G97="","",H97-G97*$C$1) | K97: =IFERROR(J97/G97,"")
A98: =A95+1 -> 531 | F98: =IFERROR(C98/G98,"") | H98: =IF(G98="","",G98-C98-($F$4)*G98) | I98: =IF(G98="","",H98/G98) | J98: =IF(G98="","",H98-G98*$C$1) | K98: =IFERROR(J98/G98,"")
A99: =A96+1 -> 731 | F99: =IFERROR(C99/G99,"") | H99: =IF(G99="","",G99-C99-($F$4)*G99) | I99: =IF(G99="","",H99/G99) | J99: =IF(G99="","",H99-G99*$C$1) | K99: =IFERROR(J99/G99,"")
A100: =A97+1 -> 931 | F100: =IFERROR(C100/G100,"") | H100: =IF(G100="","",G100-C100-($F$4)*G100) | I100: =IF(G100="","",H100/G100) | J100: =IF(G100="","",H100-G100*$C$1) | K100: =IFERROR(J100/G100,"")
...

Sheet ListaIngredientes
A1: Objetivo | C1: Lista de I N G R E D I E N T E S
A2: Data de atualização | C2: 44281 | E2: Qt | F2: =COUNT(Tabela2[Cod]) -> 155
A4: Cod | B4: Descrição do Produto | C4: unidade | D4: fração | E4: Preço | F4: Preço por(g)
A5: 102 | B5: Ovos Branco | C5: duzia | D5: 12 | E5: 20 | F5: =IFERROR(E5/D5,"") -> 1.6666667
A6: =A5+1 -> 103 | B6: Leite condensado | C6: ml | D6: 400 | E6: 18 | F6: =IFERROR(E6/D6,"") -> 0.045
A7: =A6+1 -> 104 | B7: Leite Integral | C7: ml | D7: 1000 | E7: 12 | F7: =IFERROR(E7/D7,"") -> 0.012
A8: =A7+1 -> 105 | B8: Bananas | C8: duzias | D8: 12 | E8: 6 | F8: =IFERROR(E8/D8,"") -> 0.5
A9: =A8+1 -> 106 | B9: Colorau | C9: g | D9: 100 | E9: 2 | F9: =IFERROR(E9/D9,"") -> 0.02
A10: =A9+1 -> 107 | B10: Agua mineral | C10: ml | D10: 500 | E10: 23.45 | F10: =IFERROR(E10/D10,"") -> 0.0469
A11: =A10+1 -> 108 | B11: CANELA | C11: KG | D11: 1000 | E11: 55 | F11: 0.055
A12: =A11+1 -> 109 | B12: CASTANHA DO PARÁ | C12: KG | D12: 1000 | E12: 35 | F12: =IFERROR(E12/D12,"") -> 0.035
A13: =A12+1 -> 110 | B13: CASTANHA DE CAJU | C13: KG | D13: 1000 | E13: 35 | F13: =IFERROR(E13/D13,"") -> 0.035
A14: =A13+1 -> 111 | B14: azeite | C14: ml | D14: 500 | E14: 23 | F14: =IFERROR(E14/D14,"") -> 0.046
A15: =A14+1 -> 112 | B15: farinha de arroz | C15: kg | D15: 1000 | E15: 12 | F15: =IFERROR(E15/D15,"") -> 0.012
A16: =A15+1 -> 113 | B16: polvilho doce | C16: kg | D16: 1000 | E16: 10 | F16: =IFERROR(E16/D16,"") -> 0.01
A17: =A16+1 -> 114 | B17: fecula | C17: kg | D17: 1000 | E17: 10 | F17: 0.01 | J17: =J16+1 -> 1 | K17: CAIXA MEIO OVO 100G | L17: U | M17: 1 | N17: 6.19 | O17: =IFERROR(N17/M17,"") -> 6.19
A18: =A17+1 -> 115 | B18: CAMARÃO | C18: KG | D18: 1000 | E18: 65 | F18: 0.065 | J18: CAIXA OVO 100G | K18: u | L18: 30 | M18: 5.8 | N18: =IFERROR(M18/L18,"") -> 0.19333333
A19: =A18+1 -> 116 | B19: CARNE SECA | C19: KG | D19: 500 | E19: 27.5 | F19: 0.027 | J19: caixa ovo de colher | K19: u | L19: 1 | M19: 5.19 | N19: 5.19
A20: =A19+1 -> 117 | B20: BANANA DA TERRA | C20: U | D20: 1 | E20: 1 | F20: 1 | J20: caixa ovo de colher | K20: u | L20: 2 | M20: 5.19
A21: =A20+1 -> 118 | B21: QUEIJO MUSSARELA 0 LACTOSE | C21: KG | D21: 1000 | E21: 49.9 | F21: 0.049 | J21: caixa ovo duplo | K21: u | L21: 3 | M21: 4.79 | N21: =IFERROR(M21/L21,"") -> 1.5966667
A22: =A21+1 -> 119 | B22: berinjela | C22: u | D22: 3 | E22: 5 | F22: 1.66 | J22: caixa ovo trio | K22: u | L22: 1 | M22: 4.05 | N22: =IFERROR(M22/L22,"") -> 4.05
A23: =A22+1 -> 120 | B23: embalagem lasanha | C23: u | D23: 5 | E23: 2.65 | F23: 0.53 | J23: caixa tie dye | K23: u | L23: 1 | M23: 5.19 | N23: 5.19
A24: =A23+1 -> 121 | B24: embalagem marmita | C24: u | D24: 25 | E24: 23.5 | F24: 0.94 | J24: cesta grande | K24: u | L24: 2 | M24: 6.49 | N24: 12.98
A25: =A24+1 -> 122 | B25: CARNE PATINHO | C25: KG | D25: 1000 | E25: 33 | F25: 0.033 | J25: cesta madeira | K25: u | L25: 1 | M25: 22 | N25: =IFERROR(M25/L25,"") -> 22
A26: =A25+1 -> 123 | B26: BANANA PRATA | C26: U | D26: 4 | E26: 2 | F26: 0.5 | J26: coelho pelucia | K26: u | L26: 1 | M26: 16.9 | N26: =IFERROR(M26/L26,"") -> 16.9
A27: =A26+1 -> 124 | B27: BACON | C27: KG | D27: 1000 | E27: 31.9 | F27: =IFERROR(E27/D27,"") -> 0.0319 | J27: coelho pelucia | K27: u | L27: 1 | M27: 22.9 | N27: =IFERROR(M27/L27,"") -> 22.9
A28: =A27+1 -> 125 | J28: cx encanto | K28: u | L28: 1 | M28: 6.67 | N28: =IFERROR(M28/L28,"") -> 6.67
A29: =A28+1 -> 126 | B29: CHOCOLTE BRANCO | C29: KG | D29: 1000 | E29: 159.9 | F29: 0.159 | J29: cx gourmet ovo | K29: u | L29: 4 | M29: 4.39 | N29: =IFERROR(M29/L29,"") -> 1.0975
A30: =A29+1 -> 127 | B30: CHOCOLATE 70% | C30: KG | D30: 1000 | E30: 102 | F30: =IFERROR(E30/D30,"") -> 0.102 | J30: fita espuma | K30: u | L30: 1 | M30: 5.7 | N30: =IFERROR(M30/L30,"") -> 5.7
A31: =A30+1 -> 128 | B31: coco fino | C31: kg | D31: 1000 | E31: 40 | F31: =IFERROR(E31/D31,"") -> 0.04 | J31: fita tnt | K31: u | L31: 1 | M31: 6.89 | N31: 6.89
A32: =A31+1 -> 129 | B32: coco flococo | C32: kg | D32: 100 | E32: 3.99 | F32: =IFERROR(E32/D32,"") -> 0.0399 | J32: folha chumbo | K32: u | L32: 1 | M32: 1.05 | N32: =IFERROR(M32/L32,"") -> 1.05
A33: =A32+1 -> 130 | J33: forma coelho | K33: u | L33: 1 | M33: 5.49 | N33: 5.49
A34: =A33+1 -> 131 | J34: kit de bico | K34: u | L34: 1 | M34: 9.9 | N34: =IFERROR(M34/L34,"") -> 9.9
A35: =A34+1 -> 132 | B35: copo açaí | C35: u | D35: 50 | E35: 8.49 | F35: =IFERROR(E35/D35,"") -> 0.1698 | J35: LATA PALHA ITALIANA | K35: U | L35: 1 | M35: 1.59 | N35: =IFERROR(M35/L35,"") -> 1.59
A36: =A35+1 -> 133 | B36: suporte para torta | C36: u | D36: 1 | E36: 4 | F36: 4 | J36: lata pra ovo | K36: u | L36: 1 | M36: 9.39 | N36: 9.39
A37: =A36+1 -> 134 | B37: copo bolha | C37: u | D37: 10 | E37: 8.49 | F37: =IFERROR(E37/D37,"") -> 0.849 | J37: mine colher | K37: pct | L37: 1 | M37: 8.39 | N37: =IFERROR(M37/L37,"") -> 8.39
A38: =A37+1 -> 135 | B38: ISOPOR DE PIZZA REDONDA | C38: u | D38: 10 | E38: 2.99 | F38: 0.29 | J38: ninho coelho | K38: u | L38: 2 | M38: 4.99 | N38: 9.98
A39: =A38+1 -> 136 | B39: embalagem retangular torta g630 | C39: u | D39: 10 | E39: 8.9 | F39: =IFERROR(E39/D39,"") -> 0.89 | J39: panelinha | K39: pc | L39: 1 | M39: 10.15 | N39: =IFERROR(M39/L39,"") -> 10.15
A40: =A39+1 -> 137 | B40: copo quadrado brigadeiro duo | C40: u | D40: 10 | E40: 5.89 | F40: 0.58 | J40: papel glasspel | K40: u | L40: 1 | M40: 2.99 | N40: 2.99
A41: =A40+1 -> 138 | B41: CHIPS DE COCO | C41: KG | D41: 1000 | E41: 65 | F41: =IFERROR(E41/D41,"") -> 0.065 | J41: papel manteiga | K41: u | L41: 1 | M41: 4.59 | N41: 4.59
A42: =A41+1 -> 139 | B42: cravo da india | C42: g | D42: 1700 | E42: 1 | F42: =IFERROR(E42/D42,"") -> 0.00058823529 | J42: papel toalha | K42: u | L42: 1 | M42: 3.99 | N42: 3.99
A43: =A42+1 -> 140 | B43: creme de leite italac 17% | C43: kg | D43: 200 | E43: 3.39 | F43: =IFERROR(E43/D43,"") -> 0.01695 | J43: pazinha concha | K43: pc | L43: 1 | M43: 7.2 | N43: =IFERROR(M43/L43,"") -> 7.2
A44: =A43+1 -> 141 | B44: creme de leite piracanjuba | C44: kg | D44: 200 | E44: 2.75 | F44: =IFERROR(E44/D44,"") -> 0.01375
A45: =A44+1 -> 142 | B45: embalagem galvanatec g32 | C45: u | D45: 10 | E45: 0.9 | F45: =IFERROR(E45/D45,"") -> 0.09
A46: =A45+1 -> 143
A47: =A46+1 -> 144 | B47: DAMASCO | C47: KG | D47: 1000 | E47: 50 | F47: =IFERROR(E47/D47,"") -> 0.05
A48: =A47+1 -> 145 | B48: embalagem 645 empada | C48: u | D48: 10 | E48: 2 | F48: =IFERROR(E48/D48,"") -> 0.2
A49: =A48+1 -> 146 | B49: embalagem bolo de pote | C49: u | D49: 10 | E49: 5.99 | F49: =IFERROR(E49/D49,"") -> 0.599
A50: =A49+1 -> 147 | F50: =IFERROR(E50/D50,"")
A51: =A50+1 -> 148 | B51: embalagem bolo gelado 650 | C51: u | D51: 10 | E51: 2.5 | F51: =IFERROR(E51/D51,"") -> 0.25
A52: =A51+1 -> 149 | B52: embalagem caldo 350ml | C52: u | D52: 25 | E52: 18 | F52: =IFERROR(E52/D52,"") -> 0.72
A53: =A52+1 -> 150 | B53: embalagem doce de leite | C53: u | D53: 10 | E53: 3.99 | F53: =IFERROR(E53/D53,"") -> 0.399
A54: =A53+1 -> 151 | B54: embalagem doce de leite 645d | C54: u | D54: 10 | E54: 3.65 | F54: =IFERROR(E54/D54,"") -> 0.365
A55: =A54+1 -> 152 | B55: EMBALAGEM GALVANOTEC 650 | C55: u | D55: 9 | E55: 5.31 | F55: =IFERROR(E55/D55,"") -> 0.59
A56: =A55+1 -> 153 | B56: embalagem GALVANOTEC G14 | C56: g | D56: 52 | E56: 7.23 | F56: =IFERROR(E56/D56,"") -> 0.13903846
A57: =A56+1 -> 154 | B57: embalagem GALVANOTEC G645 | C57: u | D57: 20 | E57: 16 | F57: =IFERROR(E57/D57,"") -> 0.8
A58: =A57+1 -> 155 | B58: embalagem panqueca ga08 | C58: u | D58: 10 | E58: 2.49 | F58: =IFERROR(E58/D58,"") -> 0.249
A59: =A58+1 -> 156 | B59: embalagem quiche | C59: u | D59: 10 | E59: 5.99 | F59: =IFERROR(E59/D59,"") -> 0.599
A60: =A59+1 -> 157 | B60: embalagem redonda g640 | C60: u | D60: 10 | E60: 2 | F60: =IFERROR(E60/D60,"") -> 0.2
A61: =A60+1 -> 158 | B61: ESSENCIA DE BAUNILHA | C61: ML | D61: 30 | E61: 2.99 | F61: =IFERROR(E61/D61,"") -> 0.099666667
A62: =A61+1 -> 159 | B62: essencia de mel | C62: u | D62: 1 | E62: 2.59 | F62: =IFERROR(E62/D62,"") -> 2.59
... A67: =A66+1 -> 164 | B67: FRANGO | C67: kg | D67: 1000 | E67: 12 | F67: =IFERROR(E67/D67,"") -> 0.012
A68: =A67+1 -> 165 | B68: fermento químico | C68: kg | D68: 250 | E68: 6.65 | F68: 0.025
A69: =A68+1 -> 166 | B69: QUEIJO MINAS 0 LACTOSE | C69: KG | D69: 300 | E69: 28 | F69: 0.093
A70: =A69+1 -> 167 | B70: SUPORTE DO BOLO NAKED PP | C70: U | D70: 1 | E70: 2.89 | F70: 2.89
A71: =A70+1 -> 168
A72: =A71+1 -> 169
A73: =A72+1 -> 170
A74: =A73+1 -> 171
A75: =A74+1 -> 172
A76: =A75+1 -> 173
A77: =A76+1 -> 174 | B77: Galvanatec 679 | C77: u | D77: 10 | E77: 8 | F77: =IFERROR(E77/D77,"") -> 0.8
A78: =A77+1 -> 175 | B78: forma pudim | C78: u | D78: 10 | E78: 9.79 | F78: 9.79
A79: =A78+1 -> 176 | B79: forminha de brigadeiro | C79: u | D79: 100 | E79: 2.15 | F79: =IFERROR(E79/D79,"") -> 0.0215
A80: =A79+1 -> 177 | B80: forminha jab branca | C80: ct | D80: 2 | E80: 1.6 | F80: =IFERROR(E80/D80,"") -> 0.8
A81: =A80+1 -> 178 | B81: fundo decorado | C81: U | D81: 100 | E81: 1.5 | F81: =IFERROR(E81/D81,"") -> 0.015
A82: =A81+1 -> 179 | B82: GALVANATEC G679 | C82: kg | D82: 1000 | E82: 17.3 | F82: =IFERROR(E82/D82,"") -> 0.0173
A83: =A82+1 -> 180 | B83: GALVANATEC G742 | C83: U | E83: 3.99 | F83: =IFERROR(E83/D83,"")
A84: =A83+1 -> 181 | B84: garrafa de suco | C84: u | D84: 1 | E84: 0.65 | F84: =IFERROR(E84/D84,"") -> 0.65
A85: =A84+1 -> 182 | B85: GERGILIM | C85: KG | D85: 1000 | E85: 29 | F85: =IFERROR(E85/D85,"") -> 0.029
A86: =A85+1 -> 183 | B86: gelatina sem sabor | C86: u | D86: 2 | E86: 5.05 | F86: 5.05
A87: =A86+1 -> 184 | B87: goma xantana | C87: kg | D87: 1000 | E87: 55 | F87: =IFERROR(E87/D87,"") -> 0.055
A88: =A87+1 -> 185 | B88: GRANBERRY | C88: KG | D88: 70 | E88: 3.5 | F88: =IFERROR(E88/D88,"") -> 0.05
A89: =A88+1 -> 186 | B89: Iogurte natural | C89: g | D89: 170 | E89: 2.79 | F89: =IFERROR(E89/D89,"") -> 0.016411765
A90: =A89+1 -> 187
A91: =A90+1 -> 188 | B91: LATA PALHA ITALIANA | C91: U | D91: 1 | E91: 1.59 | F91: =IFERROR(E91/D91,"") -> 1.59
A92: =A91+1 -> 189 | B92: lata pra ovo | C92: u | D92: 1 | E92: 9.39 | F92: 9.39
A93: =A92+1 -> 190 | B93: Leite de coco | C93: ml | D93: 200 | E93: 0.87 | F93: =IFERROR(E93/D93,"") -> 0.00435
A94: =A93+1 -> 191 | B94: leite de coco em po | C94: kg | D94: 1000 | E94: 79.9 | F94: =IFERROR(E94/D94,"") -> 0.0799
A95: =A94+1 -> 192 | B95: Leite Desnatado | C95: ml | D95: 500 | E95: 43.47 | F95: =IFERROR(E95/D95,"") -> 0.08694
A96: =A95+1 -> 193 | B96: LIMÃO | C96: U | D96: 10 | E96: 5 | F96: =IFERROR(E96/D96,"") -> 0.5
A97: =A96+1 -> 194 | B97: Maçã | C97: kg | D97: 1000 | E97: 3.99 | F97: =IFERROR(E97/D97,"") -> 0.00399
A98: =A97+1 -> 195 | B98: Macaxeira | C98: kg | D98: 1000 | E98: 5 | F98: =IFERROR(E98/D98,"") -> 0.005
A99: =A98+1 -> 196 | B99: Manteiga GHEE | C99: kg | D99: 3000 | E99: 190 | F99: =IFERROR(E99/D99,"") -> 0.063333333
A100: =A99+1 -> 197 | B100: Mel | C100: kg | D100: 3000 | E100: 189 | F100: =IFERROR(E100/D100,"") -> 0.063
A101: =A100+1 -> 198 | B101: Milho | C101: L | D101: 1400 | E101: 38 | F101: =IFERROR(E101/D101,"") -> 0.027142857
A102: =A101+1 -> 199
A103: =A102+1 -> 200 | B103: MIRTILO | C103: u | D103: 2 | E103: 5 | F103: =IFERROR(E103/D103,"") -> 2.5
A104: =A103+1 -> 201 | B104: MORANGO | C104: kg | D104: 1000 | E104: 17.3 | F104: =IFERROR(E104/D104,"") -> 0.0173
A105: =A104+1 -> 202
...

Sheet Violino
A1: cod | B1: 501 | C1: =VLOOKUP(B1,PRODUTOS!$A$7:$E$204,2,FALSE) -> P A S T E L | E1: =C3 -> 4.7896 | G1: SOBREMESA/DOCE | J1: 1ª PARTE - CALCULAR O TOTAL DO CUSTO | P1: C U S T O
A2: Despesas Fixas/Variáveis | C2: =L10+L11 -> 0.2 | E2: Preço Venda Unit | G2: =IFERROR(C3/(1-C2-C5),"") -> 9.5792
A3: Custo Unitário | C3: =IFERROR(C7/C4,"") -> 4.7896 | E3: Luro s/Venda | G3: =G2*C5 -> 2.87376
A4: Quantidade Produzida | C4: 6 | E4: Preço Concorrencia | G4: =G2 -> 9.5792 | L4: =C7 -> 28.7376
A5: Lucro s/Venda | C5: =L12 -> 0.3 | E5: Lucro Praticado | G5: =1-C3/G4-C2 -> 0.3 | J5: INFORMAR QUNATAS UNIDADES SERÃO PRODUZIDAS
A6: Preço ZERO | E6: =C3/(1-C2) -> 5.987
A7: Gasto Total | C7: =H29 -> 28.7376 | E7: Lucro Praticado | G7: =G5*G4 -> 2.87376 | L7: =C4 -> 6
A8: cod Prod | B8: Descrição ingredientes | D8: unid | E8: quantiadade | F8: valor $ | H8: Subtotal | J8: CALCULAR O CUSTO UNITÁRIO DE CADA PASTEL
A9: 102 | B9: =IFERROR(VLOOKUP(A9,ListaIngredientes!$A$5:$F$155,2,FALSE),"") -> Ovos Branco | D9: =IFERROR(VLOOKUP(A9,Tabela2[],3,FALSE),"") -> duzia | E9: 12 | F9: =IFERROR(VLOOKUP(A9,ListaIngredientes!$A$5:$F$155,6,FALSE),"") -> 1.6666667 | H9: =IFERROR(E9*F9,"") -> 20 | L9: =L4/L7 -> 4.7896
A10: 103 | B10: =IFERROR(VLOOKUP(A10,ListaIngredientes!$A$5:$F$155,2,FALSE),"") -> Leite condensado | D10: =IFERROR(VLOOKUP(A10,Tabela2[],3,FALSE),"") -> ml | E10: 50 | F10: =IFERROR(VLOOKUP(A10,ListaIngredientes!$A$5:$F$155,6,FALSE),"") -> 0.045 | H10: =IFERROR(E10*F10,"") -> 2.25 | J10: Despesas Fixas | L10: 0.12 | M10: O sistema gestão do preço calcula, através dos parâmateros feitos por SANDRO
A11: 104 | B11: =IFERROR(VLOOKUP(A11,ListaIngredientes!$A$5:$F$155,2,FALSE),"") -> Leite Integral | D11: =IFERROR(VLOOKUP(A11,Tabela2[],3,FALSE),"") -> ml | E11: 225 | F11: =IFERROR(VLOOKUP(A11,ListaIngredientes!$A$5:$F$155,6,FALSE),"") -> 0.012 | H11: =IFERROR(E11*F11,"") -> 2.7 | J11: Despesas Variáves | L11: 0.08
A12: 105 | B12: =IFERROR(VLOOKUP(A12,ListaIngredientes!$A$5:$F$155,2,FALSE),"") -> Bananas | D12: =IFERROR(VLOOKUP(A12,Tabela2[],3,FALSE),"") -> duzias | E12: 6 | F12: =IFERROR(VLOOKUP(A12,ListaIngredientes!$A$5:$F$155,6,FALSE),"") -> 0.5 | H12: =IFERROR(E12*F12,"") -> 3 | J12: lucro | L12: 0.3 | M12: Este varia
A13: 106 | B13: =IFERROR(VLOOKUP(A13,ListaIngredientes!$A$5:$F$155,2,FALSE),"") -> Colorau | D13: =IFERROR(VLOOKUP(A13,Tabela2[],3,FALSE),"") -> g | E13: 30 | F13: =IFERROR(VLOOKUP(A13,ListaIngredientes!$A$5:$F$155,6,FALSE),"") -> 0.02 | H13: =IFERROR(E13*F13,"") -> 0.6 | J13: soma | L13: =SUM(L10:L12) -> 0.5
A14: 107 | B14: =IFERROR(VLOOKUP(A14,ListaIngredientes!$A$5:$F$155,2,FALSE),"") -> Agua mineral | D14: =IFERROR(VLOOKUP(A14,Tabela2[],3,FALSE),"") -> ml | E14: 4 | F14: =IFERROR(VLOOKUP(A14,ListaIngredientes!$A$5:$F$155,6,FALSE),"") -> 0.0469 | H14: =IFERROR(E14*F14,"") -> 0.1876 | J14: Cálculo do Preço de Venda
B15: =IFERROR(VLOOKUP(A15,ListaIngredientes!$A$5:$F$155,2,FALSE),"") | D15: =IFERROR(VLOOKUP(A15,Tabela2[],3,FALSE),"") | F15: =IFERROR(VLOOKUP(A15,ListaIngredientes!$A$5:$F$155,6,FALSE),"") | H15: =IFERROR(E15*F15,"")
B16: =IFERROR(VLOOKUP(A16,ListaIngredientes!$A$5:$F$155,2,FALSE),"") | D16: =IFERROR(VLOOKUP(A16,Tabela2[],3,FALSE),"") | F16: =IFERROR(VLOOKUP(A16,ListaIngredientes!$A$5:$F$155,6,FALSE),"") | H16: =IFERROR(E16*F16,"") | J16: fórmula | K16: =preco custo/(1-soma)
B17: =IFERROR(VLOOKUP(A17,ListaIngredientes!$A$5:$F$155,2,FALSE),"") | D17: =IFERROR(VLOOKUP(A17,Tabela2[],3,FALSE),"") | F17: =IFERROR(VLOOKUP(A17,ListaIngredientes!$A$5:$F$155,6,FALSE),"") | H17: =IFERROR(E17*F17,"") | K17: =L9/(1-L13) -> 9.5792 | O17: C=preço de custo
B18: =IFERROR(VLOOKUP(A18,ListaIngredientes!$A$5:$F$155,2,FALSE),"") | D18: =IFERROR(VLOOKUP(A18,Tabela2[],3,FALSE),"") | F18: =IFERROR(VLOOKUP(A18,ListaIngredientes!$A$5:$F$155,6,FALSE),"") | H18: =IFERROR(E18*F18,"") | J18: sonhos de ediberto | O18: V= preço da venda conc
B19: =IFERROR(VLOOKUP(A19,ListaIngredientes!$A$5:$F$155,2,FALSE),"") | D19: =IFERROR(VLOOKUP(A19,Tabela2[],3,FALSE),"") | F19: =IFERROR(VLOOKUP(A19,ListaIngredientes!$A$5:$F$155,6,FALSE),"") | H19: =IFERROR(E19*F19,"") | J19: Ele ter um preço do concorrente | N19: =N23 -> 5.987
B20: =IFERROR(VLOOKUP(A20,ListaIngredientes!$A$5:$F$155,2,FALSE),"") | D20: =IFERROR(VLOOKUP(A20,Tabela2[],3,FALSE),"") | F20: =IFERROR(VLOOKUP(A20,ListaIngredientes!$A$5:$F$155,6,FALSE),"") | H20: =IFERROR(E20*F20,"") | J20: fórmula | K20: "=1-C/V-DF-DV
B21: =IFERROR(VLOOKUP(A21,ListaIngredientes!$A$5:$F$155,2,FALSE),"") | D21: =IFERROR(VLOOKUP(A21,Tabela2[],3,FALSE),"") | F21: =IFERROR(VLOOKUP(A21,ListaIngredientes!$A$5:$F$155,6,FALSE),"") | H21: =IFERROR(E21*F21,"") | K21: =1-L9/N19-L10-L11 -> 0
B22: =IFERROR(VLOOKUP(A22,ListaIngredientes!$A$5:$F$155,2,FALSE),"") | D22: =IFERROR(VLOOKUP(A22,Tabela2[],3,FALSE),"") | F22: =IFERROR(VLOOKUP(A22,ListaIngredientes!$A$5:$F$155,6,FALSE),"") | H22: =IFERROR(E22*F22,"") | J22: ponto de Equilibrio
B23: =IFERROR(VLOOKUP(A23,ListaIngredientes!$A$5:$F$155,2,FALSE),"") | D23: =IFERROR(VLOOKUP(A23,Tabela2[],3,FALSE),"") | F23: =IFERROR(VLOOKUP(A23,ListaIngredientes!$A$5:$F$155,6,FALSE),"") | H23: =IFERROR(E23*F23,"") | J23: DF | K23: =L10 -> 0.12 | L23: =K23*$K$17 -> 1.149504 | M23: PV | N23: =L25/(1-K23-K24) -> 5.987
B24: =IFERROR(VLOOKUP(A24,ListaIngredientes!$A$5:$F$155,2,FALSE),"") | D24: =IFERROR(VLOOKUP(A24,Tabela2[],3,FALSE),"") | F24: =IFERROR(VLOOKUP(A24,ListaIngredientes!$A$5:$F$155,6,FALSE),"") | H24: =IFERROR(E24*F24,"") | J24: DV | K24: =L11 -> 0.08 | L24: =K24*$K$17 -> 0.766336 | M24: PV =C/(1-DF-DV) | O24: PE
B25: =IFERROR(VLOOKUP(A25,ListaIngredientes!$A$5:$F$155,2,FALSE),"") | D25: =IFERROR(VLOOKUP(A25,Tabela2[],3,FALSE),"") | F25: =IFERROR(VLOOKUP(A25,ListaIngredientes!$A$5:$F$155,6,FALSE),"") | H25: =IFERROR(E25*F25,"") | J25: C | K25: =L25/K17 -> 0.5 | L25: =L9 -> 4.7896
B26: =IFERROR(VLOOKUP(A26,ListaIngredientes!$A$5:$F$155,2,FALSE),"") | D26: =IFERROR(VLOOKUP(A26,Tabela2[],3,FALSE),"") | F26: =IFERROR(VLOOKUP(A26,ListaIngredientes!$A$5:$F$155,6,FALSE),"") | H26: =IFERROR(E26*F26,"") | J26: L | K26: 0.2 | L26: =K26*$K$17 -> 1.91584
B27: =IFERROR(VLOOKUP(A27,ListaIngredientes!$A$5:$F$155,2,FALSE),"") | D27: =IFERROR(VLOOKUP(A27,Tabela2[],3,FALSE),"") | F27: =IFERROR(VLOOKUP(A27,ListaIngredientes!$A$5:$F$155,6,FALSE),"") | H27: =IFERROR(E27*F27,"") | J27: Outro sonho de Ediberto
B28: =IFERROR(VLOOKUP(A28,ListaIngredientes!$A$5:$F$155,2,FALSE),"") | D28: =IFERROR(VLOOKUP(A28,Tabela2[],3,FALSE),"") | F28: =IFERROR(VLOOKUP(A28,ListaIngredientes!$A$5:$F$155,6,FALSE),"") | H28: =IFERROR(E28*F28,"") | K28: D R E
F29: soma | H29: =SUM(H9:H28) -> 28.7376 | J29: Preço de Venda | M29: =K17 -> 9.5792
J30: Preço do Custo | M30: =-L9 -> -4.7896
J31: DF | L31: =L10 -> 0.12 | M31: =-L31*M29 -> -1.149504
J32: DV | L32: =L11 -> 0.08 | M32: =-L32*M29 -> -0.766336
J34: lucro | M34: =SUM(M29:M33) -> 2.87376 | N34: =M34/M29 -> 0.3

Sheet BOLO GELADO ABACAXI
A1: cod | B1: 502 | C1: =VLOOKUP(B1,PRODUTOS!$A$7:$E$204,2,FALSE) -> BOLO GELADO ABACAXI | E1: =C3 -> 99.690995 | G1: SOBREMESA/DOCE
A2: Despesas Fixas | C2: 0.2 | E2: Preço Venda Unit | G2: =IFERROR(C3/(1-C2-C5),"") -> 332.30332
A3: Custo Unitário | C3: =IFERROR(C6/C4,"") -> 99.690995 | E3: Luro s/Venda | G3: =G2*C5 -> 166.15166
A4: Quantidade Produzida | C4: 6 | E4: Preço Praticado | G4: 15
A5: Lucro s/Venda | C5: 0.5 | E5: Lucro Praticado | G5: =1-C3/G4-C2 -> -5.8460663
A6: Gasto Total | C6: =H28 -> 598.14597 | E6: Lucro Praticado | G6: =G5*G4 -> -87.690995
A7: cod Prod | B7: Descrição ingredientes | D7: unid | E7: quantiadade | F7: valor $ | H7: Subtotal
A8: 101 | B8: =IFERROR(VLOOKUP(A8,ListaIngredientes!$A$5:$F$155,2,FALSE),"") | D8: =IFERROR(VLOOKUP(A8,Tabela2[],3,FALSE),"") | E8: 6 | F8: =IFERROR(VLOOKUP(A8,ListaIngredientes!$A$5:$F$155,6,FALSE),"") | H8: =IFERROR(E8*F8,"")
A9: 100 | B9: =IFERROR(VLOOKUP(A9,ListaIngredientes!$A$5:$F$155,2,FALSE),"") | D9: =IFERROR(VLOOKUP(A9,Tabela2[],3,FALSE),"") | E9: 0.5 | F9: =IFERROR(VLOOKUP(A9,ListaIngredientes!$A$5:$F$155,6,FALSE),"") | H9: =IFERROR(E9*F9,"")
A10: 188 | B10: =IFERROR(VLOOKUP(A10,ListaIngredientes!$A$5:$F$155,2,FALSE),"") -> LATA PALHA ITALIANA | D10: =IFERROR(VLOOKUP(A10,Tabela2[],3,FALSE),"") -> U | E10: 350 | F10: =IFERROR(VLOOKUP(A10,ListaIngredientes!$A$5:$F$155,6,FALSE),"") -> 1.59 | H10: =IFERROR(E10*F10,"") -> 556.5
A11: 139 | B11: =IFERROR(VLOOKUP(A11,ListaIngredientes!$A$5:$F$155,2,FALSE),"") -> cravo da india | D11: =IFERROR(VLOOKUP(A11,Tabela2[],3,FALSE),"") -> g | E11: 200 | F11: =IFERROR(VLOOKUP(A11,ListaIngredientes!$A$5:$F$155,6,FALSE),"") -> 0.00058823529 | H11: =IFERROR(E11*F11,"") -> 0.11764706
A12: 126 | B12: =IFERROR(VLOOKUP(A12,ListaIngredientes!$A$5:$F$155,2,FALSE),"") -> CHOCOLTE BRANCO | D12: =IFERROR(VLOOKUP(A12,Tabela2[],3,FALSE),"") -> KG | E12: 110 | F12: =IFERROR(VLOOKUP(A12,ListaIngredientes!$A$5:$F$155,6,FALSE),"") -> 0.159 | H12: =IFERROR(E12*F12,"") -> 17.49
A13: 203 | B13: =IFERROR(VLOOKUP(A13,ListaIngredientes!$A$5:$F$155,2,FALSE),"") -> 0 | D13: =IFERROR(VLOOKUP(A13,Tabela2[],3,FALSE),"") -> 0 | E13: 3 | F13: =IFERROR(VLOOKUP(A13,ListaIngredientes!$A$5:$F$155,6,FALSE),"") -> 0 | H13: =IFERROR(E13*F13,"") -> 0
A14: 230 | B14: =IFERROR(VLOOKUP(A14,ListaIngredientes!$A$5:$F$155,2,FALSE),"") -> 0 | D14: kg | E14: 105 | F14: =IFERROR(VLOOKUP(A14,ListaIngredientes!$A$5:$F$155,6,FALSE),"") -> 0.149 | H14: =IFERROR(E14*F14,"") -> 15.645
A15: 163 | B15: =IFERROR(VLOOKUP(A15,ListaIngredientes!$A$5:$F$155,2,FALSE),"") -> fermento biologico | D15: kg | E15: 11 | F15: =IFERROR(VLOOKUP(A15,ListaIngredientes!$A$5:$F$155,6,FALSE),"") -> 0.05512 | H15: =IFERROR(E15*F15,"") -> 0.60632
A16: 146 | B16: =IFERROR(VLOOKUP(A16,ListaIngredientes!$A$5:$F$155,2,FALSE),"") -> embalagem bolo de pote | D16: u | E16: 6 | F16: =IFERROR(VLOOKUP(A16,ListaIngredientes!$A$5:$F$155,6,FALSE),"") -> 0.599 | H16: =IFERROR(E16*F16,"") -> 3.594
A17: 202 | B17: =IFERROR(VLOOKUP(A17,ListaIngredientes!$A$5:$F$155,2,FALSE),"") -> 0 | D17: =IFERROR(VLOOKUP(A17,Tabela2[],3,FALSE),"") -> 0 | E17: 50 | F17: =IFERROR(VLOOKUP(A17,ListaIngredientes!$A$5:$F$155,6,FALSE),"") -> 0 | H17: =IFERROR(E17*F17,"") -> 0
A18: 156 | B18: =IFERROR(VLOOKUP(A18,ListaIngredientes!$A$5:$F$155,2,FALSE),"") -> embalagem quiche | D18: =IFERROR(VLOOKUP(A18,Tabela2[],3,FALSE),"") -> u | E18: 7 | F18: =IFERROR(VLOOKUP(A18,ListaIngredientes!$A$5:$F$155,6,FALSE),"") -> 0.599 | H18: =IFERROR(E18*F18,"") -> 4.193
B19: =IFERROR(VLOOKUP(A19,ListaIngredientes!$A$5:$F$155,2,FALSE),"") | D19: =IFERROR(VLOOKUP(A19,Tabela2[],3,FALSE),"") | F19: =IFERROR(VLOOKUP(A19,ListaIngredientes!$A$5:$F$155,6,FALSE),"") | H19: =IFERROR(E19*F19,"")
B20: =IFERROR(VLOOKUP(A20,ListaIngredientes!$A$5:$F$155,2,FALSE),"") | D20: =IFERROR(VLOOKUP(A20,Tabela2[],3,FALSE),"") | F20: =IFERROR(VLOOKUP(A20,ListaIngredientes!$A$5:$F$155,6,FALSE),"") | H20: =IFERROR(E20*F20,"")
B21: =IFERROR(VLOOKUP(A21,ListaIngredientes!$A$5:$F$155,2,FALSE),"") | D21: =IFERROR(VLOOKUP(A21,Tabela2[],3,FALSE),"") | F21: =IFERROR(VLOOKUP(A21,ListaIngredientes!$A$5:$F$155,6,FALSE),"") | H21: =IFERROR(E21*F21,"")
B22: =IFERROR(VLOOKUP(A22,ListaIngredientes!$A$5:$F$155,2,FALSE),"") | D22: =IFERROR(VLOOKUP(A22,Tabela2[],3,FALSE),"") | F22: =IFERROR(VLOOKUP(A22,ListaIngredientes!$A$5:$F$155,6,FALSE),"") | H22: =IFERROR(E22*F22,"")
B23: =IFERROR(VLOOKUP(A23,ListaIngredientes!$A$5:$F$155,2,FALSE),"") | D23: =IFERROR(VLOOKUP(A23,Tabela2[],3,FALSE),"") | F23: =IFERROR(VLOOKUP(A23,ListaIngredientes!$A$5:$F$155,6,FALSE),"") | H23: =IFERROR(E23*F23,"")
B24: =IFERROR(VLOOKUP(A24,ListaIngredientes!$A$5:$F$155,2,FALSE),"") | D24: =IFERROR(VLOOKUP(A24,Tabela2[],3,FALSE),"") | F24: =IFERROR(VLOOKUP(A24,ListaIngredientes!$A$5:$F$155,6,FALSE),"") | H24: =IFERROR(E24*F24,"")
B25: =IFERROR(VLOOKUP(A25,ListaIngredientes!$A$5:$F$155,2,FALSE),"") | D25: =IFERROR(VLOOKUP(A25,Tabela2[],3,FALSE),"") | F25: =IFERROR(VLOOKUP(A25,ListaIngredientes!$A$5:$F$155,6,FALSE),"") | H25: =IFERROR(E25*F25,"")
B26: =IFERROR(VLOOKUP(A26,ListaIngredientes!$A$5:$F$155,2,FALSE),"") | D26: =IFERROR(VLOOKUP(A26,Tabela2[],3,FALSE),"") | F26: =IFERROR(VLOOKUP(A26,ListaIngredientes!$A$5:$F$155,6,FALSE),"") | H26: =IFERROR(E26*F26,"")
B27: =IFERROR(VLOOKUP(A27,ListaIngredientes!$A$5:$F$155,2,FALSE),"") | D27: =IFERROR(VLOOKUP(A27,Tabela2[],3,FALSE),"") | F27: =IFERROR(VLOOKUP(A27,ListaIngredientes!$A$5:$F$155,6,FALSE),"") | H27: =IFERROR(E27*F27,"")
F28: soma | H28: =SUM(H8:H27) -> 598.14597

Sheet BRIG COLHER
A1: cod | B1: 504 | C1: =VLOOKUP(B1,PRODUTOS!$A$7:$E$204,2,FALSE) -> BRIGADEIRO DE COLHER | E1: =C3 -> 4.5661438 | G1: SOBREMESA/DOCE
A2: Despesas Fixas | C2: 0.2 | E2: Preço Venda Unit | G2: =IFERROR(C3/(1-C2-C5),"") -> 15.220479
A3: Custo Unitário | C3: =IFERROR(C6/C4,"") -> 4.5661438 | E3: Luro s/Venda | G3: =G2*C5 -> 7.6102397
A4: Quantidade Produzida | C4: 9 | E4: Preço Praticado | G4: 15
A5: Lucro s/Venda | C5: 0.5 | E5: Lucro Praticado | G5: =1-C3/G4-C2 -> 0.49559041
A6: Gasto Total | C6: =H28 -> 41.095294 | E6: Lucro Praticado | G6: =G5*G4 -> 7.4338562
A7: cod Prod | B7: Descrição ingredientes | D7: unid | E7: quantiadade | F7: valor $ | H7: Subtotal
A8: 101 | B8: =IFERROR(VLOOKUP(A8,ListaIngredientes!$A$5:$F$155,2,FALSE),"") | D8: =IFERROR(VLOOKUP(A8,Tabela2[],3,FALSE),"") | E8: 9 | F8: =IFERROR(VLOOKUP(A8,ListaIngredientes!$A$5:$F$155,6,FALSE),"") | H8: =IFERROR(E8*F8,"")
A9: 105 | B9: =IFERROR(VLOOKUP(A9,ListaIngredientes!$A$5:$F$155,2,FALSE),"") -> Bananas | D9: =IFERROR(VLOOKUP(A9,Tabela2[],3,FALSE),"") -> duzias | E9: 40 | F9: =IFERROR(VLOOKUP(A9,ListaIngredientes!$A$5:$F$155,6,FALSE),"") -> 0.5 | H9: =IFERROR(E9*F9,"") -> 20
A10: 125 | B10: =IFERROR(VLOOKUP(A10,ListaIngredientes!$A$5:$F$155,2,FALSE),"") -> 0 | D10: =IFERROR(VLOOKUP(A10,Tabela2[],3,FALSE),"") -> 0 | E10: 140 | F10: =IFERROR(VLOOKUP(A10,ListaIngredientes!$A$5:$F$155,6,FALSE),"") -> 0 | H10: =IFERROR(E10*F10,"") -> 0
A11: 139 | B11: =IFERROR(VLOOKUP(A11,ListaIngredientes!$A$5:$F$155,2,FALSE),"") -> cravo da india | D11: =IFERROR(VLOOKUP(A11,Tabela2[],3,FALSE),"") -> g | E11: 400 | F11: =IFERROR(VLOOKUP(A11,ListaIngredientes!$A$5:$F$155,6,FALSE),"") -> 0.00058823529 | H11: =IFERROR(E11*F11,"") -> 0.23529412
A12: 230 | B12: =IFERROR(VLOOKUP(A12,ListaIngredientes!$A$5:$F$155,2,FALSE),"") -> 0 | D12: kg | E12: 140 | F12: =IFERROR(VLOOKUP(A12,ListaIngredientes!$A$5:$F$155,6,FALSE),"") -> 0.149 | H12: =IFERROR(E12*F12,"") -> 20.86
A13: 143 | B13: =IFERROR(VLOOKUP(A13,ListaIngredientes!$A$5:$F$155,2,FALSE),"") -> 0 | D13: u | E13: 9 | F13: =IFERROR(VLOOKUP(A13,ListaIngredientes!$A$5:$F$155,6,FALSE),"") -> 0 | H13: =IFERROR(E13*F13,"") -> 0
B14: =IFERROR(VLOOKUP(A14,ListaIngredientes!$A$5:$F$155,2,FALSE),"") | F14: =IFERROR(VLOOKUP(A14,ListaIngredientes!$A$5:$F$155,6,FALSE),"") | H14: =IFERROR(E14*F14,"")
B15: =IFERROR(VLOOKUP(A15,ListaIngredientes!$A$5:$F$155,2,FALSE),"") | F15: =IFERROR(VLOOKUP(A15,ListaIngredientes!$A$5:$F$155,6,FALSE),"") | H15: =IFERROR(E15*F15,"")
B16: =IFERROR(VLOOKUP(A16,ListaIngredientes!$A$5:$F$155,2,FALSE),"") | F16: =IFERROR(VLOOKUP(A16,ListaIngredientes!$A$5:$F$155,6,FALSE),"") | H16: =IFERROR(E16*F16,"")
B17: =IFERROR(VLOOKUP(A17,ListaIngredientes!$A$5:$F$155,2,FALSE),"") | D17: =IFERROR(VLOOKUP(A17,Tabela2[],3,FALSE),"") | F17: =IFERROR(VLOOKUP(A17,ListaIngredientes!$A$5:$F$155,6,FALSE),"") | H17: =IFERROR(E17*F17,"")
B18: =IFERROR(VLOOKUP(A18,ListaIngredientes!$A$5:$F$155,2,FALSE),"") | D18: =IFERROR(VLOOKUP(A18,Tabela2[],3,FALSE),"") | F18: =IFERROR(VLOOKUP(A18,ListaIngredientes!$A$5:$F$155,6,FALSE),"") | H18: =IFERROR(E18*F18,"")
B19: =IFERROR(VLOOKUP(A19,ListaIngredientes!$A$5:$F$155,2,FALSE),"") | D19: =IFERROR(VLOOKUP(A19,Tabela2[],3,FALSE),"") | F19: =IFERROR(VLOOKUP(A19,ListaIngredientes!$A$5:$F$155,6,FALSE),"") | H19: =IFERROR(E19*F19,"")
B20: =IFERROR(VLOOKUP(A20,ListaIngredientes!$A$5:$F$155,2,FALSE),"") | D20: =IFERROR(VLOOKUP(A20,Tabela2[],3,FALSE),"") | F20: =IFERROR(VLOOKUP(A20,ListaIngredientes!$A$5:$F$155,6,FALSE),"") | H20: =IFERROR(E20*F20,"")
B21: =IFERROR(VLOOKUP(A21,ListaIngredientes!$A$5:$F$155,2,FALSE),"") | D21: =IFERROR(VLOOKUP(A21,Tabela2[],3,FALSE),"") | F21: =IFERROR(VLOOKUP(A21,ListaIngredientes!$A$5:$F$155,6,FALSE),"") | H21: =IFERROR(E21*F21,"")
B22: =IFERROR(VLOOKUP(A22,ListaIngredientes!$A$5:$F$155,2,FALSE),"") | D22: =IFERROR(VLOOKUP(A22,Tabela2[],3,FALSE),"") | F22: =IFERROR(VLOOKUP(A22,ListaIngredientes!$A$5:$F$155,6,FALSE),"") | H22: =IFERROR(E22*F22,"")
B23: =IFERROR(VLOOKUP(A23,ListaIngredientes!$A$5:$F$155,2,FALSE),"") | D23: =IFERROR(VLOOKUP(A23,Tabela2[],3,FALSE),"") | F23: =IFERROR(VLOOKUP(A23,ListaIngredientes!$A$5:$F$155,6,FALSE),"") | H23: =IFERROR(E23*F23,"")
B24: =IFERROR(VLOOKUP(A24,ListaIngredientes!$A$5:$F$155,2,FALSE),"") | D24: =IFERROR(VLOOKUP(A24,Tabela2[],3,FALSE),"") | F24: =IFERROR(VLOOKUP(A24,ListaIngredientes!$A$5:$F$155,6,FALSE),"") | H24: =IFERROR(E24*F24,"")
B25: =IFERROR(VLOOKUP(A25,ListaIngredientes!$A$5:$F$155,2,FALSE),"") | D25: =IFERROR(VLOOKUP(A25,Tabela2[],3,FALSE),"") | F25: =IFERROR(VLOOKUP(A25,ListaIngredientes!$A$5:$F$155,6,FALSE),"") | H25: =IFERROR(E25*F25,"")
B26: =IFERROR(VLOOKUP(A26,ListaIngredientes!$A$5:$F$155,2,FALSE),"") | D26: =IFERROR(VLOOKUP(A26,Tabela2[],3,FALSE),"") | F26: =IFERROR(VLOOKUP(A26,ListaIngredientes!$A$5:$F$155,6,FALSE),"") | H26: =IFERROR(E26*F26,"")
B27: =IFERROR(VLOOKUP(A27,ListaIngredientes!$A$5:$F$155,2,FALSE),"") | D27: =IFERROR(VLOOKUP(A27,Tabela2[],3,FALSE),"") | F27: =IFERROR(VLOOKUP(A27,ListaIngredientes!$A$5:$F$155,6,FALSE),"") | H27: =IFERROR(E27*F27,"")
F28: soma | H28: =SUM(H8:H27) -> 41.095294

Sheet BRIG UNITARIO
A1: cod | B1: 505 | C1: =VLOOKUP(B1,PRODUTOS!$A$7:$E$204,2,FALSE) -> BRIGADEIRO UNITÁRIO | E1: =C3 -> 2.5251275 | G1: SOBREMESA/DOCE
A2: Despesas Fixas | C2: 0.2 | E2: Preço Venda Unit | G2: =IFERROR(C3/(1-C2-C5),"") -> 8.4170915
A3: Custo Unitário | C3: =IFERROR(C6/C4,"") -> 2.5251275 | E3: Luro s/Venda | G3: =G2*C5 -> 4.2085458
A4: Quantidade Produzida | C4: 18 | E4: Preço Praticado | G4: 4
A5: Lucro s/Venda | C5: 0.5 | E5: Lucro Praticado | G5: =1-C3/G4-C2 -> 0.16871814
A6: Gasto Total | C6: =H28 -> 45.452294 | E6: Lucro Praticado | G6: =G5*G4 -> 0.67487255
A7: cod Prod | B7: Descrição ingredientes | D7: unid | E7: quantiadade | F7: valor $ | H7: Subtotal
A8: 101 | B8: =IFERROR(VLOOKUP(A8,ListaIngredientes!$A$5:$F$155,2,FALSE),"") | D8: =IFERROR(VLOOKUP(A8,Tabela2[],3,FALSE),"") | E8: 18 | F8: =IFERROR(VLOOKUP(A8,ListaIngredientes!$A$5:$F$155,6,FALSE),"") | H8: =IFERROR(E8*F8,"")
A9: 105 | B9: =IFERROR(VLOOKUP(A9,ListaIngredientes!$A$5:$F$155,2,FALSE),"") -> Bananas | D9: =IFERROR(VLOOKUP(A9,Tabela2[],3,FALSE),"") -> duzias | E9: 40 | F9: =IFERROR(VLOOKUP(A9,ListaIngredientes!$A$5:$F$155,6,FALSE),"") -> 0.5 | H9: =IFERROR(E9*F9,"") -> 20
A10: 125 | B10: =IFERROR(VLOOKUP(A10,ListaIngredientes!$A$5:$F$155,2,FALSE),"") -> 0 | D10: =IFERROR(VLOOKUP(A10,Tabela2[],3,FALSE),"") -> 0 | E10: 140 | F10: =IFERROR(VLOOKUP(A10,ListaIngredientes!$A$5:$F$155,6,FALSE),"") -> 0 | H10: =IFERROR(E10*F10,"") -> 0
A11: 139 | B11: =IFERROR(VLOOKUP(A11,ListaIngredientes!$A$5:$F$155,2,FALSE),"") -> cravo da india | D11: =IFERROR(VLOOKUP(A11,Tabela2[],3,FALSE),"") -> g | E11: 400 | F11: =IFERROR(VLOOKUP(A11,ListaIngredientes!$A$5:$F$155,6,FALSE),"") -> 0.00058823529 | H11: =IFERROR(E11*F11,"") -> 0.23529412
A12: 230 | B12: =IFERROR(VLOOKUP(A12,ListaIngredientes!$A$5:$F$155,2,FALSE),"") -> 0 | D12: kg | E12: 70 | F12: =IFERROR(VLOOKUP(A12,ListaIngredientes!$A$5:$F$155,6,FALSE),"") -> 0.149 | H12: =IFERROR(E12*F12,"") -> 10.43
A13: 174 | B13: =IFERROR(VLOOKUP(A13,ListaIngredientes!$A$5:$F$155,2,FALSE),"") -> Galvanatec 679 | D13: u | E13: 18 | F13: =IFERROR(VLOOKUP(A13,ListaIngredientes!$A$5:$F$155,6,FALSE),"") -> 0.8 | H13: =IFERROR(E13*F13,"") -> 14.4
A14: 176 | B14: =IFERROR(VLOOKUP(A14,ListaIngredientes!$A$5:$F$155,2,FALSE),"") -> forminha de brigadeiro | D14: U | E14: 18 | F14: =IFERROR(VLOOKUP(A14,ListaIngredientes!$A$5:$F$155,6,FALSE),"") -> 0.0215 | H14: =IFERROR(E14*F14,"") -> 0.387
B15: =IFERROR(VLOOKUP(A15,ListaIngredientes!$A$5:$F$155,2,FALSE),"") | F15: =IFERROR(VLOOKUP(A15,ListaIngredientes!$A$5:$F$155,6,FALSE),"") | H15: =IFERROR(E15*F15,"")
B16: =IFERROR(VLOOKUP(A16,ListaIngredientes!$A$5:$F$155,2,FALSE),"") | F16: =IFERROR(VLOOKUP(A16,ListaIngredientes!$A$5:$F$155,6,FALSE),"") | H16: =IFERROR(E16*F16,"")
B17: =IFERROR(VLOOKUP(A17,ListaIngredientes!$A$5:$F$155,2,FALSE),"") | D17: =IFERROR(VLOOKUP(A17,Tabela2[],3,FALSE),"") | F17: =IFERROR(VLOOKUP(A17,ListaIngredientes!$A$5:$F$155,6,FALSE),"") | H17: =IFERROR(E17*F17,"")
B18: =IFERROR(VLOOKUP(A18,ListaIngredientes!$A$5:$F$155,2,FALSE),"") | D18: =IFERROR(VLOOKUP(A18,Tabela2[],3,FALSE),"") | F18: =IFERROR(VLOOKUP(A18,ListaIngredientes!$A$5:$F$155,6,FALSE),"") | H18: =IFERROR(E18*F18,"")
B19: =IFERROR(VLOOKUP(A19,ListaIngredientes!$A$5:$F$155,2,FALSE),"") | D19: =IFERROR(VLOOKUP(A19,Tabela2[],3,FALSE),"") | F19: =IFERROR(VLOOKUP(A19,ListaIngredientes!$A$5:$F$155,6,FALSE),"") | H19: =IFERROR(E19*F19,"")
B20: =IFERROR(VLOOKUP(A20,ListaIngredientes!$A$5:$F$155,2,FALSE),"") | D20: =IFERROR(VLOOKUP(A20,Tabela2[],3,FALSE),"") | F20: =IFERROR(VLOOKUP(A20,ListaIngredientes!$A$5:$F$155,6,FALSE),"") | H20: =IFERROR(E20*F20,"")
B21: =IFERROR(VLOOKUP(A21,ListaIngredientes!$A$5:$F$155,2,FALSE),"") | D21: =IFERROR(VLOOKUP(A21,Tabela2[],3,FALSE),"") | F21: =IFERROR(VLOOKUP(A21,ListaIngredientes!$A$5:$F$155,6,FALSE),"") | H21: =IFERROR(E21*F21,"")
B22: =IFERROR(VLOOKUP(A22,ListaIngredientes!$A$5:$F$155,2,FALSE),"") | D22: =IFERROR(VLOOKUP(A22,Tabela2[],3,FALSE),"") | F22: =IFERROR(VLOOKUP(A22,ListaIngredientes!$A$5:$F$155,6,FALSE),"") | H22: =IFERROR(E22*F22,"")
B23: =IFERROR(VLOOKUP(A23,ListaIngredientes!$A$5:$F$155,2,FALSE),"") | D23: =IFERROR(VLOOKUP(A23,Tabela2[],3,FALSE),"") | F23: =IFERROR(VLOOKUP(A23,ListaIngredientes!$A$5:$F$155,6,FALSE),"") | H23: =IFERROR(E23*F23,"")
B24: =IFERROR(VLOOKUP(A24,ListaIngredientes!$A$5:$F$155,2,FALSE),"") | D24: =IFERROR(VLOOKUP(A24,Tabela2[],3,FALSE),"") | F24: =IFERROR(VLOOKUP(A24,ListaIngredientes!$A$5:$F$155,6,FALSE),"") | H24: =IFERROR(E24*F24,"")
B25: =IFERROR(VLOOKUP(A25,ListaIngredientes!$A$5:$F$155,2,FALSE),"") | D25: =IFERROR(VLOOKUP(A25,Tabela2[],3,FALSE),"") | F25: =IFERROR(VLOOKUP(A25,ListaIngredientes!$A$5:$F$155,6,FALSE),"") | H25: =IFERROR(E25*F25,"")
B26: =IFERROR(VLOOKUP(A26,ListaIngredientes!$A$5:$F$155,2,FALSE),"") | D26: =IFERROR(VLOOKUP(A26,Tabela2[],3,FALSE),"") | F26: =IFERROR(VLOOKUP(A26,ListaIngredientes!$A$5:$F$155,6,FALSE),"") | H26: =IFERROR(E26*F26,"")
B27: =IFERROR(VLOOKUP(A27,ListaIngredientes!$A$5:$F$155,2,FALSE),"") | D27: =IFERROR(VLOOKUP(A27,Tabela2[],3,FALSE),"") | F27: =IFERROR(VLOOKUP(A27,ListaIngredientes!$A$5:$F$155,6,FALSE),"") | H27: =IFERROR(E27*F27,"")
F28: soma | H28: =SUM(H8:H27) -> 45.452294

Sheet BRIGADEIRO DUO
A1: cod | B1: 503 | C1: =VLOOKUP(B1,PRODUTOS!$A$7:$E$204,2,FALSE) -> BRIGADEIRO DUO | E1: =C3 -> 4.4392552 | G1: SOBREMESA/DOCE
A2: Despesas Fixas | C2: 0.2 | E2: Preço Venda Unit | G2: =IFERROR(C3/(1-C2-C5),"") -> 14.797517
A3: Custo Unitário | C3: =IFERROR(C6/C4,"") -> 4.4392552 | E3: Luro s/Venda | G3: =G2*C5 -> 7.3987586
A4: Quantidade Produzida | C4: 9 | E4: Preço Praticado | G4: 15
A5: Lucro s/Venda | C5: 0.5 | E5: Lucro Praticado | G5: =1-C3/G4-C2 -> 0.50404965
A6: Gasto Total | C6: =H28 -> 39.953297 | E6: Lucro Praticado | G6: =G5*G4 -> 7.5607448
A7: cod Prod | B7: Descrição ingredientes | D7: unid | E7: quantiadade | F7: valor $ | H7: Subtotal
A8: 101 | B8: =IFERROR(VLOOKUP(A8,ListaIngredientes!$A$5:$F$155,2,FALSE),"") | D8: =IFERROR(VLOOKUP(A8,Tabela2[],3,FALSE),"") | E8: 9 | F8: =IFERROR(VLOOKUP(A8,ListaIngredientes!$A$5:$F$170,6,FALSE),"") | H8: =IFERROR(E8*F8,"")
A9: 105 | B9: =IFERROR(VLOOKUP(A9,ListaIngredientes!$A$5:$F$155,2,FALSE),"") -> Bananas | D9: =IFERROR(VLOOKUP(A9,Tabela2[],3,FALSE),"") -> duzias | E9: 20 | F9: =IFERROR(VLOOKUP(A9,ListaIngredientes!$A$5:$F$170,6,FALSE),"") -> 0.5 | H9: =IFERROR(E9*F9,"") -> 10
A10: 125 | B10: =IFERROR(VLOOKUP(A10,ListaIngredientes!$A$5:$F$155,2,FALSE),"") -> 0 | D10: =IFERROR(VLOOKUP(A10,Tabela2[],3,FALSE),"") -> 0 | E10: 70 | F10: =IFERROR(VLOOKUP(A10,ListaIngredientes!$A$5:$F$170,6,FALSE),"") -> 0 | H10: =IFERROR(E10*F10,"") -> 0
A11: 139 | B11: =IFERROR(VLOOKUP(A11,ListaIngredientes!$A$5:$F$155,2,FALSE),"") -> cravo da india | D11: =IFERROR(VLOOKUP(A11,Tabela2[],3,FALSE),"") -> g | E11: 1000 | F11: =IFERROR(VLOOKUP(A11,ListaIngredientes!$A$5:$F$170,6,FALSE),"") -> 0.00058823529 | H11: =IFERROR(E11*F11,"") -> 0.58823529
A12: 230 | B12: =IFERROR(VLOOKUP(A12,ListaIngredientes!$A$5:$F$155,2,FALSE),"") -> 0 | D12: kg | E12: 175 | F12: =IFERROR(VLOOKUP(A12,ListaIngredientes!$A$5:$F$170,6,FALSE),"") -> 0.149 | H12: =IFERROR(E12*F12,"") -> 26.075
A13: 135 | B13: =IFERROR(VLOOKUP(A13,ListaIngredientes!$A$5:$F$155,2,FALSE),"") -> ISOPOR DE PIZZA REDONDA | D13: u | E13: 9 | F13: =IFERROR(VLOOKUP(A13,ListaIngredientes!$A$5:$F$170,6,FALSE),"") -> 0.29 | H13: =IFERROR(E13*F13,"") -> 2.61
A14: 249 | B14: =IFERROR(VLOOKUP(A14,ListaIngredientes!$A$5:$F$155,2,FALSE),"") -> Whey Protein | D14: kg | E14: 40 | F14: =IFERROR(VLOOKUP(A14,ListaIngredientes!$A$5:$F$170,6,FALSE),"") -> 0.017001534 | H14: =IFERROR(E14*F14,"") -> 0.68006135
B15: =IFERROR(VLOOKUP(A15,ListaIngredientes!$A$5:$F$170,2,FALSE),"") | F15: =IFERROR(VLOOKUP(A15,ListaIngredientes!$A$5:$F$170,6,FALSE),"") | H15: =IFERROR(E15*F15,"")
B16: =IFERROR(VLOOKUP(A16,ListaIngredientes!$A$5:$F$170,2,FALSE),"") | F16: =IFERROR(VLOOKUP(A16,ListaIngredientes!$A$5:$F$170,6,FALSE),"") | H16: =IFERROR(E16*F16,"")
B17: =IFERROR(VLOOKUP(A17,ListaIngredientes!$A$5:$F$170,2,FALSE),"") | D17: =IFERROR(VLOOKUP(A17,Tabela2[],3,FALSE),"") | F17: =IFERROR(VLOOKUP(A17,ListaIngredientes!$A$5:$F$170,6,FALSE),"") | H17: =IFERROR(E17*F17,"")
B18: =IFERROR(VLOOKUP(A18,ListaIngredientes!$A$5:$F$170,2,FALSE),"") | D18: =IFERROR(VLOOKUP(A18,Tabela2[],3,FALSE),"") | F18: =IFERROR(VLOOKUP(A18,ListaIngredientes!$A$5:$F$170,6,FALSE),"") | H18: =IFERROR(E18*F18,"")
B19: =IFERROR(VLOOKUP(A19,ListaIngredientes!$A$5:$F$170,2,FALSE),"") | D19: =IFERROR(VLOOKUP(A19,Tabela2[],3,FALSE),"") | F19: =IFERROR(VLOOKUP(A19,ListaIngredientes!$A$5:$F$170,6,FALSE),"") | H19: =IFERROR(E19*F19,"")
B20: =IFERROR(VLOOKUP(A20,ListaIngredientes!$A$5:$F$170,2,FALSE),"") | D20: =IFERROR(VLOOKUP(A20,Tabela2[],3,FALSE),"") | F20: =IFERROR(VLOOKUP(A20,ListaIngredientes!$A$5:$F$170,6,FALSE),"") | H20: =IFERROR(E20*F20,"")
B21: =IFERROR(VLOOKUP(A21,ListaIngredientes!$A$5:$F$170,2,FALSE),"") | D21: =IFERROR(VLOOKUP(A21,Tabela2[],3,FALSE),"") | F21: =IFERROR(VLOOKUP(A21,ListaIngredientes!$A$5:$F$170,6,FALSE),"") | H21: =IFERROR(E21*F21,"")
B22: =IFERROR(VLOOKUP(A22,ListaIngredientes!$A$5:$F$170,2,FALSE),"") | D22: =IFERROR(VLOOKUP(A22,Tabela2[],3,FALSE),"") | F22: =IFERROR(VLOOKUP(A22,ListaIngredientes!$A$5:$F$170,6,FALSE),"") | H22: =IFERROR(E22*F22,"")
B23: =IFERROR(VLOOKUP(A23,ListaIngredientes!$A$5:$F$170,2,FALSE),"") | D23: =IFERROR(VLOOKUP(A23,Tabela2[],3,FALSE),"") | F23: =IFERROR(VLOOKUP(A23,ListaIngredientes!$A$5:$F$170,6,FALSE),"") | H23: =IFERROR(E23*F23,"")
B24: =IFERROR(VLOOKUP(A24,ListaIngredientes!$A$5:$F$170,2,FALSE),"") | D24: =IFERROR(VLOOKUP(A24,Tabela2[],3,FALSE),"") | F24: =IFERROR(VLOOKUP(A24,ListaIngredientes!$A$5:$F$170,6,FALSE),"") | H24: =IFERROR(E24*F24,"")
B25: =IFERROR(VLOOKUP(A25,ListaIngredientes!$A$5:$F$170,2,FALSE),"") | D25: =IFERROR(VLOOKUP(A25,Tabela2[],3,FALSE),"") | F25: =IFERROR(VLOOKUP(A25,ListaIngredientes!$A$5:$F$170,6,FALSE),"") | H25: =IFERROR(E25*F25,"")
B26: =IFERROR(VLOOKUP(A26,ListaIngredientes!$A$5:$F$170,2,FALSE),"") | D26: =IFERROR(VLOOKUP(A26,Tabela2[],3,FALSE),"") | F26: =IFERROR(VLOOKUP(A26,ListaIngredientes!$A$5:$F$170,6,FALSE),"") | H26: =IFERROR(E26*F26,"")
B27: =IFERROR(VLOOKUP(A27,ListaIngredientes!$A$5:$F$170,2,FALSE),"") | D27: =IFERROR(VLOOKUP(A27,Tabela2[],3,FALSE),"") | F27: =IFERROR(VLOOKUP(A27,ListaIngredientes!$A$5:$F$170,6,FALSE),"") | H27: =IFERROR(E27*F27,"")
F28: soma | H28: =SUM(H8:H27) -> 39.953297

Sheet BARRA DE CHOCOLATE
A1: cod | B1: 501 | C1: =VLOOKUP(B1,PRODUTOS!$A$7:$E$204,2,FALSE) -> P A S T E L | E1: =C3 -> 0.21538462 | G1: SOBREMESA/DOCE
A2: Despesas Fixas | C2: 0.2 | E2: Preço Venda Unit | G2: =IFERROR(C3/(1-C2-C5),"") -> 0.71794872
A3: Custo Unitário | C3: =IFERROR(C6/C4,"") -> 0.21538462 | E3: Luro s/Venda | G3: =G2*C5 -> 0.35897436
A4: Quantidade Produzida | C4: 13 | E4: Preço Praticado | G4: 15
A5: Lucro s/Venda | C5: 0.5 | E5: Lucro Praticado | G5: =1-C3/G4-C2 -> 0.78564103
A6: Gasto Total | C6: =H28 -> 2.8 | E6: Lucro Praticado | G6: =G5*G4 -> 11.784615
A7: cod Prod | B7: Descrição ingredientes | D7: unid | E7: quantiadade | F7: valor $ | H7: Subtotal
A8: 101 | B8: =IFERROR(VLOOKUP(A8,ListaIngredientes!$A$5:$F$155,2,FALSE),"") | D8: =IFERROR(VLOOKUP(A8,Tabela2[],3,FALSE),"") | E8: 7 | F8: =IFERROR(VLOOKUP(A8,ListaIngredientes!$A$5:$F$155,6,FALSE),"") | H8: =IFERROR(E8*F8,"")
A9: 223 | B9: =IFERROR(VLOOKUP(A9,ListaIngredientes!$A$5:$F$155,2,FALSE),"") -> SACO PASCOA 24X24 | D9: =IFERROR(VLOOKUP(A9,Tabela2[],3,FALSE),"") -> u | E9: 7 | F9: =IFERROR(VLOOKUP(A9,ListaIngredientes!$A$5:$F$155,6,FALSE),"") -> 0.4 | H9: =IFERROR(E9*F9,"") -> 2.8
A10: 125 | B10: =IFERROR(VLOOKUP(A10,ListaIngredientes!$A$5:$F$155,2,FALSE),"") -> 0 | D10: =IFERROR(VLOOKUP(A10,Tabela2[],3,FALSE),"") -> 0 | E10: 300 | F10: =IFERROR(VLOOKUP(A10,ListaIngredientes!$A$5:$F$155,6,FALSE),"") -> 0 | H10: =IFERROR(E10*F10,"") -> 0
B11: =IFERROR(VLOOKUP(A11,ListaIngredientes!$A$5:$F$155,2,FALSE),"") | D11: =IFERROR(VLOOKUP(A11,Tabela2[],3,FALSE),"") | F11: =IFERROR(VLOOKUP(A11,ListaIngredientes!$A$5:$F$155,6,FALSE),"") | H11: =IFERROR(E11*F11,"")
B12: =IFERROR(VLOOKUP(A12,ListaIngredientes!$A$5:$F$155,2,FALSE),"") | F12: =IFERROR(VLOOKUP(A12,ListaIngredientes!$A$5:$F$155,6,FALSE),"") | H12: =IFERROR(E12*F12,"")
B13: =IFERROR(VLOOKUP(A13,ListaIngredientes!$A$5:$F$155,2,FALSE),"") | F13: =IFERROR(VLOOKUP(A13,ListaIngredientes!$A$5:$F$155,6,FALSE),"") | H13: =IFERROR(E13*F13,"")
B14: =IFERROR(VLOOKUP(A14,ListaIngredientes!$A$5:$F$155,2,FALSE),"") | F14: =IFERROR(VLOOKUP(A14,ListaIngredientes!$A$5:$F$155,6,FALSE),"") | H14: =IFERROR(E14*F14,"")
B15: =IFERROR(VLOOKUP(A15,ListaIngredientes!$A$5:$F$155,2,FALSE),"") | F15: =IFERROR(VLOOKUP(A15,ListaIngredientes!$A$5:$F$155,6,FALSE),"") | H15: =IFERROR(E15*F15,"")
B16: =IFERROR(VLOOKUP(A16,ListaIngredientes!$A$5:$F$155,2,FALSE),"") | F16: =IFERROR(VLOOKUP(A16,ListaIngredientes!$A$5:$F$155,6,FALSE),"") | H16: =IFERROR(E16*F16,"")
B17: =IFERROR(VLOOKUP(A17,ListaIngredientes!$A$5:$F$155,2,FALSE),"") | D17: =IFERROR(VLOOKUP(A17,Tabela2[],3,FALSE),"") | F17: =IFERROR(VLOOKUP(A17,ListaIngredientes!$A$5:$F$155,6,FALSE),"") | H17: =IFERROR(E17*F17,"")
B18: =IFERROR(VLOOKUP(A18,ListaIngredientes!$A$5:$F$155,2,FALSE),"") | D18: =IFERROR(VLOOKUP(A18,Tabela2[],3,FALSE),"") | F18: =IFERROR(VLOOKUP(A18,ListaIngredientes!$A$5:$F$155,6,FALSE),"") | H18: =IFERROR(E18*F18,"")
B19: =IFERROR(VLOOKUP(A19,ListaIngredientes!$A$5:$F$155,2,FALSE),"") | D19: =IFERROR(VLOOKUP(A19,Tabela2[],3,FALSE),"") | F19: =IFERROR(VLOOKUP(A19,ListaIngredientes!$A$5:$F$155,6,FALSE),"") | H19: =IFERROR(E19*F19,"")
B20: =IFERROR(VLOOKUP(A20,ListaIngredientes!$A$5:$F$155,2,FALSE),"") | D20: =IFERROR(VLOOKUP(A20,Tabela2[],3,FALSE),"") | F20: =IFERROR(VLOOKUP(A20,ListaIngredientes!$A$5:$F$155,6,FALSE),"") | H20: =IFERROR(E20*F20,"")
B21: =IFERROR(VLOOKUP(A21,ListaIngredientes!$A$5:$F$155,2,FALSE),"") | D21: =IFERROR(VLOOKUP(A21,Tabela2[],3,FALSE),"") | F21: =IFERROR(VLOOKUP(A21,ListaIngredientes!$A$5:$F$155,6,FALSE),"") | H21: =IFERROR(E21*F21,"")
B22: =IFERROR(VLOOKUP(A22,ListaIngredientes!$A$5:$F$155,2,FALSE),"") | D22: =IFERROR(VLOOKUP(A22,Tabela2[],3,FALSE),"") | F22: =IFERROR(VLOOKUP(A22,ListaIngredientes!$A$5:$F$155,6,FALSE),"") | H22: =IFERROR(E22*F22,"")
B23: =IFERROR(VLOOKUP(A23,ListaIngredientes!$A$5:$F$155,2,FALSE),"") | D23: =IFERROR(VLOOKUP(A23,Tabela2[],3,FALSE),"") | F23: =IFERROR(VLOOKUP(A23,ListaIngredientes!$A$5:$F$155,6,FALSE),"") | H23: =IFERROR(E23*F23,"")
B24: =IFERROR(VLOOKUP(A24,ListaIngredientes!$A$5:$F$155,2,FALSE),"") | D24: =IFERROR(VLOOKUP(A24,Tabela2[],3,FALSE),"") | F24: =IFERROR(VLOOKUP(A24,ListaIngredientes!$A$5:$F$155,6,FALSE),"") | H24: =IFERROR(E24*F24,"")
B25: =IFERROR(VLOOKUP(A25,ListaIngredientes!$A$5:$F$155,2,FALSE),"") | D25: =IFERROR(VLOOKUP(A25,Tabela2[],3,FALSE),"") | F25: =IFERROR(VLOOKUP(A25,ListaIngredientes!$A$5:$F$155,6,FALSE),"") | H25: =IFERROR(E25*F25,"")
B26: =IFERROR(VLOOKUP(A26,ListaIngredientes!$A$5:$F$155,2,FALSE),"") | D26: =IFERROR(VLOOKUP(A26,Tabela2[],3,FALSE),"") | F26: =IFERROR(VLOOKUP(A26,ListaIngredientes!$A$5:$F$155,6,FALSE),"") | H26: =IFERROR(E26*F26,"")
B27: =IFERROR(VLOOKUP(A27,ListaIngredientes!$A$5:$F$155,2,FALSE),"") | D27: =IFERROR(VLOOKUP(A27,Tabela2[],3,FALSE),"") | F27: =IFERROR(VLOOKUP(A27,ListaIngredientes!$A$5:$F$155,6,FALSE),"") | H27: =IFERROR(E27*F27,"")
F28: soma | H28: =SUM(H8:H27) -> 2.8

Sheet CAJUZINHO
A1: cod | B1: 501 | C1: =VLOOKUP(B1,PRODUTOS!$A$7:$E$204,2,FALSE) -> P A S T E L | E1: =C3 -> 5.517537 | G1: SOBREMESA/DOCE
A2: Despesas Fixas | C2: 0.2 | E2: Preço Venda Unit | G2: =IFERROR(C3/(1-C2-C5),"") -> 18.39179
A3: Custo Unitário | C3: =IFERROR(C6/C4,"") -> 5.517537 | E3: Luro s/Venda | G3: =G2*C5 -> 9.1958949
A4: Quantidade Produzida | C4: 13 | E4: Preço Praticado | G4: 15
A5: Lucro s/Venda | C5: 0.5 | E5: Lucro Praticado | G5: =1-C3/G4-C2 -> 0.4321642
A6: Gasto Total | C6: =H28 -> 71.72798 | E6: Lucro Praticado | G6: =G5*G4 -> 6.482463
A7: cod Prod | B7: Descrição ingredientes | D7: unid | E7: quantiadade | F7: valor $ | H7: Subtotal
A8: 101 | B8: =IFERROR(VLOOKUP(A8,ListaIngredientes!$A$5:$F$155,2,FALSE),"") | D8: =IFERROR(VLOOKUP(A8,Tabela2[],3,FALSE),"") | E8: 8 | F8: =IFERROR(VLOOKUP(A8,ListaIngredientes!$A$5:$F$155,6,FALSE),"") | H8: =IFERROR(E8*F8,"")
A9: 102 | B9: =IFERROR(VLOOKUP(A9,ListaIngredientes!$A$5:$F$155,2,FALSE),"") -> Ovos Branco | D9: KG | E9: 35 | F9: =IFERROR(VLOOKUP(A9,ListaIngredientes!$A$5:$F$155,6,FALSE),"") -> 1.6666667 | H9: =IFERROR(E9*F9,"") -> 58.333333
A10: 230 | B10: =IFERROR(VLOOKUP(A10,ListaIngredientes!$A$5:$F$155,2,FALSE),"") -> 0 | D10: kg | E10: 45 | F10: =IFERROR(VLOOKUP(A10,ListaIngredientes!$A$5:$F$155,6,FALSE),"") -> 0.149 | H10: =IFERROR(E10*F10,"") -> 6.705
A11: 139 | B11: =IFERROR(VLOOKUP(A11,ListaIngredientes!$A$5:$F$155,2,FALSE),"") -> cravo da india | D11: =IFERROR(VLOOKUP(A11,Tabela2[],3,FALSE),"") -> g | E11: 200 | F11: =IFERROR(VLOOKUP(A11,ListaIngredientes!$A$5:$F$155,6,FALSE),"") -> 0.00058823529 | H11: =IFERROR(E11*F11,"") -> 0.11764706
A12: 143 | B12: =IFERROR(VLOOKUP(A12,ListaIngredientes!$A$5:$F$155,2,FALSE),"") -> 0 | D12: U | E12: 8 | F12: =IFERROR(VLOOKUP(A12,ListaIngredientes!$A$5:$F$155,6,FALSE),"") -> 0 | H12: =IFERROR(E12*F12,"") -> 0
A13: 176 | B13: =IFERROR(VLOOKUP(A13,ListaIngredientes!$A$5:$F$155,2,FALSE),"") -> forminha de brigadeiro | D13: U | E13: 8 | F13: =IFERROR(VLOOKUP(A13,ListaIngredientes!$A$5:$F$155,6,FALSE),"") -> 0.0215 | H13: =IFERROR(E13*F13,"") -> 0.172
A14: 174 | B14: =IFERROR(VLOOKUP(A14,ListaIngredientes!$A$5:$F$155,2,FALSE),"") -> Galvanatec 679 | D14: U | E14: 8 | F14: =IFERROR(VLOOKUP(A14,ListaIngredientes!$A$5:$F$155,6,FALSE),"") -> 0.8 | H14: =IFERROR(E14*F14,"") -> 6.4
B15: =IFERROR(VLOOKUP(A15,ListaIngredientes!$A$5:$F$155,2,FALSE),"") | F15: =IFERROR(VLOOKUP(A15,ListaIngredientes!$A$5:$F$155,6,FALSE),"") | H15: =IFERROR(E15*F15,"")
B16: =IFERROR(VLOOKUP(A16,ListaIngredientes!$A$5:$F$155,2,FALSE),"") | F16: =IFERROR(VLOOKUP(A16,ListaIngredientes!$A$5:$F$155,6,FALSE),"") | H16: =IFERROR(E16*F16,"")
B17: =IFERROR(VLOOKUP(A17,ListaIngredientes!$A$5:$F$155,2,FALSE),"") | D17: =IFERROR(VLOOKUP(A17,Tabela2[],3,FALSE),"") | F17: =IFERROR(VLOOKUP(A17,ListaIngredientes!$A$5:$F$155,6,FALSE),"") | H17: =IFERROR(E17*F17,"")
B18: =IFERROR(VLOOKUP(A18,ListaIngredientes!$A$5:$F$155,2,FALSE),"") | D18: =IFERROR(VLOOKUP(A18,Tabela2[],3,FALSE),"") | F18: =IFERROR(VLOOKUP(A18,ListaIngredientes!$A$5:$F$155,6,FALSE),"") | H18: =IFERROR(E18*F18,"")
B19: =IFERROR(VLOOKUP(A19,ListaIngredientes!$A$5:$F$155,2,FALSE),"") | D19: =IFERROR(VLOOKUP(A19,Tabela2[],3,FALSE),"") | F19: =IFERROR(VLOOKUP(A19,ListaIngredientes!$A$5:$F$155,6,FALSE),"") | H19: =IFERROR(E19*F19,"")
B20: =IFERROR(VLOOKUP(A20,ListaIngredientes!$A$5:$F$155,2,FALSE),"") | D20: =IFERROR(VLOOKUP(A20,Tabela2[],3,FALSE),"") | F20: =IFERROR(VLOOKUP(A20,ListaIngredientes!$A$5:$F$155,6,FALSE),"") | H20: =IFERROR(E20*F20,"")
B21: =IFERROR(VLOOKUP(A21,ListaIngredientes!$A$5:$F$155,2,FALSE),"") | D21: =IFERROR(VLOOKUP(A21,Tabela2[],3,FALSE),"") | F21: =IFERROR(VLOOKUP(A21,ListaIngredientes!$A$5:$F$155,6,FALSE),"") | H21: =IFERROR(E21*F21,"")
B22: =IFERROR(VLOOKUP(A22,ListaIngredientes!$A$5:$F$155,2,FALSE),"") | D22: =IFERROR(VLOOKUP(A22,Tabela2[],3,FALSE),"") | F22: =IFERROR(VLOOKUP(A22,ListaIngredientes!$A$5:$F$155,6,FALSE),"") | H22: =IFERROR(E22*F22,"")
B23: =IFERROR(VLOOKUP(A23,ListaIngredientes!$A$5:$F$155,2,FALSE),"") | D23: =IFERROR(VLOOKUP(A23,Tabela2[],3,FALSE),"") | F23: =IFERROR(VLOOKUP(A23,ListaIngredientes!$A$5:$F$155,6,FALSE),"") | H23: =IFERROR(E23*F23,"")
B24: =IFERROR(VLOOKUP(A24,ListaIngredientes!$A$5:$F$155,2,FALSE),"") | D24: =IFERROR(VLOOKUP(A24,Tabela2[],3,FALSE),"") | F24: =IFERROR(VLOOKUP(A24,ListaIngredientes!$A$5:$F$155,6,FALSE),"") | H24: =IFERROR(E24*F24,"")
B25: =IFERROR(VLOOKUP(A25,ListaIngredientes!$A$5:$F$155,2,FALSE),"") | D25: =IFERROR(VLOOKUP(A25,Tabela2[],3,FALSE),"") | F25: =IFERROR(VLOOKUP(A25,ListaIngredientes!$A$5:$F$155,6,FALSE),"") | H25: =IFERROR(E25*F25,"")
B26: =IFERROR(VLOOKUP(A26,ListaIngredientes!$A$5:$F$155,2,FALSE),"") | D26: =IFERROR(VLOOKUP(A26,Tabela2[],3,FALSE),"") | F26: =IFERROR(VLOOKUP(A26,ListaIngredientes!$A$5:$F$155,6,FALSE),"") | H26: =IFERROR(E26*F26,"")
B27: =IFERROR(VLOOKUP(A27,ListaIngredientes!$A$5:$F$155,2,FALSE),"") | D27: =IFERROR(VLOOKUP(A27,Tabela2[],3,FALSE),"") | F27: =IFERROR(VLOOKUP(A27,ListaIngredientes!$A$5:$F$155,6,FALSE),"") | H27: =IFERROR(E27*F27,"")
F28: soma | H28: =SUM(H8:H27) -> 71.72798

Sheet BEIJINHO
A1: cod | B1: 501 | C1: =VLOOKUP(B1,PRODUTOS!$A$7:$E$204,2,FALSE) -> P A S T E L | E1: =C3 -> 2.8140226 | G1: SOBREMESA/DOCE
A2: Despesas Fixas | C2: 0.2 | E2: Preço Venda Unit | G2: =IFERROR(C3/(1-C2-C5),"") -> 9.3800754
A3: Custo Unitário | C3: =IFERROR(C6/C4,"") -> 2.8140226 | E3: Luro s/Venda | G3: =G2*C5 -> 4.6900377
A4: Quantidade Produzida | C4: 13 | E4: Preço Praticado | G4: 15
A5: Lucro s/Venda | C5: 0.5 | E5: Lucro Praticado | G5: =1-C3/G4-C2 -> 0.61239849
A6: Gasto Total | C6: =H28 -> 36.582294 | E6: Lucro Praticado | G6: =G5*G4 -> 9.1859774
A7: cod Prod | B7: Descrição ingredientes | D7: unid | E7: quantiadade | F7: valor $ | H7: Subtotal
A8: 101 | B8: =IFERROR(VLOOKUP(A8,ListaIngredientes!$A$5:$F$155,2,FALSE),"") | D8: =IFERROR(VLOOKUP(A8,Tabela2[],3,FALSE),"") | E8: 18 | F8: =IFERROR(VLOOKUP(A8,ListaIngredientes!$A$5:$F$155,6,FALSE),"") | H8: =IFERROR(E8*F8,"")
A9: 126 | B9: =IFERROR(VLOOKUP(A9,ListaIngredientes!$A$5:$F$155,2,FALSE),"") -> CHOCOLTE BRANCO | D9: KG | E9: 70 | F9: =IFERROR(VLOOKUP(A9,ListaIngredientes!$A$5:$F$155,6,FALSE),"") -> 0.159 | H9: =IFERROR(E9*F9,"") -> 11.13
A10: 230 | B10: =IFERROR(VLOOKUP(A10,ListaIngredientes!$A$5:$F$155,2,FALSE),"") -> 0 | D10: kg | E10: 70 | F10: =IFERROR(VLOOKUP(A10,ListaIngredientes!$A$5:$F$155,6,FALSE),"") -> 0.149 | H10: =IFERROR(E10*F10,"") -> 10.43
A11: 139 | B11: =IFERROR(VLOOKUP(A11,ListaIngredientes!$A$5:$F$155,2,FALSE),"") -> cravo da india | D11: =IFERROR(VLOOKUP(A11,Tabela2[],3,FALSE),"") -> g | E11: 400 | F11: =IFERROR(VLOOKUP(A11,ListaIngredientes!$A$5:$F$155,6,FALSE),"") -> 0.00058823529 | H11: =IFERROR(E11*F11,"") -> 0.23529412
A12: 176 | B12: =IFERROR(VLOOKUP(A12,ListaIngredientes!$A$5:$F$155,2,FALSE),"") -> forminha de brigadeiro | D12: U | E12: 18 | F12: =IFERROR(VLOOKUP(A12,ListaIngredientes!$A$5:$F$155,6,FALSE),"") -> 0.0215 | H12: =IFERROR(E12*F12,"") -> 0.387
A13: 174 | B13: =IFERROR(VLOOKUP(A13,ListaIngredientes!$A$5:$F$155,2,FALSE),"") -> Galvanatec 679 | D13: U | E13: 18 | F13: =IFERROR(VLOOKUP(A13,ListaIngredientes!$A$5:$F$155,6,FALSE),"") -> 0.8 | H13: =IFERROR(E13*F13,"") -> 14.4
B14: =IFERROR(VLOOKUP(A14,ListaIngredientes!$A$5:$F$155,2,FALSE),"") | F14: =IFERROR(VLOOKUP(A14,ListaIngredientes!$A$5:$F$155,6,FALSE),"") | H14: =IFERROR(E14*F14,"")
B15: =IFERROR(VLOOKUP(A15,ListaIngredientes!$A$5:$F$155,2,FALSE),"") | F15: =IFERROR(VLOOKUP(A15,ListaIngredientes!$A$5:$F$155,6,FALSE),"") | H15: =IFERROR(E15*F15,"")
B16: =IFERROR(VLOOKUP(A16,ListaIngredientes!$A$5:$F$155,2,FALSE),"") | F16: =IFERROR(VLOOKUP(A16,ListaIngredientes!$A$5:$F$155,6,FALSE),"") | H16: =IFERROR(E16*F16,"")
B17: =IFERROR(VLOOKUP(A17,ListaIngredientes!$A$5:$F$155,2,FALSE),"") | D17: =IFERROR(VLOOKUP(A17,Tabela2[],3,FALSE),"") | F17: =IFERROR(VLOOKUP(A17,ListaIngredientes!$A$5:$F$155,6,FALSE),"") | H17: =IFERROR(E17*F17,"")
B18: =IFERROR(VLOOKUP(A18,ListaIngredientes!$A$5:$F$155,2,FALSE),"") | D18: =IFERROR(VLOOKUP(A18,Tabela2[],3,FALSE),"") | F18: =IFERROR(VLOOKUP(A18,ListaIngredientes!$A$5:$F$155,6,FALSE),"") | H18: =IFERROR(E18*F18,"")
B19: =IFERROR(VLOOKUP(A19,ListaIngredientes!$A$5:$F$155,2,FALSE),"") | D19: =IFERROR(VLOOKUP(A19,Tabela2[],3,FALSE),"") | F19: =IFERROR(VLOOKUP(A19,ListaIngredientes!$A$5:$F$155,6,FALSE),"") | H19: =IFERROR(E19*F19,"")
B20: =IFERROR(VLOOKUP(A20,ListaIngredientes!$A$5:$F$155,2,FALSE),"") | D20: =IFERROR(VLOOKUP(A20,Tabela2[],3,FALSE),"") | F20: =IFERROR(VLOOKUP(A20,ListaIngredientes!$A$5:$F$155,6,FALSE),"") | H20: =IFERROR(E20*F20,"")
B21: =IFERROR(VLOOKUP(A21,ListaIngredientes!$A$5:$F$155,2,FALSE),"") | D21: =IFERROR(VLOOKUP(A21,Tabela2[],3,FALSE),"") | F21: =IFERROR(VLOOKUP(A21,ListaIngredientes!$A$5:$F$155,6,FALSE),"") | H21: =IFERROR(E21*F21,"")
B22: =IFERROR(VLOOKUP(A22,ListaIngredientes!$A$5:$F$155,2,FALSE),"") | D22: =IFERROR(VLOOKUP(A22,Tabela2[],3,FALSE),"") | F22: =IFERROR(VLOOKUP(A22,ListaIngredientes!$A$5:$F$155,6,FALSE),"") | H22: =IFERROR(E22*F22,"")
B23: =IFERROR(VLOOKUP(A23,ListaIngredientes!$A$5:$F$155,2,FALSE),"") | D23: =IFERROR(VLOOKUP(A23,Tabela2[],3,FALSE),"") | F23: =IFERROR(VLOOKUP(A23,ListaIngredientes!$A$5:$F$155,6,FALSE),"") | H23: =IFERROR(E23*F23,"")
B24: =IFERROR(VLOOKUP(A24,ListaIngredientes!$A$5:$F$155,2,FALSE),"") | D24: =IFERROR(VLOOKUP(A24,Tabela2[],3,FALSE),"") | F24: =IFERROR(VLOOKUP(A24,ListaIngredientes!$A$5:$F$155,6,FALSE),"") | H24: =IFERROR(E24*F24,"")
B25: =IFERROR(VLOOKUP(A25,ListaIngredientes!$A$5:$F$155,2,FALSE),"") | D25: =IFERROR(VLOOKUP(A25,Tabela2[],3,FALSE),"") | F25: =IFERROR(VLOOKUP(A25,ListaIngredientes!$A$5:$F$155,6,FALSE),"") | H25: =IFERROR(E25*F25,"")
B26: =IFERROR(VLOOKUP(A26,ListaIngredientes!$A$5:$F$155,2,FALSE),"") | D26: =IFERROR(VLOOKUP(A26,Tabela2[],3,FALSE),"") | F26: =IFERROR(VLOOKUP(A26,ListaIngredientes!$A$5:$F$155,6,FALSE),"") | H26: =IFERROR(E26*F26,"")
B27: =IFERROR(VLOOKUP(A27,ListaIngredientes!$A$5:$F$155,2,FALSE),"") | D27: =IFERROR(VLOOKUP(A27,Tabela2[],3,FALSE),"") | F27: =IFERROR(VLOOKUP(A27,ListaIngredientes!$A$5:$F$155,6,FALSE),"") | H27: =IFERROR(E27*F27,"")
F28: soma | H28: =SUM(H8:H27) -> 36.582294

Sheet COCADA CREMOSA
A1: cod | B1: 501 | C1: =VLOOKUP(B1,PRODUTOS!$A$7:$E$204,2,FALSE) -> P A S T E L | E1: =C3 -> 3.3531222 | G1: SOBREMESA/DOCE
A2: Despesas Fixas | C2: 0.2 | E2: Preço Venda Unit | G2: =IFERROR(C3/(1-C2-C5),"") -> 11.177074
A3: Custo Unitário | C3: =IFERROR(C6/C4,"") -> 3.3531222 | E3: Luro s/Venda | G3: =G2*C5 -> 5.588537
A4: Quantidade Produzida | C4: 13 | E4: Preço Praticado | G4: 15
A5: Lucro s/Venda | C5: 0.5 | E5: Lucro Praticado | G5: =1-C3/G4-C2 -> 0.57645852
A6: Gasto Total | C6: =SUM(H8:H28) -> 43.590588 | E6: Lucro Praticado | G6: =G5*G4 -> 8.6468778
A7: cod Prod | B7: Descrição ingredientes | D7: unid | E7: quantiadade | F7: valor $ | H7: Subtotal
A8: 101 | B8: =IFERROR(VLOOKUP(A8,ListaIngredientes!$A$5:$F$155,2,FALSE),"") | D8: =IFERROR(VLOOKUP(A8,Tabela2[],3,FALSE),"") | E8: 4 | F8: =IFERROR(VLOOKUP(A8,ListaIngredientes!$A$5:$F$155,6,FALSE),"") | H8: =IFERROR(E8*F8,"")
A9: 126 | B9: =IFERROR(VLOOKUP(A9,ListaIngredientes!$A$5:$F$155,2,FALSE),"") -> CHOCOLTE BRANCO | D9: KG | E9: 70 | F9: =IFERROR(VLOOKUP(A9,ListaIngredientes!$A$5:$F$155,6,FALSE),"") -> 0.159 | H9: =IFERROR(E9*F9,"") -> 11.13
A10: 230 | B10: =IFERROR(VLOOKUP(A10,ListaIngredientes!$A$5:$F$155,2,FALSE),"") -> 0 | D10: kg | E10: 70 | F10: =IFERROR(VLOOKUP(A10,ListaIngredientes!$A$5:$F$155,6,FALSE),"") -> 0.149 | H10: =IFERROR(E10*F10,"") -> 10.43
A11: 139 | B11: =IFERROR(VLOOKUP(A11,ListaIngredientes!$A$5:$F$155,2,FALSE),"") -> cravo da india | D11: =IFERROR(VLOOKUP(A11,Tabela2[],3,FALSE),"") -> g | E11: 400 | F11: =IFERROR(VLOOKUP(A11,ListaIngredientes!$A$5:$F$155,6,FALSE),"") -> 0.00058823529 | H11: =IFERROR(E11*F11,"") -> 0.23529412
B12: =IFERROR(VLOOKUP(A12,ListaIngredientes!$A$5:$F$155,2,FALSE),"") | F12: =IFERROR(VLOOKUP(A12,ListaIngredientes!$A$5:$F$155,6,FALSE),"") | H12: =IFERROR(E12*F12,"")
B13: =IFERROR(VLOOKUP(A13,ListaIngredientes!$A$5:$F$155,2,FALSE),"") | F13: =IFERROR(VLOOKUP(A13,ListaIngredientes!$A$5:$F$155,6,FALSE),"") | H13: =IFERROR(E13*F13,"")
B14: =IFERROR(VLOOKUP(A14,ListaIngredientes!$A$5:$F$155,2,FALSE),"") | F14: =IFERROR(VLOOKUP(A14,ListaIngredientes!$A$5:$F$155,6,FALSE),"") | H14: =IFERROR(E14*F14,"")
B15: =IFERROR(VLOOKUP(A15,ListaIngredientes!$A$5:$F$155,2,FALSE),"") | F15: =IFERROR(VLOOKUP(A15,ListaIngredientes!$A$5:$F$155,6,FALSE),"") | H15: =IFERROR(E15*F15,"")
B16: =IFERROR(VLOOKUP(A16,ListaIngredientes!$A$5:$F$155,2,FALSE),"") | F16: =IFERROR(VLOOKUP(A16,ListaIngredientes!$A$5:$F$155,6,FALSE),"") | H16: =IFERROR(E16*F16,"")
B17: =IFERROR(VLOOKUP(A17,ListaIngredientes!$A$5:$F$155,2,FALSE),"") | D17: =IFERROR(VLOOKUP(A17,Tabela2[],3,FALSE),"") | F17: =IFERROR(VLOOKUP(A17,ListaIngredientes!$A$5:$F$155,6,FALSE),"") | H17: =IFERROR(E17*F17,"")
B18: =IFERROR(VLOOKUP(A18,ListaIngredientes!$A$5:$F$155,2,FALSE),"") | D18: =IFERROR(VLOOKUP(A18,Tabela2[],3,FALSE),"") | F18: =IFERROR(VLOOKUP(A18,ListaIngredientes!$A$5:$F$155,6,FALSE),"") | H18: =IFERROR(E18*F18,"")
B19: =IFERROR(VLOOKUP(A19,ListaIngredientes!$A$5:$F$155,2,FALSE),"") | D19: =IFERROR(VLOOKUP(A19,Tabela2[],3,FALSE),"") | F19: =IFERROR(VLOOKUP(A19,ListaIngredientes!$A$5:$F$155,6,FALSE),"") | H19: =IFERROR(E19*F19,"")
B20: =IFERROR(VLOOKUP(A20,ListaIngredientes!$A$5:$F$155,2,FALSE),"") | D20: =IFERROR(VLOOKUP(A20,Tabela2[],3,FALSE),"") | F20: =IFERROR(VLOOKUP(A20,ListaIngredientes!$A$5:$F$155,6,FALSE),"") | H20: =IFERROR(E20*F20,"")
B21: =IFERROR(VLOOKUP(A21,ListaIngredientes!$A$5:$F$155,2,FALSE),"") | D21: =IFERROR(VLOOKUP(A21,Tabela2[],3,FALSE),"") | F21: =IFERROR(VLOOKUP(A21,ListaIngredientes!$A$5:$F$155,6,FALSE),"") | H21: =IFERROR(E21*F21,"")
B22: =IFERROR(VLOOKUP(A22,ListaIngredientes!$A$5:$F$155,2,FALSE),"") | D22: =IFERROR(VLOOKUP(A22,Tabela2[],3,FALSE),"") | F22: =IFERROR(VLOOKUP(A22,ListaIngredientes!$A$5:$F$155,6,FALSE),"") | H22: =IFERROR(E22*F22,"")
B23: =IFERROR(VLOOKUP(A23,ListaIngredientes!$A$5:$F$155,2,FALSE),"") | D23: =IFERROR(VLOOKUP(A23,Tabela2[],3,FALSE),"") | F23: =IFERROR(VLOOKUP(A23,ListaIngredientes!$A$5:$F$155,6,FALSE),"") | H23: =IFERROR(E23*F23,"")
B24: =IFERROR(VLOOKUP(A24,ListaIngredientes!$A$5:$F$155,2,FALSE),"") | D24: =IFERROR(VLOOKUP(A24,Tabela2[],3,FALSE),"") | F24: =IFERROR(VLOOKUP(A24,ListaIngredientes!$A$5:$F$155,6,FALSE),"") | H24: =IFERROR(E24*F24,"")
B25: =IFERROR(VLOOKUP(A25,ListaIngredientes!$A$5:$F$155,2,FALSE),"") | D25: =IFERROR(VLOOKUP(A25,Tabela2[],3,FALSE),"") | F25: =IFERROR(VLOOKUP(A25,ListaIngredientes!$A$5:$F$155,6,FALSE),"") | H25: =IFERROR(E25*F25,"")
B26: =IFERROR(VLOOKUP(A26,ListaIngredientes!$A$5:$F$155,2,FALSE),"") | D26: =IFERROR(VLOOKUP(A26,Tabela2[],3,FALSE),"") | F26: =IFERROR(VLOOKUP(A26,ListaIngredientes!$A$5:$F$155,6,FALSE),"") | H26: =IFERROR(E26*F26,"")
B27: =IFERROR(VLOOKUP(A27,ListaIngredientes!$A$5:$F$155,2,FALSE),"") | D27: =IFERROR(VLOOKUP(A27,Tabela2[],3,FALSE),"") | F27: =IFERROR(VLOOKUP(A27,ListaIngredientes!$A$5:$F$155,6,FALSE),"") | H27: =IFERROR(E27*F27,"")
F28: soma | H28: =SUM(H8:H27) -> 21.795294

Sheet ALFAJOR
A1: cod | B1: 501 | C1: =VLOOKUP(B1,PRODUTOS!$A$7:$E$204,2,FALSE) -> P A S T E L | E1: =C3 -> 6.501478 | G1: SOBREMESA/DOCE
A2: Despesas Fixas | C2: 0.2 | E2: Preço Venda Unit | G2: =IFERROR(C3/(1-C2-C5),"") -> 21.671593
A3: Custo Unitário | C3: =IFERROR(C6/C4,"") -> 6.501478 | E3: Luro s/Venda | G3: =G2*C5 -> 10.835797
A4: Quantidade Produzida | C4: 13 | E4: Preço Praticado | G4: 15
A5: Lucro s/Venda | C5: 0.5 | E5: Lucro Praticado | G5: =1-C3/G4-C2 -> 0.36656813
A6: Gasto Total | C6: =SUM(H8:H28) -> 84.519214 | E6: Lucro Praticado | G6: =G5*G4 -> 5.498522
A7: cod Prod | B7: Descrição ingredientes | D7: unid | E7: quantiadade | F7: valor $ | H7: Subtotal
A8: 101 | B8: =IFERROR(VLOOKUP(A8,ListaIngredientes!$A$5:$F$155,2,FALSE),"") | D8: =IFERROR(VLOOKUP(A8,Tabela2[],3,FALSE),"") | E8: 12 | F8: =IFERROR(VLOOKUP(A8,ListaIngredientes!$A$5:$F$155,6,FALSE),"") | H8: =IFERROR(E8*F8,"")
A9: 203 | B9: =IFERROR(VLOOKUP(A9,ListaIngredientes!$A$5:$F$155,2,FALSE),"") -> 0 | D9: =IFERROR(VLOOKUP(A9,Tabela2[],3,FALSE),"") -> 0 | E9: 1 | F9: =IFERROR(VLOOKUP(A9,ListaIngredientes!$A$5:$F$155,6,FALSE),"") -> 0 | H9: =IFERROR(E9*F9,"") -> 0
A10: 230 | B10: =IFERROR(VLOOKUP(A10,ListaIngredientes!$A$5:$F$155,2,FALSE),"") -> 0 | D10: =IFERROR(VLOOKUP(A10,Tabela2[],3,FALSE),"") -> u | E10: 80 | F10: =IFERROR(VLOOKUP(A10,ListaIngredientes!$A$5:$F$155,6,FALSE),"") -> 0.149 | H10: =IFERROR(E10*F10,"") -> 11.92
A11: 125 | B11: =IFERROR(VLOOKUP(A11,ListaIngredientes!$A$5:$F$155,2,FALSE),"") -> 0 | D11: =IFERROR(VLOOKUP(A11,Tabela2[],3,FALSE),"") -> 0 | E11: 200 | F11: =IFERROR(VLOOKUP(A11,ListaIngredientes!$A$5:$F$155,6,FALSE),"") -> 0 | H11: =IFERROR(E11*F11,"") -> 0
A12: 158 | B12: =IFERROR(VLOOKUP(A12,ListaIngredientes!$A$5:$F$155,2,FALSE),"") -> ESSENCIA DE BAUNILHA | D12: =IFERROR(VLOOKUP(A12,Tabela2[],3,FALSE),"") -> ML | E12: 100 | F12: =IFERROR(VLOOKUP(A12,ListaIngredientes!$A$5:$F$155,6,FALSE),"") -> 0.099666667 | H12: =IFERROR(E12*F12,"") -> 9.9666667
A13: 159 | B13: =IFERROR(VLOOKUP(A13,ListaIngredientes!$A$5:$F$155,2,FALSE),"") -> essencia de mel | D13: =IFERROR(VLOOKUP(A13,Tabela2[],3,FALSE),"") -> u | E13: 20 | F13: =IFERROR(VLOOKUP(A13,ListaIngredientes!$A$5:$F$155,6,FALSE),"") -> 2.59 | H13: =IFERROR(E13*F13,"") -> 51.8
A14: 160 | B14: =IFERROR(VLOOKUP(A14,ListaIngredientes!$A$5:$F$155,2,FALSE),"") -> farinha de amendoas | D14: =IFERROR(VLOOKUP(A14,Tabela2[],3,FALSE),"") -> kg | E14: 15 | F14: =IFERROR(VLOOKUP(A14,ListaIngredientes!$A$5:$F$155,6,FALSE),"") -> 0.063 | H14: =IFERROR(E14*F14,"") -> 0.945
A15: 246 | B15: =IFERROR(VLOOKUP(A15,ListaIngredientes!$A$5:$F$155,2,FALSE),"") -> Uva Passas | D15: =IFERROR(VLOOKUP(A15,Tabela2[],3,FALSE),"") -> KG | E15: 8 | F15: =IFERROR(VLOOKUP(A15,ListaIngredientes!$A$5:$F$155,6,FALSE),"") -> 0.018 | H15: =IFERROR(E15*F15,"") -> 0.144
A16: 182 | B16: =IFERROR(VLOOKUP(A16,ListaIngredientes!$A$5:$F$155,2,FALSE),"") -> GERGILIM | D16: =IFERROR(VLOOKUP(A16,Tabela2[],3,FALSE),"") -> KG | E16: 2 | F16: =IFERROR(VLOOKUP(A16,ListaIngredientes!$A$5:$F$155,6,FALSE),"") -> 0.029 | H16: =IFERROR(E16*F16,"") -> 0.058
A17: 194 | B17: =IFERROR(VLOOKUP(A17,ListaIngredientes!$A$5:$F$155,2,FALSE),"") -> Maçã | D17: =IFERROR(VLOOKUP(A17,Tabela2[],3,FALSE),"") -> kg | E17: 30 | F17: =IFERROR(VLOOKUP(A17,ListaIngredientes!$A$5:$F$155,6,FALSE),"") -> 0.00399 | H17: =IFERROR(E17*F17,"") -> 0.1197
A18: 139 | B18: =IFERROR(VLOOKUP(A18,ListaIngredientes!$A$5:$F$155,2,FALSE),"") -> cravo da india | D18: =IFERROR(VLOOKUP(A18,Tabela2[],3,FALSE),"") -> g | E18: 200 | F18: =IFERROR(VLOOKUP(A18,ListaIngredientes!$A$5:$F$155,6,FALSE),"") -> 0.00058823529 | H18: =IFERROR(E18*F18,"") -> 0.11764706
A19: 224 | B19: =IFERROR(VLOOKUP(A19,ListaIngredientes!$A$5:$F$155,2,FALSE),"") -> SACO PASCOA 32X32 | D19: =IFERROR(VLOOKUP(A19,Tabela2[],3,FALSE),"") -> kg | E19: 12 | F19: =IFERROR(VLOOKUP(A19,ListaIngredientes!$A$5:$F$155,6,FALSE),"") -> 0.0386 | H19: =IFERROR(E19*F19,"") -> 0.4632
A20: 156 | B20: =IFERROR(VLOOKUP(A20,ListaIngredientes!$A$5:$F$155,2,FALSE),"") -> embalagem quiche | D20: =IFERROR(VLOOKUP(A20,Tabela2[],3,FALSE),"") -> u | E20: 15 | F20: =IFERROR(VLOOKUP(A20,ListaIngredientes!$A$5:$F$155,6,FALSE),"") -> 0.599 | H20: =IFERROR(E20*F20,"") -> 8.985
B21: =IFERROR(VLOOKUP(A21,ListaIngredientes!$A$5:$F$155,2,FALSE),"") | D21: =IFERROR(VLOOKUP(A21,Tabela2[],3,FALSE),"") | F21: =IFERROR(VLOOKUP(A21,ListaIngredientes!$A$5:$F$155,6,FALSE),"") | H21: =IFERROR(E21*F21,"")
B22: =IFERROR(VLOOKUP(A22,ListaIngredientes!$A$5:$F$155,2,FALSE),"") | D22: =IFERROR(VLOOKUP(A22,Tabela2[],3,FALSE),"") | F22: =IFERROR(VLOOKUP(A22,ListaIngredientes!$A$5:$F$155,6,FALSE),"") | H22: =IFERROR(E22*F22,"")
B23: =IFERROR(VLOOKUP(A23,ListaIngredientes!$A$5:$F$155,2,FALSE),"") | D23: =IFERROR(VLOOKUP(A23,Tabela2[],3,FALSE),"") | F23: =IFERROR(VLOOKUP(A23,ListaIngredientes!$A$5:$F$155,6,FALSE),"") | H23: =IFERROR(E23*F23,"")
B24: =IFERROR(VLOOKUP(A24,ListaIngredientes!$A$5:$F$155,2,FALSE),"") | D24: =IFERROR(VLOOKUP(A24,Tabela2[],3,FALSE),"") | F24: =IFERROR(VLOOKUP(A24,ListaIngredientes!$A$5:$F$155,6,FALSE),"") | H24: =IFERROR(E24*F24,"")
B25: =IFERROR(VLOOKUP(A25,ListaIngredientes!$A$5:$F$155,2,FALSE),"") | D25: =IFERROR(VLOOKUP(A25,Tabela2[],3,FALSE),"") | F25: =IFERROR(VLOOKUP(A25,ListaIngredientes!$A$5:$F$155,6,FALSE),"") | H25: =IFERROR(E25*F25,"")
B26: =IFERROR(VLOOKUP(A26,ListaIngredientes!$A$5:$F$155,2,FALSE),"") | D26: =IFERROR(VLOOKUP(A26,Tabela2[],3,FALSE),"") | F26: =IFERROR(VLOOKUP(A26,ListaIngredientes!$A$5:$F$155,6,FALSE),"") | H26: =IFERROR(E26*F26,"")
B27: =IFERROR(VLOOKUP(A27,ListaIngredientes!$A$5:$F$155,2,FALSE),"") | D27: =IFERROR(VLOOKUP(A27,Tabela2[],3,FALSE),"") | F27: =IFERROR(VLOOKUP(A27,ListaIngredientes!$A$5:$F$155,6,FALSE),"") | H27: =IFERROR(E27*F27,"")
F28: soma | H28: =IFERROR(E28*F28,"")
H29: =SUM(H8:H27) -> 84.519214

Sheet PALHA ITALIANNA
A1: cod | B1: 501 | C1: =VLOOKUP(B1,PRODUTOS!$A$7:$E$204,2,FALSE) -> P A S T E L | E1: =C3 -> 10.772419 | G1: SOBREMESA/DOCE
A2: Despesas Fixas | C2: 0.2 | E2: Preço Venda Unit | G2: =IFERROR(C3/(1-C2-C5),"") -> 35.908065
A3: Custo Unitário | C3: =IFERROR(C6/C4,"") -> 10.772419 | E3: Luro s/Venda | G3: =G2*C5 -> 17.954032
A4: Quantidade Produzida | C4: 13 | E4: Preço Praticado | G4: 15
A5: Lucro s/Venda | C5: 0.5 | E5: Lucro Praticado | G5: =1-C3/G4-C2 -> 0.081838708
A6: Gasto Total | C6: =SUM(H8:H28) -> 140.04145 | E6: Lucro Praticado | G6: =G5*G4 -> 1.2275806
A7: cod Prod | B7: Descrição ingredientes | D7: unid | E7: quantiadade | F7: valor $ | H7: Subtotal
A8: 101 | B8: =IFERROR(VLOOKUP(A8,ListaIngredientes!$A$5:$F$155,2,FALSE),"") | D8: =IFERROR(VLOOKUP(A8,Tabela2[],3,FALSE),"") | E8: 12 | F8: =IFERROR(VLOOKUP(A8,ListaIngredientes!$A$5:$F$155,6,FALSE),"") | H8: =IFERROR(E8*F8,"")
A9: 143 | B9: =IFERROR(VLOOKUP(A9,ListaIngredientes!$A$5:$F$155,2,FALSE),"") -> 0 | D9: =IFERROR(VLOOKUP(A9,Tabela2[],3,FALSE),"") -> 0 | E9: 13 | F9: =IFERROR(VLOOKUP(A9,ListaIngredientes!$A$5:$F$155,6,FALSE),"") -> 0 | H9: =IFERROR(E9*F9,"") -> 0
A10: 230 | B10: =IFERROR(VLOOKUP(A10,ListaIngredientes!$A$5:$F$155,2,FALSE),"") -> 0 | D10: =IFERROR(VLOOKUP(A10,Tabela2[],3,FALSE),"") -> u | E10: 290 | F10: =IFERROR(VLOOKUP(A10,ListaIngredientes!$A$5:$F$155,6,FALSE),"") -> 0.149 | H10: =IFERROR(E10*F10,"") -> 43.21
A11: 125 | B11: =IFERROR(VLOOKUP(A11,ListaIngredientes!$A$5:$F$155,2,FALSE),"") -> 0 | D11: =IFERROR(VLOOKUP(A11,Tabela2[],3,FALSE),"") -> 0 | E11: 150 | F11: =IFERROR(VLOOKUP(A11,ListaIngredientes!$A$5:$F$155,6,FALSE),"") -> 0 | H11: =IFERROR(E11*F11,"") -> 0
A12: 158 | B12: =IFERROR(VLOOKUP(A12,ListaIngredientes!$A$5:$F$155,2,FALSE),"") -> ESSENCIA DE BAUNILHA | D12: =IFERROR(VLOOKUP(A12,Tabela2[],3,FALSE),"") -> ML | E12: 220 | F12: =IFERROR(VLOOKUP(A12,ListaIngredientes!$A$5:$F$155,6,FALSE),"") -> 0.099666667 | H12: =IFERROR(E12*F12,"") -> 21.926667
A13: 159 | B13: =IFERROR(VLOOKUP(A13,ListaIngredientes!$A$5:$F$155,2,FALSE),"") -> essencia de mel | D13: =IFERROR(VLOOKUP(A13,Tabela2[],3,FALSE),"") -> u | E13: 15 | F13: =IFERROR(VLOOKUP(A13,ListaIngredientes!$A$5:$F$155,6,FALSE),"") -> 2.59 | H13: =IFERROR(E13*F13,"") -> 38.85
A14: 160 | B14: =IFERROR(VLOOKUP(A14,ListaIngredientes!$A$5:$F$155,2,FALSE),"") -> farinha de amendoas | D14: =IFERROR(VLOOKUP(A14,Tabela2[],3,FALSE),"") -> kg | E14: 15 | F14: =IFERROR(VLOOKUP(A14,ListaIngredientes!$A$5:$F$155,6,FALSE),"") -> 0.063 | H14: =IFERROR(E14*F14,"") -> 0.945
A15: 246 | B15: =IFERROR(VLOOKUP(A15,ListaIngredientes!$A$5:$F$155,2,FALSE),"") -> Uva Passas | D15: =IFERROR(VLOOKUP(A15,Tabela2[],3,FALSE),"") -> KG | E15: 15 | F15: =IFERROR(VLOOKUP(A15,ListaIngredientes!$A$5:$F$155,6,FALSE),"") -> 0.018 | H15: =IFERROR(E15*F15,"") -> 0.27
A16: 182 | B16: =IFERROR(VLOOKUP(A16,ListaIngredientes!$A$5:$F$155,2,FALSE),"") -> GERGILIM | D16: =IFERROR(VLOOKUP(A16,Tabela2[],3,FALSE),"") -> KG | E16: 3 | F16: =IFERROR(VLOOKUP(A16,ListaIngredientes!$A$5:$F$155,6,FALSE),"") -> 0.029 | H16: =IFERROR(E16*F16,"") -> 0.087
A17: 194 | B17: =IFERROR(VLOOKUP(A17,ListaIngredientes!$A$5:$F$155,2,FALSE),"") -> Maçã | D17: =IFERROR(VLOOKUP(A17,Tabela2[],3,FALSE),"") -> kg | E17: 45 | F17: =IFERROR(VLOOKUP(A17,ListaIngredientes!$A$5:$F$155,6,FALSE),"") -> 0.00399 | H17: =IFERROR(E17*F17,"") -> 0.17955
A18: 139 | B18: =IFERROR(VLOOKUP(A18,ListaIngredientes!$A$5:$F$155,2,FALSE),"") -> cravo da india | D18: =IFERROR(VLOOKUP(A18,Tabela2[],3,FALSE),"") -> g | E18: 1000 | F18: =IFERROR(VLOOKUP(A18,ListaIngredientes!$A$5:$F$155,6,FALSE),"") -> 0.00058823529 | H18: =IFERROR(E18*F18,"") -> 0.58823529
A20: 105 | B20: =IFERROR(VLOOKUP(A20,ListaIngredientes!$A$5:$F$155,2,FALSE),"") -> Bananas | D20: =IFERROR(VLOOKUP(A20,Tabela2[],3,FALSE),"") -> duzias | E20: 50 | F20: =IFERROR(VLOOKUP(A20,ListaIngredientes!$A$5:$F$155,6,FALSE),"") -> 0.5 | H20: =IFERROR(E20*F20,"") -> 25
... A22: 156 | B22: =IFERROR(VLOOKUP(A22,ListaIngredientes!$A$5:$F$155,2,FALSE),"") -> embalagem quiche | D22: =IFERROR(VLOOKUP(A22,Tabela2[],3,FALSE),"") -> u | E22: 15 | F22: =IFERROR(VLOOKUP(A22,ListaIngredientes!$A$5:$F$155,6,FALSE),"") -> 0.599 | H22: =IFERROR(E22*F22,"") -> 8.985
B23: =IFERROR(VLOOKUP(A23,ListaIngredientes!$A$5:$F$155,2,FALSE),"") | D23: =IFERROR(VLOOKUP(A23,Tabela2[],3,FALSE),"") | F23: =IFERROR(VLOOKUP(A23,ListaIngredientes!$A$5:$F$155,6,FALSE),"") | H23: =IFERROR(E23*F23,"")
B24: =IFERROR(VLOOKUP(A24,ListaIngredientes!$A$5:$F$155,2,FALSE),"") | D24: =IFERROR(VLOOKUP(A24,Tabela2[],3,FALSE),"") | F24: =IFERROR(VLOOKUP(A24,ListaIngredientes!$A$5:$F$155,6,FALSE),"") | H24: =IFERROR(E24*F24,"")
B25: =IFERROR(VLOOKUP(A25,ListaIngredientes!$A$5:$F$155,2,FALSE),"") | D25: =IFERROR(VLOOKUP(A25,Tabela2[],3,FALSE),"") | F25: =IFERROR(VLOOKUP(A25,ListaIngredientes!$A$5:$F$155,6,FALSE),"") | H25: =IFERROR(E25*F25,"")
B26: =IFERROR(VLOOKUP(A26,ListaIngredientes!$A$5:$F$155,2,FALSE),"") | D26: =IFERROR(VLOOKUP(A26,Tabela2[],3,FALSE),"") | F26: =IFERROR(VLOOKUP(A26,ListaIngredientes!$A$5:$F$155,6,FALSE),"") | H26: =IFERROR(E26*F26,"")
B27: =IFERROR(VLOOKUP(A27,ListaIngredientes!$A$5:$F$155,2,FALSE),"") | D27: =IFERROR(VLOOKUP(A27,Tabela2[],3,FALSE),"") | F27: =IFERROR(VLOOKUP(A27,ListaIngredientes!$A$5:$F$155,6,FALSE),"") | H27: =IFERROR(E27*F27,"")
F28: soma | H28: =IFERROR(E28*F28,"")
H29: =SUM(H8:H27) -> 140.04145

Sheet EMPADA DE FRANGO
A1: cod | B1: 501 | C1: =VLOOKUP(B1,PRODUTOS!$A$7:$E$204,2,FALSE) -> P A S T E L | E1: =C3 -> 5.2173974 | G1: SOBREMESA/DOCE
A2: Despesas Fixas | C2: 0.2 | E2: Preço Venda Unit | G2: =IFERROR(C3/(1-C2-C5),"") -> 17.391325
A3: Custo Unitário | C3: =IFERROR(C6/C4,"") -> 5.2173974 | E3: Luro s/Venda | G3: =G2*C5 -> 8.6956624
A4: Quantidade Produzida | C4: 13 | E4: Preço Praticado | G4: 15
A5: Lucro s/Venda | C5: 0.5 | E5: Lucro Praticado | G5: =1-C3/G4-C2 -> 0.4521735
A6: Gasto Total | C6: =SUM(H8:H28) -> 67.826167 | E6: Lucro Praticado | G6: =G5*G4 -> 6.7826026
A7: cod Prod | B7: Descrição ingredientes | D7: unid | E7: quantiadade | F7: valor $ | H7: Subtotal
A8: 101 | B8: =IFERROR(VLOOKUP(A8,ListaIngredientes!$A$5:$F$155,2,FALSE),"") | D8: =IFERROR(VLOOKUP(A8,Tabela2[],3,FALSE),"") | E8: 7 | F8: =IFERROR(VLOOKUP(A8,ListaIngredientes!$A$5:$F$155,6,FALSE),"") | H8: =IFERROR(E8*F8,"")
A9: 143 | B9: =IFERROR(VLOOKUP(A9,ListaIngredientes!$A$5:$F$155,2,FALSE),"") -> 0 | D9: =IFERROR(VLOOKUP(A9,Tabela2[],3,FALSE),"") -> 0 | E9: 7 | F9: =IFERROR(VLOOKUP(A9,ListaIngredientes!$A$5:$F$155,6,FALSE),"") -> 0 | H9: =IFERROR(E9*F9,"") -> 0
A10: 182 | B10: =IFERROR(VLOOKUP(A10,ListaIngredientes!$A$5:$F$155,2,FALSE),"") -> GERGILIM | D10: =IFERROR(VLOOKUP(A10,Tabela2[],3,FALSE),"") -> KG | E10: 3 | F10: =IFERROR(VLOOKUP(A10,ListaIngredientes!$A$5:$F$155,6,FALSE),"") -> 0.029 | H10: =IFERROR(E10*F10,"") -> 0.087
A11: 194 | B11: =IFERROR(VLOOKUP(A11,ListaIngredientes!$A$5:$F$155,2,FALSE),"") -> Maçã | D11: =IFERROR(VLOOKUP(A11,Tabela2[],3,FALSE),"") -> kg | E11: 50 | F11: =IFERROR(VLOOKUP(A11,ListaIngredientes!$A$5:$F$155,6,FALSE),"") -> 0.00399 | H11: =IFERROR(E11*F11,"") -> 0.1995
A12: 158 | B12: =IFERROR(VLOOKUP(A12,ListaIngredientes!$A$5:$F$155,2,FALSE),"") -> ESSENCIA DE BAUNILHA | D12: =IFERROR(VLOOKUP(A12,Tabela2[],3,FALSE),"") -> ML | E12: 160 | F12: =IFERROR(VLOOKUP(A12,ListaIngredientes!$A$5:$F$155,6,FALSE),"") -> 0.099666667 | H12: =IFERROR(E12*F12,"") -> 15.946667
A13: 159 | B13: =IFERROR(VLOOKUP(A13,ListaIngredientes!$A$5:$F$155,2,FALSE),"") -> essencia de mel | D13: =IFERROR(VLOOKUP(A13,Tabela2[],3,FALSE),"") -> u | E13: 15 | F13: =IFERROR(VLOOKUP(A13,ListaIngredientes!$A$5:$F$155,6,FALSE),"") -> 2.59 | H13: =IFERROR(E13*F13,"") -> 38.85
A14: 160 | B14: =IFERROR(VLOOKUP(A14,ListaIngredientes!$A$5:$F$155,2,FALSE),"") -> farinha de amendoas | D14: =IFERROR(VLOOKUP(A14,Tabela2[],3,FALSE),"") -> kg | E14: 30 | F14: =IFERROR(VLOOKUP(A14,ListaIngredientes!$A$5:$F$155,6,FALSE),"") -> 0.063 | H14: =IFERROR(E14*F14,"") -> 1.89
A15: 203 | B15: =IFERROR(VLOOKUP(A15,ListaIngredientes!$A$5:$F$155,2,FALSE),"") -> 0 | D15: =IFERROR(VLOOKUP(A15,Tabela2[],3,FALSE),"") -> 0 | E15: 2 | F15: =IFERROR(VLOOKUP(A15,ListaIngredientes!$A$5:$F$155,6,FALSE),"") -> 0 | H15: =IFERROR(E15*F15,"") -> 0
A16: 162 | B16: =IFERROR(VLOOKUP(A16,ListaIngredientes!$A$5:$F$155,2,FALSE),"") -> farinha de linhaça dourada | D16: =IFERROR(VLOOKUP(A16,Tabela2[],3,FALSE),"") -> kg | E16: 300 | F16: =IFERROR(VLOOKUP(A16,ListaIngredientes!$A$5:$F$155,6,FALSE),"") -> 0.02499 | H16: =IFERROR(E16*F16,"") -> 7.497
A17: 219 | B17: =IFERROR(VLOOKUP(A17,ListaIngredientes!$A$5:$F$155,2,FALSE),"") -> Queijo Minas | D17: =IFERROR(VLOOKUP(A17,Tabela2[],3,FALSE),"") -> g | E17: 100 | F17: =IFERROR(VLOOKUP(A17,ListaIngredientes!$A$5:$F$155,6,FALSE),"") -> 0.0153 | H17: =IFERROR(E17*F17,"") -> 1.53
A18: 232 | B18: =IFERROR(VLOOKUP(A18,ListaIngredientes!$A$5:$F$155,2,FALSE),"") -> xilitol | D18: =IFERROR(VLOOKUP(A18,Tabela2[],3,FALSE),"") -> kg | E18: 50 | F18: =IFERROR(VLOOKUP(A18,ListaIngredientes!$A$5:$F$155,6,FALSE),"") -> 0.03652 | H18: =IFERROR(E18*F18,"") -> 1.826
B19: =IFERROR(VLOOKUP(A19,ListaIngredientes!$A$5:$F$155,2,FALSE),"") | D19: =IFERROR(VLOOKUP(A19,Tabela2[],3,FALSE),"") | F19: =IFERROR(VLOOKUP(A19,ListaIngredientes!$A$5:$F$155,6,FALSE),"") | H19: =IFERROR(E19*F19,"")
B20: =IFERROR(VLOOKUP(A20,ListaIngredientes!$A$5:$F$155,2,FALSE),"") | D20: =IFERROR(VLOOKUP(A20,Tabela2[],3,FALSE),"") | F20: =IFERROR(VLOOKUP(A20,ListaIngredientes!$A$5:$F$155,6,FALSE),"") | H20: =IFERROR(E20*F20,"")
B21: =IFERROR(VLOOKUP(A21,ListaIngredientes!$A$5:$F$155,2,FALSE),"") | D21: =IFERROR(VLOOKUP(A21,Tabela2[],3,FALSE),"") | F21: =IFERROR(VLOOKUP(A21,ListaIngredientes!$A$5:$F$155,6,FALSE),"") | H21: =IFERROR(E21*F21,"")
B22: =IFERROR(VLOOKUP(A22,ListaIngredientes!$A$5:$F$155,2,FALSE),"") | D22: =IFERROR(VLOOKUP(A22,Tabela2[],3,FALSE),"") | F22: =IFERROR(VLOOKUP(A22,ListaIngredientes!$A$5:$F$155,6,FALSE),"") | H22: =IFERROR(E22*F22,"")
B23: =IFERROR(VLOOKUP(A23,ListaIngredientes!$A$5:$F$155,2,FALSE),"") | D23: =IFERROR(VLOOKUP(A23,Tabela2[],3,FALSE),"") | F23: =IFERROR(VLOOKUP(A23,ListaIngredientes!$A$5:$F$155,6,FALSE),"") | H23: =IFERROR(E23*F23,"")
B24: =IFERROR(VLOOKUP(A24,ListaIngredientes!$A$5:$F$155,2,FALSE),"") | D24: =IFERROR(VLOOKUP(A24,Tabela2[],3,FALSE),"") | F24: =IFERROR(VLOOKUP(A24,ListaIngredientes!$A$5:$F$155,6,FALSE),"") | H24: =IFERROR(E24*F24,"")
B25: =IFERROR(VLOOKUP(A25,ListaIngredientes!$A$5:$F$155,2,FALSE),"") | D25: =IFERROR(VLOOKUP(A25,Tabela2[],3,FALSE),"") | F25: =IFERROR(VLOOKUP(A25,ListaIngredientes!$A$5:$F$155,6,FALSE),"") | H25: =IFERROR(E25*F25,"")
B26: =IFERROR(VLOOKUP(A26,ListaIngredientes!$A$5:$F$155,2,FALSE),"") | D26: =IFERROR(VLOOKUP(A26,Tabela2[],3,FALSE),"") | F26: =IFERROR(VLOOKUP(A26,ListaIngredientes!$A$5:$F$155,6,FALSE),"") | H26: =IFERROR(E26*F26,"")
B27: =IFERROR(VLOOKUP(A27,ListaIngredientes!$A$5:$F$155,2,FALSE),"") | D27: =IFERROR(VLOOKUP(A27,Tabela2[],3,FALSE),"") | F27: =IFERROR(VLOOKUP(A27,ListaIngredientes!$A$5:$F$155,6,FALSE),"") | H27: =IFERROR(E27*F27,"")
F28: soma | H28: =IFERROR(E28*F28,"")
H29: =SUM(H8:H27) -> 67.826167

Sheet EMPADA DE CARNE SECA
A1: cod | B1: 501 | C1: =VLOOKUP(B1,PRODUTOS!$A$7:$E$204,2,FALSE) -> P A S T E L | E1: =C3 -> 4.8047436 | G1: SOBREMESA/DOCE
A2: Despesas Fixas | C2: 0.2 | E2: Preço Venda Unit | G2: =IFERROR(C3/(1-C2-C5),"") -> 16.015812
A3: Custo Unitário | C3: =IFERROR(C6/C4,"") -> 4.8047436 | E3: Luro s/Venda | G3: =G2*C5 -> 8.007906
A4: Quantidade Produzida | C4: 13 | E4: Preço Praticado | G4: 15
A5: Lucro s/Venda | C5: 0.5 | E5: Lucro Praticado | G5: =1-C3/G4-C2 -> 0.47968376
A6: Gasto Total | C6: =SUM(H8:H28) -> 62.461667 | E6: Lucro Praticado | G6: =G5*G4 -> 7.1952564
A7: cod Prod | B7: Descrição ingredientes | D7: unid | E7: quantiadade | F7: valor $ | H7: Subtotal
A8: 101 | B8: =IFERROR(VLOOKUP(A8,ListaIngredientes!$A$5:$F$155,2,FALSE),"") | D8: =IFERROR(VLOOKUP(A8,Tabela2[],3,FALSE),"") | E8: 7 | F8: =IFERROR(VLOOKUP(A8,ListaIngredientes!$A$5:$F$155,6,FALSE),"") | H8: =IFERROR(E8*F8,"")
A9: 143 | B9: =IFERROR(VLOOKUP(A9,ListaIngredientes!$A$5:$F$155,2,FALSE),"") -> 0 | D9: =IFERROR(VLOOKUP(A9,Tabela2[],3,FALSE),"") -> 0 | E9: 7 | F9: =IFERROR(VLOOKUP(A9,ListaIngredientes!$A$5:$F$155,6,FALSE),"") -> 0 | H9: =IFERROR(E9*F9,"") -> 0
A10: 182 | B10: =IFERROR(VLOOKUP(A10,ListaIngredientes!$A$5:$F$155,2,FALSE),"") -> GERGILIM | D10: =IFERROR(VLOOKUP(A10,Tabela2[],3,FALSE),"") -> KG | E10: 3 | F10: =IFERROR(VLOOKUP(A10,ListaIngredientes!$A$5:$F$155,6,FALSE),"") -> 0.029 | H10: =IFERROR(E10*F10,"") -> 0.087
A11: 194 | B11: =IFERROR(VLOOKUP(A11,ListaIngredientes!$A$5:$F$155,2,FALSE),"") -> Maçã | D11: =IFERROR(VLOOKUP(A11,Tabela2[],3,FALSE),"") -> kg | E11: 50 | F11: =IFERROR(VLOOKUP(A11,ListaIngredientes!$A$5:$F$155,6,FALSE),"") -> 0.00399 | H11: =IFERROR(E11*F11,"") -> 0.1995
A12: 158 | B12: =IFERROR(VLOOKUP(A12,ListaIngredientes!$A$5:$F$155,2,FALSE),"") -> ESSENCIA DE BAUNILHA | D12: =IFERROR(VLOOKUP(A12,Tabela2[],3,FALSE),"") -> ML | E12: 160 | F12: =IFERROR(VLOOKUP(A12,ListaIngredientes!$A$5:$F$155,6,FALSE),"") -> 0.099666667 | H12: =IFERROR(E12*F12,"") -> 15.946667
A13: 159 | B13: =IFERROR(VLOOKUP(A13,ListaIngredientes!$A$5:$F$155,2,FALSE),"") -> essencia de mel | D13: =IFERROR(VLOOKUP(A13,Tabela2[],3,FALSE),"") -> u | E13: 15 | F13: =IFERROR(VLOOKUP(A13,ListaIngredientes!$A$5:$F$155,6,FALSE),"") -> 2.59 | H13: =IFERROR(E13*F13,"") -> 38.85
A14: 160 | B14: =IFERROR(VLOOKUP(A14,ListaIngredientes!$A$5:$F$155,2,FALSE),"") -> farinha de amendoas | D14: =IFERROR(VLOOKUP(A14,Tabela2[],3,FALSE),"") -> kg | E14: 30 | F14: =IFERROR(VLOOKUP(A14,ListaIngredientes!$A$5:$F$155,6,FALSE),"") -> 0.063 | H14: =IFERROR(E14*F14,"") -> 1.89
A15: 203 | B15: =IFERROR(VLOOKUP(A15,ListaIngredientes!$A$5:$F$155,2,FALSE),"") -> 0 | D15: =IFERROR(VLOOKUP(A15,Tabela2[],3,FALSE),"") -> 0 | E15: 1 | F15: =IFERROR(VLOOKUP(A15,ListaIngredientes!$A$5:$F$155,6,FALSE),"") -> 0 | H15: =IFERROR(E15*F15,"") -> 0
A16: 114 | B16: =IFERROR(VLOOKUP(A16,ListaIngredientes!$A$5:$F$155,2,FALSE),"") -> fecula | D16: =IFERROR(VLOOKUP(A16,Tabela2[],3,FALSE),"") -> kg | E16: 210 | F16: =IFERROR(VLOOKUP(A16,ListaIngredientes!$A$5:$F$155,6,FALSE),"") -> 0.01 | H16: =IFERROR(E16*F16,"") -> 2.1
A17: 219 | B17: =IFERROR(VLOOKUP(A17,ListaIngredientes!$A$5:$F$155,2,FALSE),"") -> Queijo Minas | D17: =IFERROR(VLOOKUP(A17,Tabela2[],3,FALSE),"") -> g | E17: 100 | F17: =IFERROR(VLOOKUP(A17,ListaIngredientes!$A$5:$F$155,6,FALSE),"") -> 0.0153 | H17: =IFERROR(E17*F17,"") -> 1.53
A18: 232 | B18: =IFERROR(VLOOKUP(A18,ListaIngredientes!$A$5:$F$155,2,FALSE),"") -> xilitol | D18: =IFERROR(VLOOKUP(A18,Tabela2[],3,FALSE),"") -> kg | E18: 50 | F18: =IFERROR(VLOOKUP(A18,ListaIngredientes!$A$5:$F$155,6,FALSE),"") -> 0.03652 | H18: =IFERROR(E18*F18,"") -> 1.826
A19: 115 | B19: =IFERROR(VLOOKUP(A19,ListaIngredientes!$A$5:$F$155,2,FALSE),"") -> CAMARÃO | D19: =IFERROR(VLOOKUP(A19,Tabela2[],3,FALSE),"") -> KG | E19: 0.5 | F19: =IFERROR(VLOOKUP(A19,ListaIngredientes!$A$5:$F$155,6,FALSE),"") -> 0.065 | H19: =IFERROR(E19*F19,"") -> 0.0325
B20: =IFERROR(VLOOKUP(A20,ListaIngredientes!$A$5:$F$155,2,FALSE),"") | D20: =IFERROR(VLOOKUP(A20,Tabela2[],3,FALSE),"") | F20: =IFERROR(VLOOKUP(A20,ListaIngredientes!$A$5:$F$155,6,FALSE),"") | H20: =IFERROR(E20*F20,"")
B21: =IFERROR(VLOOKUP(A21,ListaIngredientes!$A$5:$F$155,2,FALSE),"") | D21: =IFERROR(VLOOKUP(A21,Tabela2[],3,FALSE),"") | F21: =IFERROR(VLOOKUP(A21,ListaIngredientes!$A$5:$F$155,6,FALSE),"") | H21: =IFERROR(E21*F21,"")
B22: =IFERROR(VLOOKUP(A22,ListaIngredientes!$A$5:$F$155,2,FALSE),"") | D22: =IFERROR(VLOOKUP(A22,Tabela2[],3,FALSE),"") | F22: =IFERROR(VLOOKUP(A22,ListaIngredientes!$A$5:$F$155,6,FALSE),"") | H22: =IFERROR(E22*F22,"")
B23: =IFERROR(VLOOKUP(A23,ListaIngredientes!$A$5:$F$155,2,FALSE),"") | D23: =IFERROR(VLOOKUP(A23,Tabela2[],3,FALSE),"") | F23: =IFERROR(VLOOKUP(A23,ListaIngredientes!$A$5:$F$155,6,FALSE),"") | H23: =IFERROR(E23*F23,"")
B24: =IFERROR(VLOOKUP(A24,ListaIngredientes!$A$5:$F$155,2,FALSE),"") | D24: =IFERROR(VLOOKUP(A24,Tabela2[],3,FALSE),"") | F24: =IFERROR(VLOOKUP(A24,ListaIngredientes!$A$5:$F$155,6,FALSE),"") | H24: =IFERROR(E24*F24,"")
B25: =IFERROR(VLOOKUP(A25,ListaIngredientes!$A$5:$F$155,2,FALSE),"") | D25: =IFERROR(VLOOKUP(A25,Tabela2[],3,FALSE),"") | F25: =IFERROR(VLOOKUP(A25,ListaIngredientes!$A$5:$F$155,6,FALSE),"") | H25: =IFERROR(E25*F25,"")
B26: =IFERROR(VLOOKUP(A26,ListaIngredientes!$A$5:$F$155,2,FALSE),"") | D26: =IFERROR(VLOOKUP(A26,Tabela2[],3,FALSE),"") | F26: =IFERROR(VLOOKUP(A26,ListaIngredientes!$A$5:$F$155,6,FALSE),"") | H26: =IFERROR(E26*F26,"")
B27: =IFERROR(VLOOKUP(A27,ListaIngredientes!$A$5:$F$155,2,FALSE),"") | D27: =IFERROR(VLOOKUP(A27,Tabela2[],3,FALSE),"") | F27: =IFERROR(VLOOKUP(A27,ListaIngredientes!$A$5:$F$155,6,FALSE),"") | H27: =IFERROR(E27*F27,"")
F28: soma | H28: =IFERROR(E28*F28,"")
H29: =SUM(H8:H27) -> 62.461667

Sheet EMPADA DE CAMARÃO
A1: cod | B1: 501 | C1: =VLOOKUP(B1,PRODUTOS!$A$7:$E$204,2,FALSE) -> P A S T E L | E1: =C3 -> 4.8022436 | G1: SOBREMESA/DOCE
A2: Despesas Fixas | C2: 0.2 | E2: Preço Venda Unit | G2: =IFERROR(C3/(1-C2-C5),"") -> 16.007479
A3: Custo Unitário | C3: =IFERROR(C6/C4,"") -> 4.8022436 | E3: Luro s/Venda | G3: =G2*C5 -> 8.0037393
A4: Quantidade Produzida | C4: 13 | E4: Preço Praticado | G4: 15
A5: Lucro s/Venda | C5: 0.5 | E5: Lucro Praticado | G5: =1-C3/G4-C2 -> 0.47985043
A6: Gasto Total | C6: =SUM(H8:H28) -> 62.429167 | E6: Lucro Praticado | G6: =G5*G4 -> 7.1977564
A7: cod Prod | B7: Descrição ingredientes | D7: unid | E7: quantiadade | F7: valor $ | H7: Subtotal
A8: 101 | B8: =IFERROR(VLOOKUP(A8,ListaIngredientes!$A$5:$F$155,2,FALSE),"") | D8: =IFERROR(VLOOKUP(A8,Tabela2[],3,FALSE),"") | E8: 7 | F8: =IFERROR(VLOOKUP(A8,ListaIngredientes!$A$5:$F$155,6,FALSE),"") | H8: =IFERROR(E8*F8,"")
A9: 143 | B9: =IFERROR(VLOOKUP(A9,ListaIngredientes!$A$5:$F$155,2,FALSE),"") -> 0 | D9: =IFERROR(VLOOKUP(A9,Tabela2[],3,FALSE),"") -> 0 | E9: 7 | F9: =IFERROR(VLOOKUP(A9,ListaIngredientes!$A$5:$F$155,6,FALSE),"") -> 0 | H9: =IFERROR(E9*F9,"") -> 0
A10: 182 | B10: =IFERROR(VLOOKUP(A10,ListaIngredientes!$A$5:$F$155,2,FALSE),"") -> GERGILIM | D10: =IFERROR(VLOOKUP(A10,Tabela2[],3,FALSE),"") -> KG | E10: 3 | F10: =IFERROR(VLOOKUP(A10,ListaIngredientes!$A$5:$F$155,6,FALSE),"") -> 0.029 | H10: =IFERROR(E10*F10,"") -> 0.087
A11: 194 | B11: =IFERROR(VLOOKUP(A11,ListaIngredientes!$A$5:$F$155,2,FALSE),"") -> Maçã | D11: =IFERROR(VLOOKUP(A11,Tabela2[],3,FALSE),"") -> kg | E11: 50 | F11: =IFERROR(VLOOKUP(A11,ListaIngredientes!$A$5:$F$155,6,FALSE),"") -> 0.00399 | H11: =IFERROR(E11*F11,"") -> 0.1995
A12: 158 | B12: =IFERROR(VLOOKUP(A12,ListaIngredientes!$A$5:$F$155,2,FALSE),"") -> ESSENCIA DE BAUNILHA | D12: =IFERROR(VLOOKUP(A12,Tabela2[],3,FALSE),"") -> ML | E12: 160 | F12: =IFERROR(VLOOKUP(A12,ListaIngredientes!$A$5:$F$155,6,FALSE),"") -> 0.099666667 | H12: =IFERROR(E12*F12,"") -> 15.946667
A13: 159 | B13: =IFERROR(VLOOKUP(A13,ListaIngredientes!$A$5:$F$155,2,FALSE),"") -> essencia de mel | D13: =IFERROR(VLOOKUP(A13,Tabela2[],3,FALSE),"") -> u | E13: 15 | F13: =IFERROR(VLOOKUP(A13,ListaIngredientes!$A$5:$F$155,6,FALSE),"") -> 2.59 | H13: =IFERROR(E13*F13,"") -> 38.85
A14: 160 | B14: =IFERROR(VLOOKUP(A14,ListaIngredientes!$A$5:$F$155,2,FALSE),"") -> farinha de amendoas | D14: =IFERROR(VLOOKUP(A14,Tabela2[],3,FALSE),"") -> kg | E14: 30 | F14: =IFERROR(VLOOKUP(A14,ListaIngredientes!$A$5:$F$155,6,FALSE),"") -> 0.063 | H14: =IFERROR(E14*F14,"") -> 1.89
A15: 203 | B15: =IFERROR(VLOOKUP(A15,ListaIngredientes!$A$5:$F$155,2,FALSE),"") -> 0 | D15: =IFERROR(VLOOKUP(A15,Tabela2[],3,FALSE),"") -> 0 | E15: 1 | F15: =IFERROR(VLOOKUP(A15,ListaIngredientes!$A$5:$F$155,6,FALSE),"") -> 0 | H15: =IFERROR(E15*F15,"") -> 0
A16: 113 | B16: =IFERROR(VLOOKUP(A16,ListaIngredientes!$A$5:$F$155,2,FALSE),"") -> polvilho doce | D16: =IFERROR(VLOOKUP(A16,Tabela2[],3,FALSE),"") -> kg | E16: 210 | F16: =IFERROR(VLOOKUP(A16,ListaIngredientes!$A$5:$F$155,6,FALSE),"") -> 0.01 | H16: =IFERROR(E16*F16,"") -> 2.1
A17: 219 | B17: =IFERROR(VLOOKUP(A17,ListaIngredientes!$A$5:$F$155,2,FALSE),"") -> Queijo Minas | D17: =IFERROR(VLOOKUP(A17,Tabela2[],3,FALSE),"") -> g | E17: 100 | F17: =IFERROR(VLOOKUP(A17,ListaIngredientes!$A$5:$F$155,6,FALSE),"") -> 0.0153 | H17: =IFERROR(E17*F17,"") -> 1.53
A18: 232 | B18: =IFERROR(VLOOKUP(A18,ListaIngredientes!$A$5:$F$155,2,FALSE),"") -> xilitol | D18: =IFERROR(VLOOKUP(A18,Tabela2[],3,FALSE),"") -> kg | E18: 50 | F18: =IFERROR(VLOOKUP(A18,ListaIngredientes!$A$5:$F$155,6,FALSE),"") -> 0.03652 | H18: =IFERROR(E18*F18,"") -> 1.826
B19: =IFERROR(VLOOKUP(A19,ListaIngredientes!$A$5:$F$155,2,FALSE),"") | D19: =IFERROR(VLOOKUP(A19,Tabela2[],3,FALSE),"") | F19: =IFERROR(VLOOKUP(A19,ListaIngredientes!$A$5:$F$155,6,FALSE),"") | H19: =IFERROR(E19*F19,"")
B20: =IFERROR(VLOOKUP(A20,ListaIngredientes!$A$5:$F$155,2,FALSE),"") | D20: =IFERROR(VLOOKUP(A20,Tabela2[],3,FALSE),"") | F20: =IFERROR(VLOOKUP(A20,ListaIngredientes!$A$5:$F$155,6,FALSE),"") | H20: =IFERROR(E20*F20,"")
B21: =IFERROR(VLOOKUP(A21,ListaIngredientes!$A$5:$F$155,2,FALSE),"") | D21: =IFERROR(VLOOKUP(A21,Tabela2[],3,FALSE),"") | F21: =IFERROR(VLOOKUP(A21,ListaIngredientes!$A$5:$F$155,6,FALSE),"") | H21: =IFERROR(E21*F21,"")
B22: =IFERROR(VLOOKUP(A22,ListaIngredientes!$A$5:$F$155,2,FALSE),"") | D22: =IFERROR(VLOOKUP(A22,Tabela2[],3,FALSE),"") | F22: =IFERROR(VLOOKUP(A22,ListaIngredientes!$A$5:$F$155,6,FALSE),"") | H22: =IFERROR(E22*F22,"")
B23: =IFERROR(VLOOKUP(A23,ListaIngredientes!$A$5:$F$155,2,FALSE),"") | D23: =IFERROR(VLOOKUP(A23,Tabela2[],3,FALSE),"") | F23: =IFERROR(VLOOKUP(A23,ListaIngredientes!$A$5:$F$155,6,FALSE),"") | H23: =IFERROR(E23*F23,"")
B24: =IFERROR(VLOOKUP(A24,ListaIngredientes!$A$5:$F$155,2,FALSE),"") | D24: =IFERROR(VLOOKUP(A24,Tabela2[],3,FALSE),"") | F24: =IFERROR(VLOOKUP(A24,ListaIngredientes!$A$5:$F$155,6,FALSE),"") | H24: =IFERROR(E24*F24,"")
B25: =IFERROR(VLOOKUP(A25,ListaIngredientes!$A$5:$F$155,2,FALSE),"") | D25: =IFERROR(VLOOKUP(A25,Tabela2[],3,FALSE),"") | F25: =IFERROR(VLOOKUP(A25,ListaIngredientes!$A$5:$F$155,6,FALSE),"") | H25: =IFERROR(E25*F25,"")
B26: =IFERROR(VLOOKUP(A26,ListaIngredientes!$A$5:$F$155,2,FALSE),"") | D26: =IFERROR(VLOOKUP(A26,Tabela2[],3,FALSE),"") | F26: =IFERROR(VLOOKUP(A26,ListaIngredientes!$A$5:$F$155,6,FALSE),"") | H26: =IFERROR(E26*F26,"")
B27: =IFERROR(VLOOKUP(A27,ListaIngredientes!$A$5:$F$155,2,FALSE),"") | D27: =IFERROR(VLOOKUP(A27,Tabela2[],3,FALSE),"") | F27: =IFERROR(VLOOKUP(A27,ListaIngredientes!$A$5:$F$155,6,FALSE),"") | H27: =IFERROR(E27*F27,"")
F28: soma

Sheet QUICHE DE FRANGO
A1: cod | B1: 501 | C1: =VLOOKUP(B1,PRODUTOS!$A$7:$E$204,2,FALSE) -> P A S T E L | E1: =C3 -> 3.978371 | G1: SOBREMESA/DOCE
A2: Despesas Fixas | C2: 0.2 | E2: Preço Venda Unit | G2: =IFERROR(C3/(1-C2-C5),"") -> 13.261237
A3: Custo Unitário | C3: =IFERROR(C6/C4,"") -> 3.978371 | E3: Luro s/Venda | G3: =G2*C5 -> 6.6306184
A4: Quantidade Produzida | C4: 13 | E4: Preço Praticado | G4: 15
A5: Lucro s/Venda | C5: 0.5 | E5: Lucro Praticado | G5: =1-C3/G4-C2 -> 0.53477526
A6: Gasto Total | C6: =SUM(H8:H28) -> 51.718824 | E6: Lucro Praticado | G6: =G5*G4 -> 8.021629
A7: cod Prod | B7: Descrição ingredientes | D7: unid | E7: quantiadade | F7: valor $ | H7: Subtotal
A8: 101 | B8: =IFERROR(VLOOKUP(A8,ListaIngredientes!$A$5:$F$155,2,FALSE),"") | D8: =IFERROR(VLOOKUP(A8,Tabela2[],3,FALSE),"") | E8: 12 | F8: =IFERROR(VLOOKUP(A8,ListaIngredientes!$A$5:$F$155,6,FALSE),"") | H8: =IFERROR(E8*F8,"")
A9: 154 | B9: =IFERROR(VLOOKUP(A9,ListaIngredientes!$A$5:$F$155,2,FALSE),"") -> embalagem GALVANOTEC G645 | D9: =IFERROR(VLOOKUP(A9,Tabela2[],3,FALSE),"") -> u | E9: 12 | F9: =IFERROR(VLOOKUP(A9,ListaIngredientes!$A$5:$F$155,6,FALSE),"") -> 0.8 | H9: =IFERROR(E9*F9,"") -> 9.6
A10: 203 | B10: =IFERROR(VLOOKUP(A10,ListaIngredientes!$A$5:$F$155,2,FALSE),"") -> 0 | D10: =IFERROR(VLOOKUP(A10,Tabela2[],3,FALSE),"") -> 0 | E10: 7 | F10: =IFERROR(VLOOKUP(A10,ListaIngredientes!$A$5:$F$155,6,FALSE),"") -> 0 | H10: =IFERROR(E10*F10,"") -> 0
A11: 158 | B11: =IFERROR(VLOOKUP(A11,ListaIngredientes!$A$5:$F$155,2,FALSE),"") -> ESSENCIA DE BAUNILHA | D11: =IFERROR(VLOOKUP(A11,Tabela2[],3,FALSE),"") -> ML | E11: 240 | F11: =IFERROR(VLOOKUP(A11,ListaIngredientes!$A$5:$F$155,6,FALSE),"") -> 0.099666667 | H11: =IFERROR(E11*F11,"") -> 23.92
A12: 160 | B12: =IFERROR(VLOOKUP(A12,ListaIngredientes!$A$5:$F$155,2,FALSE),"") -> farinha de amendoas | D12: =IFERROR(VLOOKUP(A12,Tabela2[],3,FALSE),"") -> kg | E12: 30 | F12: =IFERROR(VLOOKUP(A12,ListaIngredientes!$A$5:$F$155,6,FALSE),"") -> 0.063 | H12: =IFERROR(E12*F12,"") -> 1.89
A13: 194 | B13: =IFERROR(VLOOKUP(A13,ListaIngredientes!$A$5:$F$155,2,FALSE),"") -> Maçã | D13: =IFERROR(VLOOKUP(A13,Tabela2[],3,FALSE),"") -> kg | E13: 100 | F13: =IFERROR(VLOOKUP(A13,ListaIngredientes!$A$5:$F$155,6,FALSE),"") -> 0.00399 | H13: =IFERROR(E13*F13,"") -> 0.399
A14: 219 | B14: =IFERROR(VLOOKUP(A14,ListaIngredientes!$A$5:$F$155,2,FALSE),"") -> Queijo Minas | D14: =IFERROR(VLOOKUP(A14,Tabela2[],3,FALSE),"") -> g | E14: 100 | F14: =IFERROR(VLOOKUP(A14,ListaIngredientes!$A$5:$F$155,6,FALSE),"") -> 0.0153 | H14: =IFERROR(E14*F14,"") -> 1.53
A15: 139 | B15: =IFERROR(VLOOKUP(A15,ListaIngredientes!$A$5:$F$155,2,FALSE),"") -> cravo da india | D15: =IFERROR(VLOOKUP(A15,Tabela2[],3,FALSE),"") -> g | E15: 100 | F15: =IFERROR(VLOOKUP(A15,ListaIngredientes!$A$5:$F$155,6,FALSE),"") -> 0.00058823529 | H15: =IFERROR(E15*F15,"") -> 0.058823529
A16: 162 | B16: =IFERROR(VLOOKUP(A16,ListaIngredientes!$A$5:$F$155,2,FALSE),"") -> farinha de linhaça dourada | D16: =IFERROR(VLOOKUP(A16,Tabela2[],3,FALSE),"") -> kg | E16: 500 | F16: =IFERROR(VLOOKUP(A16,ListaIngredientes!$A$5:$F$155,6,FALSE),"") -> 0.02499 | H16: =IFERROR(E16*F16,"") -> 12.495
A17: 232 | B17: =IFERROR(VLOOKUP(A17,ListaIngredientes!$A$5:$F$155,2,FALSE),"") -> xilitol | D17: =IFERROR(VLOOKUP(A17,Tabela2[],3,FALSE),"") -> kg | E17: 50 | F17: =IFERROR(VLOOKUP(A17,ListaIngredientes!$A$5:$F$155,6,FALSE),"") -> 0.03652 | H17: =IFERROR(E17*F17,"") -> 1.826
B18: =IFERROR(VLOOKUP(A18,ListaIngredientes!$A$5:$F$155,2,FALSE),"") | D18: =IFERROR(VLOOKUP(A18,Tabela2[],3,FALSE),"") | F18: =IFERROR(VLOOKUP(A18,ListaIngredientes!$A$5:$F$155,6,FALSE),"") | H18: =IFERROR(E18*F18,"")
B19: =IFERROR(VLOOKUP(A19,ListaIngredientes!$A$5:$F$155,2,FALSE),"") | D19: =IFERROR(VLOOKUP(A19,Tabela2[],3,FALSE),"") | F19: =IFERROR(VLOOKUP(A19,ListaIngredientes!$A$5:$F$155,6,FALSE),"") | H19: =IFERROR(E19*F19,"")
B20: =IFERROR(VLOOKUP(A20,ListaIngredientes!$A$5:$F$155,2,FALSE),"") | D20: =IFERROR(VLOOKUP(A20,Tabela2[],3,FALSE),"") | F20: =IFERROR(VLOOKUP(A20,ListaIngredientes!$A$5:$F$155,6,FALSE),"") | H20: =IFERROR(E20*F20,"")
B21: =IFERROR(VLOOKUP(A21,ListaIngredientes!$A$5:$F$155,2,FALSE),"") | D21: =IFERROR(VLOOKUP(A21,Tabela2[],3,FALSE),"") | F21: =IFERROR(VLOOKUP(A21,ListaIngredientes!$A$5:$F$155,6,FALSE),"") | H21: =IFERROR(E21*F21,"")
B22: =IFERROR(VLOOKUP(A22,ListaIngredientes!$A$5:$F$155,2,FALSE),"") | D22: =IFERROR(VLOOKUP(A22,Tabela2[],3,FALSE),"") | F22: =IFERROR(VLOOKUP(A22,ListaIngredientes!$A$5:$F$155,6,FALSE),"") | H22: =IFERROR(E22*F22,"")
B23: =IFERROR(VLOOKUP(A23,ListaIngredientes!$A$5:$F$155,2,FALSE),"") | D23: =IFERROR(VLOOKUP(A23,Tabela2[],3,FALSE),"") | F23: =IFERROR(VLOOKUP(A23,ListaIngredientes!$A$5:$F$155,6,FALSE),"") | H23: =IFERROR(E23*F23,"")
B24: =IFERROR(VLOOKUP(A24,ListaIngredientes!$A$5:$F$155,2,FALSE),"") | D24: =IFERROR(VLOOKUP(A24,Tabela2[],3,FALSE),"") | F24: =IFERROR(VLOOKUP(A24,ListaIngredientes!$A$5:$F$155,6,FALSE),"") | H24: =IFERROR(E24*F24,"")
B25: =IFERROR(VLOOKUP(A25,ListaIngredientes!$A$5:$F$155,2,FALSE),"") | D25: =IFERROR(VLOOKUP(A25,Tabela2[],3,FALSE),"") | F25: =IFERROR(VLOOKUP(A25,ListaIngredientes!$A$5:$F$155,6,FALSE),"") | H25: =IFERROR(E25*F25,"")
B26: =IFERROR(VLOOKUP(A26,ListaIngredientes!$A$5:$F$155,2,FALSE),"") | D26: =IFERROR(VLOOKUP(A26,Tabela2[],3,FALSE),"") | F26: =IFERROR(VLOOKUP(A26,ListaIngredientes!$A$5:$F$155,6,FALSE),"") | H26: =IFERROR(E26*F26,"")
B27: =IFERROR(VLOOKUP(A27,ListaIngredientes!$A$5:$F$155,2,FALSE),"") | D27: =IFERROR(VLOOKUP(A27,Tabela2[],3,FALSE),"") | F27: =IFERROR(VLOOKUP(A27,ListaIngredientes!$A$5:$F$155,6,FALSE),"") | H27: =IFERROR(E27*F27,"")
F28: soma | H28: =IFERROR(E28*F28,"")
H29: =SUM(H8:H28) -> 51.718824

Sheet QUICHE BACON
A1: cod | B1: 501 | C1: =VLOOKUP(B1,PRODUTOS!$A$7:$E$204,2,FALSE) -> P A S T E L | E1: =C3 -> 7.5228959 | G1: SOBREMESA/DOCE
A2: Despesas Fixas | C2: 0.2 | E2: Preço Venda Unit | G2: =IFERROR(C3/(1-C2-C5),"") -> 25.07632
A3: Custo Unitário | C3: =IFERROR(C6/C4,"") -> 7.5228959 | E3: Luro s/Venda | G3: =G2*C5 -> 12.53816
A4: Quantidade Produzida | C4: 13 | E4: Preço Praticado | G4: 15
A5: Lucro s/Venda | C5: 0.5 | E5: Lucro Praticado | G5: =1-C3/G4-C2 -> 0.2984736
A6: Gasto Total | C6: =SUM(H8:H28) -> 97.797647 | E6: Lucro Praticado | G6: =G5*G4 -> 4.4771041
A7: cod Prod | B7: Descrição ingredientes | D7: unid | E7: quantiadade | F7: valor $ | H7: Subtotal
A8: 101 | B8: =IFERROR(VLOOKUP(A8,ListaIngredientes!$A$5:$F$155,2,FALSE),"") | D8: =IFERROR(VLOOKUP(A8,Tabela2[],3,FALSE),"") | E8: 12 | F8: =IFERROR(VLOOKUP(A8,ListaIngredientes!$A$5:$F$155,6,FALSE),"") | H8: =IFERROR(E8*F8,"")
A9: 154 | B9: =IFERROR(VLOOKUP(A9,ListaIngredientes!$A$5:$F$155,2,FALSE),"") -> embalagem GALVANOTEC G645 | D9: =IFERROR(VLOOKUP(A9,Tabela2[],3,FALSE),"") -> u | E9: 12 | F9: =IFERROR(VLOOKUP(A9,ListaIngredientes!$A$5:$F$155,6,FALSE),"") -> 0.8 | H9: =IFERROR(E9*F9,"") -> 9.6
A10: 203 | B10: =IFERROR(VLOOKUP(A10,ListaIngredientes!$A$5:$F$155,2,FALSE),"") -> 0 | D10: =IFERROR(VLOOKUP(A10,Tabela2[],3,FALSE),"") -> 0 | E10: 7 | F10: =IFERROR(VLOOKUP(A10,ListaIngredientes!$A$5:$F$155,6,FALSE),"") -> 0 | H10: =IFERROR(E10*F10,"") -> 0
A11: 158 | B11: =IFERROR(VLOOKUP(A11,ListaIngredientes!$A$5:$F$155,2,FALSE),"") -> ESSENCIA DE BAUNILHA | D11: =IFERROR(VLOOKUP(A11,Tabela2[],3,FALSE),"") -> ML | E11: 240 | F11: =IFERROR(VLOOKUP(A11,ListaIngredientes!$A$5:$F$155,6,FALSE),"") -> 0.099666667 | H11: =IFERROR(E11*F11,"") -> 23.92
A12: 160 | B12: =IFERROR(VLOOKUP(A12,ListaIngredientes!$A$5:$F$155,2,FALSE),"") -> farinha de amendoas | D12: =IFERROR(VLOOKUP(A12,Tabela2[],3,FALSE),"") -> kg | E12: 30 | F12: =IFERROR(VLOOKUP(A12,ListaIngredientes!$A$5:$F$155,6,FALSE),"") -> 0.063 | H12: =IFERROR(E12*F12,"") -> 1.89
A13: 194 | B13: =IFERROR(VLOOKUP(A13,ListaIngredientes!$A$5:$F$155,2,FALSE),"") -> Maçã | D13: =IFERROR(VLOOKUP(A13,Tabela2[],3,FALSE),"") -> kg | E13: 100 | F13: =IFERROR(VLOOKUP(A13,ListaIngredientes!$A$5:$F$155,6,FALSE),"") -> 0.00399 | H13: =IFERROR(E13*F13,"") -> 0.399
A14: 219 | B14: =IFERROR(VLOOKUP(A14,ListaIngredientes!$A$5:$F$155,2,FALSE),"") -> Queijo Minas | D14: =IFERROR(VLOOKUP(A14,Tabela2[],3,FALSE),"") -> g | E14: 100 | F14: =IFERROR(VLOOKUP(A14,ListaIngredientes!$A$5:$F$155,6,FALSE),"") -> 0.0153 | H14: =IFERROR(E14*F14,"") -> 1.53
A15: 139 | B15: =IFERROR(VLOOKUP(A15,ListaIngredientes!$A$5:$F$155,2,FALSE),"") -> cravo da india | D15: =IFERROR(VLOOKUP(A15,Tabela2[],3,FALSE),"") -> g | E15: 100 | F15: =IFERROR(VLOOKUP(A15,ListaIngredientes!$A$5:$F$155,6,FALSE),"") -> 0.00058823529 | H15: =IFERROR(E15*F15,"") -> 0.058823529
A16: 122 | B16: =IFERROR(VLOOKUP(A16,ListaIngredientes!$A$5:$F$155,2,FALSE),"") -> CARNE PATINHO | D16: =IFERROR(VLOOKUP(A16,Tabela2[],3,FALSE),"") -> KG | E16: 240 | F16: =IFERROR(VLOOKUP(A16,ListaIngredientes!$A$5:$F$155,6,FALSE),"") -> 0.033 | H16: =IFERROR(E16*F16,"") -> 7.92
A17: 116 | B17: =IFERROR(VLOOKUP(A17,ListaIngredientes!$A$5:$F$155,2,FALSE),"") -> CARNE SECA | D17: =IFERROR(VLOOKUP(A17,Tabela2[],3,FALSE),"") -> KG | E17: 65 | F17: =IFERROR(VLOOKUP(A17,ListaIngredientes!$A$5:$F$155,6,FALSE),"") -> 0.027 | H17: =IFERROR(E17*F17,"") -> 1.755
A18: 232 | B18: =IFERROR(VLOOKUP(A18,ListaIngredientes!$A$5:$F$155,2,FALSE),"") -> xilitol | D18: =IFERROR(VLOOKUP(A18,Tabela2[],3,FALSE),"") -> kg | E18: 50 | F18: =IFERROR(VLOOKUP(A18,ListaIngredientes!$A$5:$F$155,6,FALSE),"") -> 0.03652 | H18: =IFERROR(E18*F18,"") -> 1.826
B19: =IFERROR(VLOOKUP(A19,ListaIngredientes!$A$5:$F$155,2,FALSE),"") | D19: =IFERROR(VLOOKUP(A19,Tabela2[],3,FALSE),"") | F19: =IFERROR(VLOOKUP(A19,ListaIngredientes!$A$5:$F$155,6,FALSE),"") | H19: =IFERROR(E19*F19,"")
B20: =IFERROR(VLOOKUP(A20,ListaIngredientes!$A$5:$F$155,2,FALSE),"") | D20: =IFERROR(VLOOKUP(A20,Tabela2[],3,FALSE),"") | F20: =IFERROR(VLOOKUP(A20,ListaIngredientes!$A$5:$F$155,6,FALSE),"") | H20: =IFERROR(E20*F20,"")
B21: =IFERROR(VLOOKUP(A21,ListaIngredientes!$A$5:$F$155,2,FALSE),"") | D21: =IFERROR(VLOOKUP(A21,Tabela2[],3,FALSE),"") | F21: =IFERROR(VLOOKUP(A21,ListaIngredientes!$A$5:$F$155,6,FALSE),"") | H21: =IFERROR(E21*F21,"")
B22: =IFERROR(VLOOKUP(A22,ListaIngredientes!$A$5:$F$155,2,FALSE),"") | D22: =IFERROR(VLOOKUP(A22,Tabela2[],3,FALSE),"") | F22: =IFERROR(VLOOKUP(A22,ListaIngredientes!$A$5:$F$155,6,FALSE),"") | H22: =IFERROR(E22*F22,"")
B23: =IFERROR(VLOOKUP(A23,ListaIngredientes!$A$5:$F$155,2,FALSE),"") | D23: =IFERROR(VLOOKUP(A23,Tabela2[],3,FALSE),"") | F23: =IFERROR(VLOOKUP(A23,ListaIngredientes!$A$5:$F$155,6,FALSE),"") | H23: =IFERROR(E23*F23,"")
B24: =IFERROR(VLOOKUP(A24,ListaIngredientes!$A$5:$F$155,2,FALSE),"") | D24: =IFERROR(VLOOKUP(A24,Tabela2[],3,FALSE),"") | F24: =IFERROR(VLOOKUP(A24,ListaIngredientes!$A$5:$F$155,6,FALSE),"") | H24: =IFERROR(E24*F24,"")
B25: =IFERROR(VLOOKUP(A25,ListaIngredientes!$A$5:$F$155,2,FALSE),"") | D25: =IFERROR(VLOOKUP(A25,Tabela2[],3,FALSE),"") | F25: =IFERROR(VLOOKUP(A25,ListaIngredientes!$A$5:$F$155,6,FALSE),"") | H25: =IFERROR(E25*F25,"")
B26: =IFERROR(VLOOKUP(A26,ListaIngredientes!$A$5:$F$155,2,FALSE),"") | D26: =IFERROR(VLOOKUP(A26,Tabela2[],3,FALSE),"") | F26: =IFERROR(VLOOKUP(A26,ListaIngredientes!$A$5:$F$155,6,FALSE),"") | H26: =IFERROR(E26*F26,"")
F27: soma | H27: =IFERROR(E27*F27,"")
H28: =SUM(H8:H27) -> 48.898824

Sheet CHARGE
A1: cod | B1: 501 | C1: =VLOOKUP(B1,PRODUTOS!$A$7:$E$204,2,FALSE) -> P A S T E L | E1: =C3 -> 57.72364 | G1: SOBREMESA/DOCE
A2: Despesas Fixas | C2: 0.2 | E2: Preço Venda Unit | G2: =IFERROR(C3/(1-C2-C5),"") -> 192.41213
A3: Custo Unitário | C3: =IFERROR(C6/C4,"") -> 57.72364 | E3: Luro s/Venda | G3: =G2*C5 -> 96.206066
A4: Quantidade Produzida | C4: 13 | E4: Preço Praticado | G4: 15
A5: Lucro s/Venda | C5: 0.5 | E5: Lucro Praticado | G5: =1-C3/G4-C2 -> -3.0482426
A6: Gasto Total | C6: =SUM(H8:H28) -> 750.40732 | E6: Lucro Praticado | G6: =G5*G4 -> -45.72364
A7: cod Prod | B7: Descrição ingredientes | D7: unid | E7: quantiadade | F7: valor $ | H7: Subtotal
A8: 101 | B8: =IFERROR(VLOOKUP(A8,ListaIngredientes!$A$5:$F$155,2,FALSE),"") | D8: =IFERROR(VLOOKUP(A8,Tabela2[],3,FALSE),"") | E8: 9 | F8: =IFERROR(VLOOKUP(A8,ListaIngredientes!$A$5:$F$155,6,FALSE),"") | H8: =IFERROR(E8*F8,"")
A9: 105 | B9: =IFERROR(VLOOKUP(A9,ListaIngredientes!$A$5:$F$155,2,FALSE),"") -> Bananas | D9: =IFERROR(VLOOKUP(A9,Tabela2[],3,FALSE),"") -> duzias | E9: 20 | F9: =IFERROR(VLOOKUP(A9,ListaIngredientes!$A$5:$F$155,6,FALSE),"") -> 0.5 | H9: =IFERROR(E9*F9,"") -> 10
A10: 125 | B10: =IFERROR(VLOOKUP(A10,ListaIngredientes!$A$5:$F$155,2,FALSE),"") -> 0 | D10: =IFERROR(VLOOKUP(A10,Tabela2[],3,FALSE),"") -> 0 | E10: 70 | F10: =IFERROR(VLOOKUP(A10,ListaIngredientes!$A$5:$F$155,6,FALSE),"") -> 0 | H10: =IFERROR(E10*F10,"") -> 0
A11: 139 | B11: =IFERROR(VLOOKUP(A11,ListaIngredientes!$A$5:$F$155,2,FALSE),"") -> cravo da india | D11: =IFERROR(VLOOKUP(A11,Tabela2[],3,FALSE),"") -> g | E11: 400 | F11: =IFERROR(VLOOKUP(A11,ListaIngredientes!$A$5:$F$155,6,FALSE),"") -> 0.00058823529 | H11: =IFERROR(E11*F11,"") -> 0.23529412
A12: 230 | B12: =IFERROR(VLOOKUP(A12,ListaIngredientes!$A$5:$F$155,2,FALSE),"") -> 0 | D12: kg | E12: 175 | F12: =IFERROR(VLOOKUP(A12,ListaIngredientes!$A$5:$F$155,6,FALSE),"") -> 0.149 | H12: =IFERROR(E12*F12,"") -> 26.075
A13: 135 | B13: =IFERROR(VLOOKUP(A13,ListaIngredientes!$A$5:$F$155,2,FALSE),"") -> ISOPOR DE PIZZA REDONDA | D13: u | E13: 9 | F13: =IFERROR(VLOOKUP(A13,ListaIngredientes!$A$5:$F$155,6,FALSE),"") -> 0.29 | H13: =IFERROR(E13*F13,"") -> 2.61
A14: 249 | B14: =IFERROR(VLOOKUP(A14,ListaIngredientes!$A$5:$F$155,2,FALSE),"") -> Whey Protein | D14: kg | E14: 20 | F14: =IFERROR(VLOOKUP(A14,ListaIngredientes!$A$5:$F$155,6,FALSE),"") -> 0.017001534 | H14: =IFERROR(E14*F14,"") -> 0.34003067
A15: 102 | B15: =IFERROR(VLOOKUP(A15,ListaIngredientes!$A$5:$F$155,2,FALSE),"") -> Ovos Branco | D15: KG | E15: 200 | F15: =IFERROR(VLOOKUP(A15,ListaIngredientes!$A$5:$F$155,6,FALSE),"") -> 1.6666667 | H15: =IFERROR(E15*F15,"") -> 333.33333
A16: 135 | B16: =IFERROR(VLOOKUP(A16,ListaIngredientes!$A$5:$F$155,2,FALSE),"") -> ISOPOR DE PIZZA REDONDA | D16: U | E16: 9 | F16: =IFERROR(VLOOKUP(A16,ListaIngredientes!$A$5:$F$155,6,FALSE),"") -> 0.29 | H16: =IFERROR(E16*F16,"") -> 2.61
B17: =IFERROR(VLOOKUP(A17,ListaIngredientes!$A$5:$F$155,2,FALSE),"") | D17: =IFERROR(VLOOKUP(A17,Tabela2[],3,FALSE),"") | F17: =IFERROR(VLOOKUP(A17,ListaIngredientes!$A$5:$F$155,6,FALSE),"") | H17: =IFERROR(E17*F17,"")
B18: =IFERROR(VLOOKUP(A18,ListaIngredientes!$A$5:$F$155,2,FALSE),"") | D18: =IFERROR(VLOOKUP(A18,Tabela2[],3,FALSE),"") | F18: =IFERROR(VLOOKUP(A18,ListaIngredientes!$A$5:$F$155,6,FALSE),"") | H18: =IFERROR(E18*F18,"")
B19: =IFERROR(VLOOKUP(A19,ListaIngredientes!$A$5:$F$155,2,FALSE),"") | D19: =IFERROR(VLOOKUP(A19,Tabela2[],3,FALSE),"") | F19: =IFERROR(VLOOKUP(A19,ListaIngredientes!$A$5:$F$155,6,FALSE),"") | H19: =IFERROR(E19*F19,"")
B20: =IFERROR(VLOOKUP(A20,ListaIngredientes!$A$5:$F$155,2,FALSE),"") | D20: =IFERROR(VLOOKUP(A20,Tabela2[],3,FALSE),"") | F20: =IFERROR(VLOOKUP(A20,ListaIngredientes!$A$5:$F$155,6,FALSE),"") | H20: =IFERROR(E20*F20,"")
B21: =IFERROR(VLOOKUP(A21,ListaIngredientes!$A$5:$F$155,2,FALSE),"") | D21: =IFERROR(VLOOKUP(A21,Tabela2[],3,FALSE),"") | F21: =IFERROR(VLOOKUP(A21,ListaIngredientes!$A$5:$F$155,6,FALSE),"") | H21: =IFERROR(E21*F21,"")
B22: =IFERROR(VLOOKUP(A22,ListaIngredientes!$A$5:$F$155,2,FALSE),"") | D22: =IFERROR(VLOOKUP(A22,Tabela2[],3,FALSE),"") | F22: =IFERROR(VLOOKUP(A22,ListaIngredientes!$A$5:$F$155,6,FALSE),"") | H22: =IFERROR(E22*F22,"")
B23: =IFERROR(VLOOKUP(A23,ListaIngredientes!$A$5:$F$155,2,FALSE),"") | D23: =IFERROR(VLOOKUP(A23,Tabela2[],3,FALSE),"") | F23: =IFERROR(VLOOKUP(A23,ListaIngredientes!$A$5:$F$155,6,FALSE),"") | H23: =IFERROR(E23*F23,"")
B24: =IFERROR(VLOOKUP(A24,ListaIngredientes!$A$5:$F$155,2,FALSE),"") | D24: =IFERROR(VLOOKUP(A24,Tabela2[],3,FALSE),"") | F24: =IFERROR(VLOOKUP(A24,ListaIngredientes!$A$5:$F$155,6,FALSE),"") | H24: =IFERROR(E24*F24,"")
B25: =IFERROR(VLOOKUP(A25,ListaIngredientes!$A$5:$F$155,2,FALSE),"") | D25: =IFERROR(VLOOKUP(A25,Tabela2[],3,FALSE),"") | F25: =IFERROR(VLOOKUP(A25,ListaIngredientes!$A$5:$F$155,6,FALSE),"") | H25: =IFERROR(E25*F25,"")
B26: =IFERROR(VLOOKUP(A26,ListaIngredientes!$A$5:$F$155,2,FALSE),"") | D26: =IFERROR(VLOOKUP(A26,Tabela2[],3,FALSE),"") | F26: =IFERROR(VLOOKUP(A26,ListaIngredientes!$A$5:$F$155,6,FALSE),"") | H26: =IFERROR(E26*F26,"")
B27: =IFERROR(VLOOKUP(A27,ListaIngredientes!$A$5:$F$155,2,FALSE),"") | D27: =IFERROR(VLOOKUP(A27,Tabela2[],3,FALSE),"") | F27: =IFERROR(VLOOKUP(A27,ListaIngredientes!$A$5:$F$155,6,FALSE),"") | H27: =IFERROR(E27*F27,"")
F28: soma | H28: =SUM(H8:H27) -> 375.20366
F29: soma | H29: =IFERROR(E29*F29,"")

Sheet BISCOITINHO DE COCO COM CANELA
A1: cod | B1: 501 | C1: =VLOOKUP(B1,PRODUTOS!$A$7:$E$204,2,FALSE) -> P A S T E L | E1: =C3 -> 20.667821 | G1: SOBREMESA/DOCE
A2: Despesas Fixas | C2: 0.2 | E2: Preço Venda Unit | G2: =IFERROR(C3/(1-C2-C5),"") -> 68.892735
A3: Custo Unitário | C3: =IFERROR(C6/C4,"") -> 20.667821 | E3: Luro s/Venda | G3: =G2*C5 -> 34.446368
A4: Quantidade Produzida | C4: 13 | E4: Preço Praticado | G4: 15
A5: Lucro s/Venda | C5: 0.5 | E5: Lucro Praticado | G5: =1-C3/G4-C2 -> -0.5778547
A6: Gasto Total | C6: =SUM(H8:H28) -> 268.68167 | E6: Lucro Praticado | G6: =G5*G4 -> -8.6678205
A7: cod Prod | B7: Descrição ingredientes | D7: unid | E7: quantiadade | F7: valor $ | H7: Subtotal
A8: 101 | B8: =IFERROR(VLOOKUP(A8,ListaIngredientes!$A$5:$F$155,2,FALSE),"") | D8: =IFERROR(VLOOKUP(A8,Tabela2[],3,FALSE),"") | E8: 4 | F8: =IFERROR(VLOOKUP(A8,ListaIngredientes!$A$5:$F$155,6,FALSE),"") | H8: =IFERROR(E8*F8,"")
A9: 223 | B9: =IFERROR(VLOOKUP(A9,ListaIngredientes!$A$5:$F$155,2,FALSE),"") -> SACO PASCOA 24X24 | D9: =IFERROR(VLOOKUP(A9,Tabela2[],3,FALSE),"") -> u | E9: 4 | F9: =IFERROR(VLOOKUP(A9,ListaIngredientes!$A$5:$F$155,6,FALSE),"") -> 0.4 | H9: =IFERROR(E9*F9,"") -> 1.6
A10: 202 | B10: =IFERROR(VLOOKUP(A10,ListaIngredientes!$A$5:$F$155,2,FALSE),"") -> 0 | D10: =IFERROR(VLOOKUP(A10,Tabela2[],3,FALSE),"") -> 0 | E10: 80 | F10: =IFERROR(VLOOKUP(A10,ListaIngredientes!$A$5:$F$155,6,FALSE),"") -> 0 | H10: =IFERROR(E10*F10,"") -> 0
A11: 230 | B11: =IFERROR(VLOOKUP(A11,ListaIngredientes!$A$5:$F$155,2,FALSE),"") -> 0 | D11: =IFERROR(VLOOKUP(A11,Tabela2[],3,FALSE),"") -> u | E11: 85 | F11: =IFERROR(VLOOKUP(A11,ListaIngredientes!$A$5:$F$155,6,FALSE),"") -> 0.149 | H11: =IFERROR(E11*F11,"") -> 12.665
A12: 158 | B12: =IFERROR(VLOOKUP(A12,ListaIngredientes!$A$5:$F$155,2,FALSE),"") -> ESSENCIA DE BAUNILHA | D12: =IFERROR(VLOOKUP(A12,Tabela2[],3,FALSE),"") -> ML | E12: 130 | F12: =IFERROR(VLOOKUP(A12,ListaIngredientes!$A$5:$F$155,6,FALSE),"") -> 0.099666667 | H12: =IFERROR(E12*F12,"") -> 12.956667
A13: 159 | B13: =IFERROR(VLOOKUP(A13,ListaIngredientes!$A$5:$F$155,2,FALSE),"") -> essencia de mel | D13: =IFERROR(VLOOKUP(A13,Tabela2[],3,FALSE),"") -> u | E13: 60 | F13: =IFERROR(VLOOKUP(A13,ListaIngredientes!$A$5:$F$155,6,FALSE),"") -> 2.59 | H13: =IFERROR(E13*F13,"") -> 155.4
A14: 188 | B14: =IFERROR(VLOOKUP(A14,ListaIngredientes!$A$5:$F$155,2,FALSE),"") -> LATA PALHA ITALIANA | D14: =IFERROR(VLOOKUP(A14,Tabela2[],3,FALSE),"") -> U | E14: 50 | F14: =IFERROR(VLOOKUP(A14,ListaIngredientes!$A$5:$F$155,6,FALSE),"") -> 1.59 | H14: =IFERROR(E14*F14,"") -> 79.5
A15: 203 | B15: =IFERROR(VLOOKUP(A15,ListaIngredientes!$A$5:$F$155,2,FALSE),"") -> 0 | D15: =IFERROR(VLOOKUP(A15,Tabela2[],3,FALSE),"") -> 0 | E15: 2 | F15: =IFERROR(VLOOKUP(A15,ListaIngredientes!$A$5:$F$155,6,FALSE),"") -> 0 | H15: =IFERROR(E15*F15,"") -> 0
A16: 106 | B16: =IFERROR(VLOOKUP(A16,ListaIngredientes!$A$5:$F$155,2,FALSE),"") -> Colorau | D16: =IFERROR(VLOOKUP(A16,Tabela2[],3,FALSE),"") -> g | E16: 10 | F16: =IFERROR(VLOOKUP(A16,ListaIngredientes!$A$5:$F$155,6,FALSE),"") -> 0.02 | H16: =IFERROR(E16*F16,"") -> 0.2
A17: 126 | B17: =IFERROR(VLOOKUP(A17,ListaIngredientes!$A$5:$F$155,2,FALSE),"") -> CHOCOLTE BRANCO | D17: =IFERROR(VLOOKUP(A17,Tabela2[],3,FALSE),"") -> KG | E17: 40 | F17: =IFERROR(VLOOKUP(A17,ListaIngredientes!$A$5:$F$155,6,FALSE),"") -> 0.159 | H17: =IFERROR(E17*F17,"") -> 6.36
B18: =IFERROR(VLOOKUP(A18,ListaIngredientes!$A$5:$F$155,2,FALSE),"") | D18: =IFERROR(VLOOKUP(A18,Tabela2[],3,FALSE),"") | F18: =IFERROR(VLOOKUP(A18,ListaIngredientes!$A$5:$F$155,6,FALSE),"") | H18: =IFERROR(E18*F18,"")
B19: =IFERROR(VLOOKUP(A19,ListaIngredientes!$A$5:$F$155,2,FALSE),"") | D19: =IFERROR(VLOOKUP(A19,Tabela2[],3,FALSE),"") | F19: =IFERROR(VLOOKUP(A19,ListaIngredientes!$A$5:$F$155,6,FALSE),"") | H19: =IFERROR(E19*F19,"")
B20: =IFERROR(VLOOKUP(A20,ListaIngredientes!$A$5:$F$155,2,FALSE),"") | D20: =IFERROR(VLOOKUP(A20,Tabela2[],3,FALSE),"") | F20: =IFERROR(VLOOKUP(A20,ListaIngredientes!$A$5:$F$155,6,FALSE),"") | H20: =IFERROR(E20*F20,"")
B21: =IFERROR(VLOOKUP(A21,ListaIngredientes!$A$5:$F$155,2,FALSE),"") | D21: =IFERROR(VLOOKUP(A21,Tabela2[],3,FALSE),"") | F21: =IFERROR(VLOOKUP(A21,ListaIngredientes!$A$5:$F$155,6,FALSE),"") | H21: =IFERROR(E21*F21,"")
B22: =IFERROR(VLOOKUP(A22,ListaIngredientes!$A$5:$F$155,2,FALSE),"") | D22: =IFERROR(VLOOKUP(A22,Tabela2[],3,FALSE),"") | F22: =IFERROR(VLOOKUP(A22,ListaIngredientes!$A$5:$F$155,6,FALSE),"") | H22: =IFERROR(E22*F22,"")
B23: =IFERROR(VLOOKUP(A23,ListaIngredientes!$A$5:$F$155,2,FALSE),"") | D23: =IFERROR(VLOOKUP(A23,Tabela2[],3,FALSE),"") | F23: =IFERROR(VLOOKUP(A23,ListaIngredientes!$A$5:$F$155,6,FALSE),"") | H23: =IFERROR(E23*F23,"")
B24: =IFERROR(VLOOKUP(A24,ListaIngredientes!$A$5:$F$155,2,FALSE),"") | D24: =IFERROR(VLOOKUP(A24,Tabela2[],3,FALSE),"") | F24: =IFERROR(VLOOKUP(A24,ListaIngredientes!$A$5:$F$155,6,FALSE),"") | H24: =IFERROR(E24*F24,"")
B25: =IFERROR(VLOOKUP(A25,ListaIngredientes!$A$5:$F$155,2,FALSE),"") | D25: =IFERROR(VLOOKUP(A25,Tabela2[],3,FALSE),"") | F25: =IFERROR(VLOOKUP(A25,ListaIngredientes!$A$5:$F$155,6,FALSE),"") | H25: =IFERROR(E25*F25,"")
B26: =IFERROR(VLOOKUP(A26,ListaIngredientes!$A$5:$F$155,2,FALSE),"") | D26: =IFERROR(VLOOKUP(A26,Tabela2[],3,FALSE),"") | F26: =IFERROR(VLOOKUP(A26,ListaIngredientes!$A$5:$F$155,6,FALSE),"") | H26: =IFERROR(E26*F26,"")
B27: =IFERROR(VLOOKUP(A27,ListaIngredientes!$A$5:$F$155,2,FALSE),"") | D27: =IFERROR(VLOOKUP(A27,Tabela2[],3,FALSE),"") | F27: =IFERROR(VLOOKUP(A27,ListaIngredientes!$A$5:$F$155,6,FALSE),"") | H27: =IFERROR(E27*F27,"")
F28: soma | H28: =IFERROR(E28*F28,"")
H29: =SUM(H8:H27) -> 268.68167

Sheet BISCOITINHO DE LIMÃO
A1: cod | B1: 501 | C1: =VLOOKUP(B1,PRODUTOS!$A$7:$E$204,2,FALSE) -> P A S T E L | E1: =C3 -> 20.181644 | G1: SOBREMESA/DOCE
A2: Despesas Fixas | C2: 0.2 | E2: Preço Venda Unit | G2: =IFERROR(C3/(1-C2-C5),"") -> 67.272145
A3: Custo Unitário | C3: =IFERROR(C6/C4,"") -> 20.181644 | E3: Luro s/Venda | G3: =G2*C5 -> 33.636073
A4: Quantidade Produzida | C4: 13 | E4: Preço Praticado | G4: 15
A5: Lucro s/Venda | C5: 0.5 | E5: Lucro Praticado | G5: =1-C3/G4-C2 -> -0.54544291
A6: Gasto Total | C6: =SUM(H8:H28) -> 262.36137 | E6: Lucro Praticado | G6: =G5*G4 -> -8.1816436
A7: cod Prod | B7: Descrição ingredientes | D7: unid | E7: quantiadade | F7: valor $ | H7: Subtotal
A8: 101 | B8: =IFERROR(VLOOKUP(A8,ListaIngredientes!$A$5:$F$155,2,FALSE),"") | D8: =IFERROR(VLOOKUP(A8,Tabela2[],3,FALSE),"") | E8: 4 | F8: =IFERROR(VLOOKUP(A8,ListaIngredientes!$A$5:$F$155,6,FALSE),"") | H8: =IFERROR(E8*F8,"")
A9: 223 | B9: =IFERROR(VLOOKUP(A9,ListaIngredientes!$A$5:$F$155,2,FALSE),"") -> SACO PASCOA 24X24 | D9: =IFERROR(VLOOKUP(A9,Tabela2[],3,FALSE),"") -> u | E9: 4 | F9: =IFERROR(VLOOKUP(A9,ListaIngredientes!$A$5:$F$155,6,FALSE),"") -> 0.4 | H9: =IFERROR(E9*F9,"") -> 1.6
A10: 202 | B10: =IFERROR(VLOOKUP(A10,ListaIngredientes!$A$5:$F$155,2,FALSE),"") -> 0 | D10: =IFERROR(VLOOKUP(A10,Tabela2[],3,FALSE),"") -> 0 | E10: 80 | F10: =IFERROR(VLOOKUP(A10,ListaIngredientes!$A$5:$F$155,6,FALSE),"") -> 0 | H10: =IFERROR(E10*F10,"") -> 0
A11: 230 | B11: =IFERROR(VLOOKUP(A11,ListaIngredientes!$A$5:$F$155,2,FALSE),"") -> 0 | D11: =IFERROR(VLOOKUP(A11,Tabela2[],3,FALSE),"") -> u | E11: 85 | F11: =IFERROR(VLOOKUP(A11,ListaIngredientes!$A$5:$F$155,6,FALSE),"") -> 0.149 | H11: =IFERROR(E11*F11,"") -> 12.665
A12: 158 | B12: =IFERROR(VLOOKUP(A12,ListaIngredientes!$A$5:$F$155,2,FALSE),"") -> ESSENCIA DE BAUNILHA | D12: =IFERROR(VLOOKUP(A12,Tabela2[],3,FALSE),"") -> ML | E12: 130 | F12: =IFERROR(VLOOKUP(A12,ListaIngredientes!$A$5:$F$155,6,FALSE),"") -> 0.099666667 | H12: =IFERROR(E12*F12,"") -> 12.956667
A13: 159 | B13: =IFERROR(VLOOKUP(A13,ListaIngredientes!$A$5:$F$155,2,FALSE),"") -> essencia de mel | D13: =IFERROR(VLOOKUP(A13,Tabela2[],3,FALSE),"") -> u | E13: 60 | F13: =IFERROR(VLOOKUP(A13,ListaIngredientes!$A$5:$F$155,6,FALSE),"") -> 2.59 | H13: =IFERROR(E13*F13,"") -> 155.4
A14: 188 | B14: =IFERROR(VLOOKUP(A14,ListaIngredientes!$A$5:$F$155,2,FALSE),"") -> LATA PALHA ITALIANA | D14: =IFERROR(VLOOKUP(A14,Tabela2[],3,FALSE),"") -> U | E14: 50 | F14: =IFERROR(VLOOKUP(A14,ListaIngredientes!$A$5:$F$155,6,FALSE),"") -> 1.59 | H14: =IFERROR(E14*F14,"") -> 79.5
A15: 203 | B15: =IFERROR(VLOOKUP(A15,ListaIngredientes!$A$5:$F$155,2,FALSE),"") -> 0 | D15: =IFERROR(VLOOKUP(A15,Tabela2[],3,FALSE),"") -> 0 | E15: 2 | F15: =IFERROR(VLOOKUP(A15,ListaIngredientes!$A$5:$F$155,6,FALSE),"") -> 0 | H15: =IFERROR(E15*F15,"") -> 0
A16: 191 | B16: =IFERROR(VLOOKUP(A16,ListaIngredientes!$A$5:$F$155,2,FALSE),"") -> leite de coco em po | D16: =IFERROR(VLOOKUP(A16,Tabela2[],3,FALSE),"") -> kg | E16: 3 | F16: =IFERROR(VLOOKUP(A16,ListaIngredientes!$A$5:$F$155,6,FALSE),"") -> 0.0799 | H16: =IFERROR(E16*F16,"") -> 0.2397
B17: =IFERROR(VLOOKUP(A17,ListaIngredientes!$A$5:$F$155,2,FALSE),"") | D17: =IFERROR(VLOOKUP(A17,Tabela2[],3,FALSE),"") | F17: =IFERROR(VLOOKUP(A17,ListaIngredientes!$A$5:$F$155,6,FALSE),"") | H17: =IFERROR(E17*F17,"")
B18: =IFERROR(VLOOKUP(A18,ListaIngredientes!$A$5:$F$155,2,FALSE),"") | D18: =IFERROR(VLOOKUP(A18,Tabela2[],3,FALSE),"") | F18: =IFERROR(VLOOKUP(A18,ListaIngredientes!$A$5:$F$155,6,FALSE),"") | H18: =IFERROR(E18*F18,"")
B19: =IFERROR(VLOOKUP(A19,ListaIngredientes!$A$5:$F$155,2,FALSE),"") | D19: =IFERROR(VLOOKUP(A19,Tabela2[],3,FALSE),"") | F19: =IFERROR(VLOOKUP(A19,ListaIngredientes!$A$5:$F$155,6,FALSE),"") | H19: =IFERROR(E19*F19,"")
B20: =IFERROR(VLOOKUP(A20,ListaIngredientes!$A$5:$F$155,2,FALSE),"") | D20: =IFERROR(VLOOKUP(A20,Tabela2[],3,FALSE),"") | F20: =IFERROR(VLOOKUP(A20,ListaIngredientes!$A$5:$F$155,6,FALSE),"") | H20: =IFERROR(E20*F20,"")
B21: =IFERROR(VLOOKUP(A21,ListaIngredientes!$A$5:$F$155,2,FALSE),"") | D21: =IFERROR(VLOOKUP(A21,Tabela2[],3,FALSE),"") | F21: =IFERROR(VLOOKUP(A21,ListaIngredientes!$A$5:$F$155,6,FALSE),"") | H21: =IFERROR(E21*F21,"")
B22: =IFERROR(VLOOKUP(A22,ListaIngredientes!$A$5:$F$155,2,FALSE),"") | D22: =IFERROR(VLOOKUP(A22,Tabela2[],3,FALSE),"") | F22: =IFERROR(VLOOKUP(A22,ListaIngredientes!$A$5:$F$155,6,FALSE),"") | H22: =IFERROR(E22*F22,"")
B23: =IFERROR(VLOOKUP(A23,ListaIngredientes!$A$5:$F$155,2,FALSE),"") | D23: =IFERROR(VLOOKUP(A23,Tabela2[],3,FALSE),"") | F23: =IFERROR(VLOOKUP(A23,ListaIngredientes!$A$5:$F$155,6,FALSE),"") | H23: =IFERROR(E23*F23,"")
B24: =IFERROR(VLOOKUP(A24,ListaIngredientes!$A$5:$F$155,2,FALSE),"") | D24: =IFERROR(VLOOKUP(A24,Tabela2[],3,FALSE),"") | F24: =IFERROR(VLOOKUP(A24,ListaIngredientes!$A$5:$F$155,6,FALSE),"") | H24: =IFERROR(E24*F24,"")
B25: =IFERROR(VLOOKUP(A25,ListaIngredientes!$A$5:$F$155,2,FALSE),"") | D25: =IFERROR(VLOOKUP(A25,Tabela2[],3,FALSE),"") | F25: =IFERROR(VLOOKUP(A25,ListaIngredientes!$A$5:$F$155,6,FALSE),"") | H25: =IFERROR(E25*F25,"")
B26: =IFERROR(VLOOKUP(A26,ListaIngredientes!$A$5:$F$155,2,FALSE),"") | D26: =IFERROR(VLOOKUP(A26,Tabela2[],3,FALSE),"") | F26: =IFERROR(VLOOKUP(A26,ListaIngredientes!$A$5:$F$155,6,FALSE),"") | H26: =IFERROR(E26*F26,"")
B27: =IFERROR(VLOOKUP(A27,ListaIngredientes!$A$5:$F$155,2,FALSE),"") | D27: =IFERROR(VLOOKUP(A27,Tabela2[],3,FALSE),"") | F27: =IFERROR(VLOOKUP(A27,ListaIngredientes!$A$5:$F$155,6,FALSE),"") | H27: =IFERROR(E27*F27,"")
F28: soma | H28: =IFERROR(E28*F28,"")
H29: =SUM(H8:H27) -> 262.36137

Sheet COOKIES
A1: cod | B1: 501 | C1: =VLOOKUP(B1,PRODUTOS!$A$7:$E$204,2,FALSE) -> P A S T E L | E1: =C3 -> 2.5117652 | G1: SOBREMESA/DOCE
A2: Despesas Fixas | C2: 0.2 | E2: Preço Venda Unit | G2: =IFERROR(C3/(1-C2-C5),"") -> 8.3725507
A3: Custo Unitário | C3: =IFERROR(C6/C4,"") -> 2.5117652 | E3: Luro s/Venda | G3: =G2*C5 -> 4.1862754
A4: Quantidade Produzida | C4: 13 | E4: Preço Praticado | G4: 15
A5: Lucro s/Venda | C5: 0.5 | E5: Lucro Praticado | G5: =1-C3/G4-C2 -> 0.63254899
A6: Gasto Total | C6: =SUM(H8:H28) -> 32.652948 | E6: Lucro Praticado | G6: =G5*G4 -> 9.4882348
A7: cod Prod | B7: Descrição ingredientes | D7: unid | E7: quantiadade | F7: valor $ | H7: Subtotal
A8: 101 | B8: =IFERROR(VLOOKUP(A8,ListaIngredientes!$A$5:$F$155,2,FALSE),"") | D8: =IFERROR(VLOOKUP(A8,Tabela2[],3,FALSE),"") | E8: 9 | F8: =IFERROR(VLOOKUP(A8,ListaIngredientes!$A$5:$F$155,6,FALSE),"") | H8: =IFERROR(E8*F8,"")
A9: 143 | B9: =IFERROR(VLOOKUP(A9,ListaIngredientes!$A$5:$F$155,2,FALSE),"") -> 0 | D9: =IFERROR(VLOOKUP(A9,Tabela2[],3,FALSE),"") -> 0 | E9: 9 | F9: =IFERROR(VLOOKUP(A9,ListaIngredientes!$A$5:$F$155,6,FALSE),"") -> 0 | H9: =IFERROR(E9*F9,"") -> 0
A10: 230 | B10: =IFERROR(VLOOKUP(A10,ListaIngredientes!$A$5:$F$155,2,FALSE),"") -> 0 | D10: =IFERROR(VLOOKUP(A10,Tabela2[],3,FALSE),"") -> u | E10: 75 | F10: =IFERROR(VLOOKUP(A10,ListaIngredientes!$A$5:$F$155,6,FALSE),"") -> 0.149 | H10: =IFERROR(E10*F10,"") -> 11.175
A11: 125 | B11: =IFERROR(VLOOKUP(A11,ListaIngredientes!$A$5:$F$155,2,FALSE),"") -> 0 | D11: =IFERROR(VLOOKUP(A11,Tabela2[],3,FALSE),"") -> 0 | E11: 200 | F11: =IFERROR(VLOOKUP(A11,ListaIngredientes!$A$5:$F$155,6,FALSE),"") -> 0 | H11: =IFERROR(E11*F11,"") -> 0
A12: 158 | B12: =IFERROR(VLOOKUP(A12,ListaIngredientes!$A$5:$F$155,2,FALSE),"") -> ESSENCIA DE BAUNILHA | D12: =IFERROR(VLOOKUP(A12,Tabela2[],3,FALSE),"") -> ML | E12: 150 | F12: =IFERROR(VLOOKUP(A12,ListaIngredientes!$A$5:$F$155,6,FALSE),"") -> 0.099666667 | H12: =IFERROR(E12*F12,"") -> 14.95
A13: 249 | B13: =IFERROR(VLOOKUP(A13,ListaIngredientes!$A$5:$F$155,2,FALSE),"") -> Whey Protein | D13: =IFERROR(VLOOKUP(A13,Tabela2[],3,FALSE),"") -> g | E13: 35 | F13: =IFERROR(VLOOKUP(A13,ListaIngredientes!$A$5:$F$155,6,FALSE),"") -> 0.017001534 | H13: =IFERROR(E13*F13,"") -> 0.59505368
A14: 160 | B14: =IFERROR(VLOOKUP(A14,ListaIngredientes!$A$5:$F$155,2,FALSE),"") -> farinha de amendoas | D14: =IFERROR(VLOOKUP(A14,Tabela2[],3,FALSE),"") -> kg | E14: 10 | F14: =IFERROR(VLOOKUP(A14,ListaIngredientes!$A$5:$F$155,6,FALSE),"") -> 0.063 | H14: =IFERROR(E14*F14,"") -> 0.63
A15: 163 | B15: =IFERROR(VLOOKUP(A15,ListaIngredientes!$A$5:$F$155,2,FALSE),"") -> fermento biologico | D15: =IFERROR(VLOOKUP(A15,Tabela2[],3,FALSE),"") -> kg | E15: 5 | F15: =IFERROR(VLOOKUP(A15,ListaIngredientes!$A$5:$F$155,6,FALSE),"") -> 0.05512 | H15: =IFERROR(E15*F15,"") -> 0.2756
B16: =IFERROR(VLOOKUP(A16,ListaIngredientes!$A$5:$F$155,2,FALSE),"") | D16: =IFERROR(VLOOKUP(A16,Tabela2[],3,FALSE),"") | F16: =IFERROR(VLOOKUP(A16,ListaIngredientes!$A$5:$F$155,6,FALSE),"") | H16: =IFERROR(E16*F16,"")
B17: =IFERROR(VLOOKUP(A17,ListaIngredientes!$A$5:$F$155,2,FALSE),"") | D17: =IFERROR(VLOOKUP(A17,Tabela2[],3,FALSE),"") | F17: =IFERROR(VLOOKUP(A17,ListaIngredientes!$A$5:$F$155,6,FALSE),"") | H17: =IFERROR(E17*F17,"")
A18: 139 | B18: =IFERROR(VLOOKUP(A18,ListaIngredientes!$A$5:$F$155,2,FALSE),"") -> cravo da india | D18: =IFERROR(VLOOKUP(A18,Tabela2[],3,FALSE),"") -> g | E18: 400 | F18: =IFERROR(VLOOKUP(A18,ListaIngredientes!$A$5:$F$155,6,FALSE),"") -> 0.00058823529 | H18: =IFERROR(E18*F18,"") -> 0.23529412
B20: =IFERROR(VLOOKUP(A20,ListaIngredientes!$A$5:$F$155,2,FALSE),"") | D20: =IFERROR(VLOOKUP(A20,Tabela2[],3,FALSE),"") | F20: =IFERROR(VLOOKUP(A20,ListaIngredientes!$A$5:$F$155,6,FALSE),"") | H20: =IFERROR(E20*F20,"")
A21: 203 | B21: =IFERROR(VLOOKUP(A21,ListaIngredientes!$A$5:$F$155,2,FALSE),"") -> 0 | D21: =IFERROR(VLOOKUP(A21,Tabela2[],3,FALSE),"") -> 0 | E21: 3 | F21: =IFERROR(VLOOKUP(A21,ListaIngredientes!$A$5:$F$155,6,FALSE),"") -> 0 | H21: =IFERROR(E21*F21,"") -> 0
A22: 156 | B22: =IFERROR(VLOOKUP(A22,ListaIngredientes!$A$5:$F$155,2,FALSE),"") -> embalagem quiche | D22: =IFERROR(VLOOKUP(A22,Tabela2[],3,FALSE),"") -> u | E22: 8 | F22: =IFERROR(VLOOKUP(A22,ListaIngredientes!$A$5:$F$155,6,FALSE),"") -> 0.599 | H22: =IFERROR(E22*F22,"") -> 4.792
B23: =IFERROR(VLOOKUP(A23,ListaIngredientes!$A$5:$F$155,2,FALSE),"") | D23: =IFERROR(VLOOKUP(A23,Tabela2[],3,FALSE),"") | F23: =IFERROR(VLOOKUP(A23,ListaIngredientes!$A$5:$F$155,6,FALSE),"") | H23: =IFERROR(E23*F23,"")
B24: =IFERROR(VLOOKUP(A24,ListaIngredientes!$A$5:$F$155,2,FALSE),"") | D24: =IFERROR(VLOOKUP(A24,Tabela2[],3,FALSE),"") | F24: =IFERROR(VLOOKUP(A24,ListaIngredientes!$A$5:$F$155,6,FALSE),"") | H24: =IFERROR(E24*F24,"")
B25: =IFERROR(VLOOKUP(A25,ListaIngredientes!$A$5:$F$155,2,FALSE),"") | D25: =IFERROR(VLOOKUP(A25,Tabela2[],3,FALSE),"") | F25: =IFERROR(VLOOKUP(A25,ListaIngredientes!$A$5:$F$155,6,FALSE),"") | H25: =IFERROR(E25*F25,"")
B26: =IFERROR(VLOOKUP(A26,ListaIngredientes!$A$5:$F$155,2,FALSE),"") | D26: =IFERROR(VLOOKUP(A26,Tabela2[],3,FALSE),"") | F26: =IFERROR(VLOOKUP(A26,ListaIngredientes!$A$5:$F$155,6,FALSE),"") | H26: =IFERROR(E26*F26,"")
B27: =IFERROR(VLOOKUP(A27,ListaIngredientes!$A$5:$F$155,2,FALSE),"") | D27: =IFERROR(VLOOKUP(A27,Tabela2[],3,FALSE),"") | F27: =IFERROR(VLOOKUP(A27,ListaIngredientes!$A$5:$F$155,6,FALSE),"") | H27: =IFERROR(E27*F27,"")
F28: soma | H28: =IFERROR(E28*F28,"")
H29: =SUM(H8:H27) -> 32.652948

Sheet PÃO DE FORMA
A1: cod | B1: 501 | C1: =VLOOKUP(B1,PRODUTOS!$A$7:$E$204,2,FALSE) -> P A S T E L | E1: =C3 -> 2.1559472 | G1: SOBREMESA/DOCE
A2: Despesas Fixas | C2: 0.2 | E2: Preço Venda Unit | G2: =IFERROR(C3/(1-C2-C5),"") -> 7.1864906
A3: Custo Unitário | C3: =IFERROR(C6/C4,"") -> 2.1559472 | E3: Luro s/Venda | G3: =G2*C5 -> 3.5932453
A4: Quantidade Produzida | C4: 13 | E4: Preço Praticado | G4: 15
A5: Lucro s/Venda | C5: 0.5 | E5: Lucro Praticado | G5: =1-C3/G4-C2 -> 0.65627019
A6: Gasto Total | C6: =SUM(H8:H28) -> 28.027313 | E6: Lucro Praticado | G6: =G5*G4 -> 9.8440528
A7: cod Prod | B7: Descrição ingredientes | D7: unid | E7: quantiadade | F7: valor $ | H7: Subtotal
A8: 101 | B8: =IFERROR(VLOOKUP(A8,ListaIngredientes!$A$5:$F$155,2,FALSE),"") | D8: =IFERROR(VLOOKUP(A8,Tabela2[],3,FALSE),"") | E8: 2 | F8: =IFERROR(VLOOKUP(A8,ListaIngredientes!$A$5:$F$155,6,FALSE),"") | H8: =IFERROR(E8*F8,"")
A9: 220 | B9: =IFERROR(VLOOKUP(A9,ListaIngredientes!$A$5:$F$155,2,FALSE),"") -> queijo prato | D9: =IFERROR(VLOOKUP(A9,Tabela2[],3,FALSE),"") -> kg | E9: 2 | F9: =IFERROR(VLOOKUP(A9,ListaIngredientes!$A$5:$F$155,6,FALSE),"") -> 0.04989 | H9: =IFERROR(E9*F9,"") -> 0.09978
A10: 202 | B10: =IFERROR(VLOOKUP(A10,ListaIngredientes!$A$5:$F$155,2,FALSE),"") -> 0 | D10: =IFERROR(VLOOKUP(A10,Tabela2[],3,FALSE),"") -> 0 | E10: 30 | F10: =IFERROR(VLOOKUP(A10,ListaIngredientes!$A$5:$F$155,6,FALSE),"") -> 0 | H10: =IFERROR(E10*F10,"") -> 0
A11: 182 | B11: =IFERROR(VLOOKUP(A11,ListaIngredientes!$A$5:$F$155,2,FALSE),"") -> GERGILIM | D11: =IFERROR(VLOOKUP(A11,Tabela2[],3,FALSE),"") -> KG | E11: 2 | F11: =IFERROR(VLOOKUP(A11,ListaIngredientes!$A$5:$F$155,6,FALSE),"") -> 0.029 | H11: =IFERROR(E11*F11,"") -> 0.058
A12: 158 | B12: =IFERROR(VLOOKUP(A12,ListaIngredientes!$A$5:$F$155,2,FALSE),"") -> ESSENCIA DE BAUNILHA | D12: =IFERROR(VLOOKUP(A12,Tabela2[],3,FALSE),"") -> ML | E12: 260 | F12: =IFERROR(VLOOKUP(A12,ListaIngredientes!$A$5:$F$155,6,FALSE),"") -> 0.099666667 | H12: =IFERROR(E12*F12,"") -> 25.913333
A13: 194 | B13: =IFERROR(VLOOKUP(A13,ListaIngredientes!$A$5:$F$155,2,FALSE),"") -> Maçã | D13: =IFERROR(VLOOKUP(A13,Tabela2[],3,FALSE),"") -> kg | E13: 100 | F13: =IFERROR(VLOOKUP(A13,ListaIngredientes!$A$5:$F$155,6,FALSE),"") -> 0.00399 | H13: =IFERROR(E13*F13,"") -> 0.399
A14: 232 | B14: =IFERROR(VLOOKUP(A14,ListaIngredientes!$A$5:$F$155,2,FALSE),"") -> xilitol | D14: =IFERROR(VLOOKUP(A14,Tabela2[],3,FALSE),"") -> kg | E14: 20 | F14: =IFERROR(VLOOKUP(A14,ListaIngredientes!$A$5:$F$155,6,FALSE),"") -> 0.03652 | H14: =IFERROR(E14*F14,"") -> 0.7304
A15: 203 | B15: =IFERROR(VLOOKUP(A15,ListaIngredientes!$A$5:$F$155,2,FALSE),"") -> 0 | D15: =IFERROR(VLOOKUP(A15,Tabela2[],3,FALSE),"") -> 0 | E15: 7 | F15: =IFERROR(VLOOKUP(A15,ListaIngredientes!$A$5:$F$155,6,FALSE),"") -> 0 | H15: =IFERROR(E15*F15,"") -> 0
A16: 163 | B16: =IFERROR(VLOOKUP(A16,ListaIngredientes!$A$5:$F$155,2,FALSE),"") -> fermento biologico | D16: =IFERROR(VLOOKUP(A16,Tabela2[],3,FALSE),"") -> kg | E16: 15 | F16: =IFERROR(VLOOKUP(A16,ListaIngredientes!$A$5:$F$155,6,FALSE),"") -> 0.05512 | H16: =IFERROR(E16*F16,"") -> 0.8268
B17: =IFERROR(VLOOKUP(A17,ListaIngredientes!$A$5:$F$155,2,FALSE),"") | D17: =IFERROR(VLOOKUP(A17,Tabela2[],3,FALSE),"") | F17: =IFERROR(VLOOKUP(A17,ListaIngredientes!$A$5:$F$155,6,FALSE),"") | H17: =IFERROR(E17*F17,"")
B18: =IFERROR(VLOOKUP(A18,ListaIngredientes!$A$5:$F$155,2,FALSE),"") | D18: =IFERROR(VLOOKUP(A18,Tabela2[],3,FALSE),"") | F18: =IFERROR(VLOOKUP(A18,ListaIngredientes!$A$5:$F$155,6,FALSE),"") | H18: =IFERROR(E18*F18,"")
B19: =IFERROR(VLOOKUP(A19,ListaIngredientes!$A$5:$F$155,2,FALSE),"") | D19: =IFERROR(VLOOKUP(A19,Tabela2[],3,FALSE),"") | F19: =IFERROR(VLOOKUP(A19,ListaIngredientes!$A$5:$F$155,6,FALSE),"") | H19: =IFERROR(E19*F19,"")
B20: =IFERROR(VLOOKUP(A20,ListaIngredientes!$A$5:$F$155,2,FALSE),"") | D20: =IFERROR(VLOOKUP(A20,Tabela2[],3,FALSE),"") | F20: =IFERROR(VLOOKUP(A20,ListaIngredientes!$A$5:$F$155,6,FALSE),"") | H20: =IFERROR(E20*F20,"")
B21: =IFERROR(VLOOKUP(A21,ListaIngredientes!$A$5:$F$155,2,FALSE),"") | D21: =IFERROR(VLOOKUP(A21,Tabela2[],3,FALSE),"") | F21: =IFERROR(VLOOKUP(A21,ListaIngredientes!$A$5:$F$155,6,FALSE),"") | H21: =IFERROR(E21*F21,"")
B22: =IFERROR(VLOOKUP(A22,ListaIngredientes!$A$5:$F$155,2,FALSE),"") | D22: =IFERROR(VLOOKUP(A22,Tabela2[],3,FALSE),"") | F22: =IFERROR(VLOOKUP(A22,ListaIngredientes!$A$5:$F$155,6,FALSE),"") | H22: =IFERROR(E22*F22,"")
B23: =IFERROR(VLOOKUP(A23,ListaIngredientes!$A$5:$F$155,2,FALSE),"") | D23: =IFERROR(VLOOKUP(A23,Tabela2[],3,FALSE),"") | F23: =IFERROR(VLOOKUP(A23,ListaIngredientes!$A$5:$F$155,6,FALSE),"") | H23: =IFERROR(E23*F23,"")
B24: =IFERROR(VLOOKUP(A24,ListaIngredientes!$A$5:$F$155,2,FALSE),"") | D24: =IFERROR(VLOOKUP(A24,Tabela2[],3,FALSE),"") | F24: =IFERROR(VLOOKUP(A24,ListaIngredientes!$A$5:$F$155,6,FALSE),"") | H24: =IFERROR(E24*F24,"")
B25: =IFERROR(VLOOKUP(A25,ListaIngredientes!$A$5:$F$155,2,FALSE),"") | D25: =IFERROR(VLOOKUP(A25,Tabela2[],3,FALSE),"") | F25: =IFERROR(VLOOKUP(A25,ListaIngredientes!$A$5:$F$155,6,FALSE),"") | H25: =IFERROR(E25*F25,"")
B26: =IFERROR(VLOOKUP(A26,ListaIngredientes!$A$5:$F$155,2,FALSE),"") | D26: =IFERROR(VLOOKUP(A26,Tabela2[],3,FALSE),"") | F26: =IFERROR(VLOOKUP(A26,ListaIngredientes!$A$5:$F$155,6,FALSE),"") | H26: =IFERROR(E26*F26,"")
B27: =IFERROR(VLOOKUP(A27,ListaIngredientes!$A$5:$F$155,2,FALSE),"") | D27: =IFERROR(VLOOKUP(A27,Tabela2[],3,FALSE),"") | F27: =IFERROR(VLOOKUP(A27,ListaIngredientes!$A$5:$F$155,6,FALSE),"") | H27: =IFERROR(E27*F27,"")
F28: soma | H28: =IFERROR(E28*F28,"")
H29: =SUM(H8:H27) -> 28.027313

Sheet GRANOLA
A1: cod | B1: 501 | C1: =VLOOKUP(B1,PRODUTOS!$A$7:$E$204,2,FALSE) -> P A S T E L | E1: =C3 -> 115.63623 | G1: SOBREMESA/DOCE
A2: Despesas Fixas | C2: 0.2 | E2: Preço Venda Unit | G2: =IFERROR(C3/(1-C2-C5),"") -> 385.4541
A3: Custo Unitário | C3: =IFERROR(C6/C4,"") -> 115.63623 | E3: Luro s/Venda | G3: =G2*C5 -> 192.72705
A4: Quantidade Produzida | C4: 13 | E4: Preço Praticado | G4: 15
A5: Lucro s/Venda | C5: 0.5 | E5: Lucro Praticado | G5: =1-C3/G4-C2 -> -6.9090821
A6: Gasto Total | C6: =SUM(H8:H28) -> 1503.271 | E6: Lucro Praticado | G6: =G5*G4 -> -103.63623
A7: cod Prod | B7: Descrição ingredientes | D7: unid | E7: quantiadade | F7: valor $ | H7: Subtotal
A8: 101 | B8: =IFERROR(VLOOKUP(A8,ListaIngredientes!$A$5:$F$155,2,FALSE),"") | D8: =IFERROR(VLOOKUP(A8,Tabela2[],3,FALSE),"") | E8: 4 | F8: =IFERROR(VLOOKUP(A8,ListaIngredientes!$A$5:$F$155,6,FALSE),"") | H8: =IFERROR(E8*F8,"")
A9: 230 | B9: =IFERROR(VLOOKUP(A9,ListaIngredientes!$A$5:$F$155,2,FALSE),"") -> 0 | D9: =IFERROR(VLOOKUP(A9,Tabela2[],3,FALSE),"") -> u | E9: 50 | F9: =IFERROR(VLOOKUP(A9,ListaIngredientes!$A$5:$F$155,6,FALSE),"") -> 0.149 | H9: =IFERROR(E9*F9,"") -> 7.45
A10: 202 | B10: =IFERROR(VLOOKUP(A10,ListaIngredientes!$A$5:$F$155,2,FALSE),"") -> 0 | D10: =IFERROR(VLOOKUP(A10,Tabela2[],3,FALSE),"") -> 0 | E10: 30 | F10: =IFERROR(VLOOKUP(A10,ListaIngredientes!$A$5:$F$155,6,FALSE),"") -> 0 | H10: =IFERROR(E10*F10,"") -> 0
A11: 231 | B11: =IFERROR(VLOOKUP(A11,ListaIngredientes!$A$5:$F$155,2,FALSE),"") -> sacola papel branco | D11: =IFERROR(VLOOKUP(A11,Tabela2[],3,FALSE),"") -> u | E11: 50 | F11: =IFERROR(VLOOKUP(A11,ListaIngredientes!$A$5:$F$155,6,FALSE),"") -> 14.9 | H11: =IFERROR(E11*F11,"") -> 745
A12: 103 | B12: =IFERROR(VLOOKUP(A12,ListaIngredientes!$A$5:$F$155,2,FALSE),"") -> Leite condensado | D12: =IFERROR(VLOOKUP(A12,Tabela2[],3,FALSE),"") -> ml | E12: 75 | F12: =IFERROR(VLOOKUP(A12,ListaIngredientes!$A$5:$F$155,6,FALSE),"") -> 0.045 | H12: =IFERROR(E12*F12,"") -> 3.375
A13: 183 | B13: =IFERROR(VLOOKUP(A13,ListaIngredientes!$A$5:$F$155,2,FALSE),"") -> gelatina sem sabor | D13: =IFERROR(VLOOKUP(A13,Tabela2[],3,FALSE),"") -> u | E13: 125 | F13: =IFERROR(VLOOKUP(A13,ListaIngredientes!$A$5:$F$155,6,FALSE),"") -> 5.05 | H13: =IFERROR(E13*F13,"") -> 631.25
A14: 142 | B14: =IFERROR(VLOOKUP(A14,ListaIngredientes!$A$5:$F$155,2,FALSE),"") -> embalagem galvanatec g32 | D14: =IFERROR(VLOOKUP(A14,Tabela2[],3,FALSE),"") -> u | E14: 125 | F14: =IFERROR(VLOOKUP(A14,ListaIngredientes!$A$5:$F$155,6,FALSE),"") -> 0.09 | H14: =IFERROR(E14*F14,"") -> 11.25
A15: 203 | B15: =IFERROR(VLOOKUP(A15,ListaIngredientes!$A$5:$F$155,2,FALSE),"") -> 0 | D15: =IFERROR(VLOOKUP(A15,Tabela2[],3,FALSE),"") -> 0 | E15: 2 | F15: =IFERROR(VLOOKUP(A15,ListaIngredientes!$A$5:$F$155,6,FALSE),"") -> 0 | H15: =IFERROR(E15*F15,"") -> 0
A16: 136 | B16: =IFERROR(VLOOKUP(A16,ListaIngredientes!$A$5:$F$155,2,FALSE),"") -> embalagem retangular torta g630 | D16: =IFERROR(VLOOKUP(A16,Tabela2[],3,FALSE),"") -> u | E16: 100 | F16: =IFERROR(VLOOKUP(A16,ListaIngredientes!$A$5:$F$155,6,FALSE),"") -> 0.89 | H16: =IFERROR(E16*F16,"") -> 89
A17: 104 | B17: =IFERROR(VLOOKUP(A17,ListaIngredientes!$A$5:$F$155,2,FALSE),"") -> Leite Integral | D17: =IFERROR(VLOOKUP(A17,Tabela2[],3,FALSE),"") -> ml | E17: 140 | F17: =IFERROR(VLOOKUP(A17,ListaIngredientes!$A$5:$F$155,6,FALSE),"") -> 0.012 | H17: =IFERROR(E17*F17,"") -> 1.68
A18: 107 | B18: =IFERROR(VLOOKUP(A18,ListaIngredientes!$A$5:$F$155,2,FALSE),"") -> Agua mineral | D18: =IFERROR(VLOOKUP(A18,Tabela2[],3,FALSE),"") -> ml | E18: 140 | F18: =IFERROR(VLOOKUP(A18,ListaIngredientes!$A$5:$F$155,6,FALSE),"") -> 0.0469 | H18: =IFERROR(E18*F18,"") -> 6.566
A19: 108 | B19: =IFERROR(VLOOKUP(A19,ListaIngredientes!$A$5:$F$155,2,FALSE),"") -> CANELA | D19: =IFERROR(VLOOKUP(A19,Tabela2[],3,FALSE),"") -> KG | E19: 140 | F19: =IFERROR(VLOOKUP(A19,ListaIngredientes!$A$5:$F$155,6,FALSE),"") -> 0.055 | H19: =IFERROR(E19*F19,"") -> 7.7
A20: 180 | B20: =IFERROR(VLOOKUP(A20,ListaIngredientes!$A$5:$F$155,2,FALSE),"") -> GALVANATEC G742 | D20: =IFERROR(VLOOKUP(A20,Tabela2[],3,FALSE),"") -> U | E20: 35 | F20: =IFERROR(VLOOKUP(A20,ListaIngredientes!$A$5:$F$155,6,FALSE),"") | H20: =IFERROR(E20*F20,"")
B21: =IFERROR(VLOOKUP(A21,ListaIngredientes!$A$5:$F$155,2,FALSE),"") | D21: =IFERROR(VLOOKUP(A21,Tabela2[],3,FALSE),"") | F21: =IFERROR(VLOOKUP(A21,ListaIngredientes!$A$5:$F$155,6,FALSE),"") | H21: =IFERROR(E21*F21,"")
B22: =IFERROR(VLOOKUP(A22,ListaIngredientes!$A$5:$F$155,2,FALSE),"") | D22: =IFERROR(VLOOKUP(A22,Tabela2[],3,FALSE),"") | F22: =IFERROR(VLOOKUP(A22,ListaIngredientes!$A$5:$F$155,6,FALSE),"") | H22: =IFERROR(E22*F22,"")
B23: =IFERROR(VLOOKUP(A23,ListaIngredientes!$A$5:$F$155,2,FALSE),"") | D23: =IFERROR(VLOOKUP(A23,Tabela2[],3,FALSE),"") | F23: =IFERROR(VLOOKUP(A23,ListaIngredientes!$A$5:$F$155,6,FALSE),"") | H23: =IFERROR(E23*F23,"")
B24: =IFERROR(VLOOKUP(A24,ListaIngredientes!$A$5:$F$155,2,FALSE),"") | D24: =IFERROR(VLOOKUP(A24,Tabela2[],3,FALSE),"") | F24: =IFERROR(VLOOKUP(A24,ListaIngredientes!$A$5:$F$155,6,FALSE),"") | H24: =IFERROR(E24*F24,"")
B25: =IFERROR(VLOOKUP(A25,ListaIngredientes!$A$5:$F$155,2,FALSE),"") | D25: =IFERROR(VLOOKUP(A25,Tabela2[],3,FALSE),"") | F25: =IFERROR(VLOOKUP(A25,ListaIngredientes!$A$5:$F$155,6,FALSE),"") | H25: =IFERROR(E25*F25,"")
B26: =IFERROR(VLOOKUP(A26,ListaIngredientes!$A$5:$F$155,2,FALSE),"") | D26: =IFERROR(VLOOKUP(A26,Tabela2[],3,FALSE),"") | F26: =IFERROR(VLOOKUP(A26,ListaIngredientes!$A$5:$F$155,6,FALSE),"") | H26: =IFERROR(E26*F26,"")
B27: =IFERROR(VLOOKUP(A27,ListaIngredientes!$A$5:$F$155,2,FALSE),"") | D27: =IFERROR(VLOOKUP(A27,Tabela2[],3,FALSE),"") | F27: =IFERROR(VLOOKUP(A27,ListaIngredientes!$A$5:$F$155,6,FALSE),"") | H27: =IFERROR(E27*F27,"")
F28: soma | H28: =IFERROR(E28*F28,"")
H29: =SUM(H8:H27) -> 1503.271

Sheet TORTINHA DE FRANGO
A1: cod | B1: 501 | C1: =VLOOKUP(B1,PRODUTOS!$A$7:$E$204,2,FALSE) -> P A S T E L | E1: =C3 -> 5.6336513 | G1: SOBREMESA/DOCE
A2: Despesas Fixas | C2: 0.2 | E2: Preço Venda Unit | G2: =IFERROR(C3/(1-C2-C5),"") -> 18.778838
A3: Custo Unitário | C3: =IFERROR(C6/C4,"") -> 5.6336513 | E3: Luro s/Venda | G3: =G2*C5 -> 9.3894188
A4: Quantidade Produzida | C4: 13 | E4: Preço Praticado | G4: 15
A5: Lucro s/Venda | C5: 0.5 | E5: Lucro Praticado | G5: =1-C3/G4-C2 -> 0.42442325
A6: Gasto Total | C6: =SUM(H8:H28) -> 73.237467 | E6: Lucro Praticado | G6: =G5*G4 -> 6.3663487
A7: cod Prod | B7: Descrição ingredientes | D7: unid | E7: quantiadade | F7: valor $ | H7: Subtotal
A8: 101 | B8: =IFERROR(VLOOKUP(A8,ListaIngredientes!$A$5:$F$155,2,FALSE),"") | D8: =IFERROR(VLOOKUP(A8,Tabela2[],3,FALSE),"") | E8: 12 | F8: =IFERROR(VLOOKUP(A8,ListaIngredientes!$A$5:$F$155,6,FALSE),"") | H8: =IFERROR(E8*F8,"")
A9: 109 | B9: =IFERROR(VLOOKUP(A9,ListaIngredientes!$A$5:$F$155,2,FALSE),"") -> CASTANHA DO PARÁ | D9: =IFERROR(VLOOKUP(A9,Tabela2[],3,FALSE),"") -> KG | E9: 15 | F9: =IFERROR(VLOOKUP(A9,ListaIngredientes!$A$5:$F$155,6,FALSE),"") -> 0.035 | H9: =IFERROR(E9*F9,"") -> 0.525
A10: 203 | B10: =IFERROR(VLOOKUP(A10,ListaIngredientes!$A$5:$F$155,2,FALSE),"") -> 0 | D10: =IFERROR(VLOOKUP(A10,Tabela2[],3,FALSE),"") -> 0 | E10: 8 | F10: =IFERROR(VLOOKUP(A10,ListaIngredientes!$A$5:$F$155,6,FALSE),"") -> 0 | H10: =IFERROR(E10*F10,"") -> 0
A11: 158 | B11: =IFERROR(VLOOKUP(A11,ListaIngredientes!$A$5:$F$155,2,FALSE),"") -> ESSENCIA DE BAUNILHA | D11: =IFERROR(VLOOKUP(A11,Tabela2[],3,FALSE),"") -> ML | E11: 260 | F11: =IFERROR(VLOOKUP(A11,ListaIngredientes!$A$5:$F$155,6,FALSE),"") -> 0.099666667 | H11: =IFERROR(E11*F11,"") -> 25.913333
A12: 163 | B12: =IFERROR(VLOOKUP(A12,ListaIngredientes!$A$5:$F$155,2,FALSE),"") -> fermento biologico | D12: =IFERROR(VLOOKUP(A12,Tabela2[],3,FALSE),"") -> kg | E12: 15 | F12: =IFERROR(VLOOKUP(A12,ListaIngredientes!$A$5:$F$155,6,FALSE),"") -> 0.05512 | H12: =IFERROR(E12*F12,"") -> 0.8268
A13: 232 | B13: =IFERROR(VLOOKUP(A13,ListaIngredientes!$A$5:$F$155,2,FALSE),"") -> xilitol | D13: =IFERROR(VLOOKUP(A13,Tabela2[],3,FALSE),"") -> kg | E13: 50 | F13: =IFERROR(VLOOKUP(A13,ListaIngredientes!$A$5:$F$155,6,FALSE),"") -> 0.03652 | H13: =IFERROR(E13*F13,"") -> 1.826
A14: 162 | B14: =IFERROR(VLOOKUP(A14,ListaIngredientes!$A$5:$F$155,2,FALSE),"") -> farinha de linhaça dourada | D14: =IFERROR(VLOOKUP(A14,Tabela2[],3,FALSE),"") -> kg | E14: 240 | F14: =IFERROR(VLOOKUP(A14,ListaIngredientes!$A$5:$F$155,6,FALSE),"") -> 0.02499 | H14: =IFERROR(E14*F14,"") -> 5.9976
A15: 219 | B15: =IFERROR(VLOOKUP(A15,ListaIngredientes!$A$5:$F$155,2,FALSE),"") -> Queijo Minas | D15: =IFERROR(VLOOKUP(A15,Tabela2[],3,FALSE),"") -> g | E15: 100 | F15: =IFERROR(VLOOKUP(A15,ListaIngredientes!$A$5:$F$155,6,FALSE),"") -> 0.0153 | H15: =IFERROR(E15*F15,"") -> 1.53
A16: 143 | B16: =IFERROR(VLOOKUP(A16,ListaIngredientes!$A$5:$F$155,2,FALSE),"") -> 0 | D16: =IFERROR(VLOOKUP(A16,Tabela2[],3,FALSE),"") -> 0 | E16: 12 | F16: =IFERROR(VLOOKUP(A16,ListaIngredientes!$A$5:$F$155,6,FALSE),"") -> 0 | H16: =IFERROR(E16*F16,"") -> 0
B17: =IFERROR(VLOOKUP(A17,ListaIngredientes!$A$5:$F$155,2,FALSE),"") | D17: =IFERROR(VLOOKUP(A17,Tabela2[],3,FALSE),"") | F17: =IFERROR(VLOOKUP(A17,ListaIngredientes!$A$5:$F$155,6,FALSE),"") | H17: =IFERROR(E17*F17,"")
B18: =IFERROR(VLOOKUP(A18,ListaIngredientes!$A$5:$F$155,2,FALSE),"") | D18: =IFERROR(VLOOKUP(A18,Tabela2[],3,FALSE),"") | F18: =IFERROR(VLOOKUP(A18,ListaIngredientes!$A$5:$F$155,6,FALSE),"") | H18: =IFERROR(E18*F18,"")
B19: =IFERROR(VLOOKUP(A19,ListaIngredientes!$A$5:$F$155,2,FALSE),"") | D19: =IFERROR(VLOOKUP(A19,Tabela2[],3,FALSE),"") | F19: =IFERROR(VLOOKUP(A19,ListaIngredientes!$A$5:$F$155,6,FALSE),"") | H19: =IFERROR(E19*F19,"")
B20: =IFERROR(VLOOKUP(A20,ListaIngredientes!$A$5:$F$155,2,FALSE),"") | D20: =IFERROR(VLOOKUP(A20,Tabela2[],3,FALSE),"") | F20: =IFERROR(VLOOKUP(A20,ListaIngredientes!$A$5:$F$155,6,FALSE),"") | H20: =IFERROR(E20*F20,"")
B21: =IFERROR(VLOOKUP(A21,ListaIngredientes!$A$5:$F$155,2,FALSE),"") | D21: =IFERROR(VLOOKUP(A21,Tabela2[],3,FALSE),"") | F21: =IFERROR(VLOOKUP(A21,ListaIngredientes!$A$5:$F$155,6,FALSE),"") | H21: =IFERROR(E21*F21,"")
B22: =IFERROR(VLOOKUP(A22,ListaIngredientes!$A$5:$F$155,2,FALSE),"") | D22: =IFERROR(VLOOKUP(A22,Tabela2[],3,FALSE),"") | F22: =IFERROR(VLOOKUP(A22,ListaIngredientes!$A$5:$F$155,6,FALSE),"") | H22: =IFERROR(E22*F22,"")
B23: =IFERROR(VLOOKUP(A23,ListaIngredientes!$A$5:$F$155,2,FALSE),"") | D23: =IFERROR(VLOOKUP(A23,Tabela2[],3,FALSE),"") | F23: =IFERROR(VLOOKUP(A23,ListaIngredientes!$A$5:$F$155,6,FALSE),"") | H23: =IFERROR(E23*F23,"")
B24: =IFERROR(VLOOKUP(A24,ListaIngredientes!$A$5:$F$155,2,FALSE),"") | D24: =IFERROR(VLOOKUP(A24,Tabela2[],3,FALSE),"") | F24: =IFERROR(VLOOKUP(A24,ListaIngredientes!$A$5:$F$155,6,FALSE),"") | H24: =IFERROR(E24*F24,"")
B25: =IFERROR(VLOOKUP(A25,ListaIngredientes!$A$5:$F$155,2,FALSE),"") | D25: =IFERROR(VLOOKUP(A25,Tabela2[],3,FALSE),"") | F25: =IFERROR(VLOOKUP(A25,ListaIngredientes!$A$5:$F$155,6,FALSE),"") | H25: =IFERROR(E25*F25,"")
B26: =IFERROR(VLOOKUP(A26,ListaIngredientes!$A$5:$F$155,2,FALSE),"") | D26: =IFERROR(VLOOKUP(A26,Tabela2[],3,FALSE),"") | F26: =IFERROR(VLOOKUP(A26,ListaIngredientes!$A$5:$F$155,6,FALSE),"") | H26: =IFERROR(E26*F26,"")
F27: soma | H27: =IFERROR(E27*F27,"")
H28: =SUM(H8:H27) -> 36.618733

Sheet TORTINHA DE CAMARÃO
A1: cod | B1: 501 | C1: =VLOOKUP(B1,PRODUTOS!$A$7:$E$204,2,FALSE) -> P A S T E L | E1: =C3 -> 5.0801744 | G1: SOBREMESA/DOCE
A2: Despesas Fixas | C2: 0.2 | E2: Preço Venda Unit | G2: =IFERROR(C3/(1-C2-C5),"") -> 16.933915
A3: Custo Unitário | C3: =IFERROR(C6/C4,"") -> 5.0801744 | E3: Luro s/Venda | G3: =G2*C5 -> 8.4669573
A4: Quantidade Produzida | C4: 13 | E4: Preço Praticado | G4: 15
A5: Lucro s/Venda | C5: 0.5 | E5: Lucro Praticado | G5: =1-C3/G4-C2 -> 0.46132171
A6: Gasto Total | C6: =SUM(H8:H28) -> 66.042267 | E6: Lucro Praticado | G6: =G5*G4 -> 6.9198256
A7: cod Prod | B7: Descrição ingredientes | D7: unid | E7: quantiadade | F7: valor $ | H7: Subtotal
A8: 101 | B8: =IFERROR(VLOOKUP(A8,ListaIngredientes!$A$5:$F$155,2,FALSE),"") | D8: =IFERROR(VLOOKUP(A8,Tabela2[],3,FALSE),"") | E8: 12 | F8: =IFERROR(VLOOKUP(A8,ListaIngredientes!$A$5:$F$155,6,FALSE),"") | H8: =IFERROR(E8*F8,"")
A9: 109 | B9: =IFERROR(VLOOKUP(A9,ListaIngredientes!$A$5:$F$155,2,FALSE),"") -> CASTANHA DO PARÁ | D9: =IFERROR(VLOOKUP(A9,Tabela2[],3,FALSE),"") -> KG | E9: 15 | F9: =IFERROR(VLOOKUP(A9,ListaIngredientes!$A$5:$F$155,6,FALSE),"") -> 0.035 | H9: =IFERROR(E9*F9,"") -> 0.525
A10: 203 | B10: =IFERROR(VLOOKUP(A10,ListaIngredientes!$A$5:$F$155,2,FALSE),"") -> 0 | D10: =IFERROR(VLOOKUP(A10,Tabela2[],3,FALSE),"") -> 0 | E10: 8 | F10: =IFERROR(VLOOKUP(A10,ListaIngredientes!$A$5:$F$155,6,FALSE),"") -> 0 | H10: =IFERROR(E10*F10,"") -> 0
A11: 158 | B11: =IFERROR(VLOOKUP(A11,ListaIngredientes!$A$5:$F$155,2,FALSE),"") -> ESSENCIA DE BAUNILHA | D11: =IFERROR(VLOOKUP(A11,Tabela2[],3,FALSE),"") -> ML | E11: 260 | F11: =IFERROR(VLOOKUP(A11,ListaIngredientes!$A$5:$F$155,6,FALSE),"") -> 0.099666667 | H11: =IFERROR(E11*F11,"") -> 25.913333
A12: 163 | B12: =IFERROR(VLOOKUP(A12,ListaIngredientes!$A$5:$F$155,2,FALSE),"") -> fermento biologico | D12: =IFERROR(VLOOKUP(A12,Tabela2[],3,FALSE),"") -> kg | E12: 15 | F12: =IFERROR(VLOOKUP(A12,ListaIngredientes!$A$5:$F$155,6,FALSE),"") -> 0.05512 | H12: =IFERROR(E12*F12,"") -> 0.8268
A13: 232 | B13: =IFERROR(VLOOKUP(A13,ListaIngredientes!$A$5:$F$155,2,FALSE),"") -> xilitol | D13: =IFERROR(VLOOKUP(A13,Tabela2[],3,FALSE),"") -> kg | E13: 50 | F13: =IFERROR(VLOOKUP(A13,ListaIngredientes!$A$5:$F$155,6,FALSE),"") -> 0.03652 | H13: =IFERROR(E13*F13,"") -> 1.826
A14: 113 | B14: =IFERROR(VLOOKUP(A14,ListaIngredientes!$A$5:$F$155,2,FALSE),"") -> polvilho doce | D14: =IFERROR(VLOOKUP(A14,Tabela2[],3,FALSE),"") -> kg | E14: 240 | F14: =IFERROR(VLOOKUP(A14,ListaIngredientes!$A$5:$F$155,6,FALSE),"") -> 0.01 | H14: =IFERROR(E14*F14,"") -> 2.4
A15: 219 | B15: =IFERROR(VLOOKUP(A15,ListaIngredientes!$A$5:$F$155,2,FALSE),"") -> Queijo Minas | D15: =IFERROR(VLOOKUP(A15,Tabela2[],3,FALSE),"") -> g | E15: 100 | F15: =IFERROR(VLOOKUP(A15,ListaIngredientes!$A$5:$F$155,6,FALSE),"") -> 0.0153 | H15: =IFERROR(E15*F15,"") -> 1.53
A16: 143 | B16: =IFERROR(VLOOKUP(A16,ListaIngredientes!$A$5:$F$155,2,FALSE),"") -> 0 | D16: =IFERROR(VLOOKUP(A16,Tabela2[],3,FALSE),"") -> 0 | E16: 12 | F16: =IFERROR(VLOOKUP(A16,ListaIngredientes!$A$5:$F$155,6,FALSE),"") -> 0 | H16: =IFERROR(E16*F16,"") -> 0
B17: =IFERROR(VLOOKUP(A17,ListaIngredientes!$A$5:$F$155,2,FALSE),"") | D17: =IFERROR(VLOOKUP(A17,Tabela2[],3,FALSE),"") | F17: =IFERROR(VLOOKUP(A17,ListaIngredientes!$A$5:$F$155,6,FALSE),"") | H17: =IFERROR(E17*F17,"")
B18: =IFERROR(VLOOKUP(A18,ListaIngredientes!$A$5:$F$155,2,FALSE),"") | D18: =IFERROR(VLOOKUP(A18,Tabela2[],3,FALSE),"") | F18: =IFERROR(VLOOKUP(A18,ListaIngredientes!$A$5:$F$155,6,FALSE),"") | H18: =IFERROR(E18*F18,"")
B19: =IFERROR(VLOOKUP(A19,ListaIngredientes!$A$5:$F$155,2,FALSE),"") | D19: =IFERROR(VLOOKUP(A19,Tabela2[],3,FALSE),"") | F19: =IFERROR(VLOOKUP(A19,ListaIngredientes!$A$5:$F$155,6,FALSE),"") | H19: =IFERROR(E19*F19,"")
B20: =IFERROR(VLOOKUP(A20,ListaIngredientes!$A$5:$F$155,2,FALSE),"") | D20: =IFERROR(VLOOKUP(A20,Tabela2[],3,FALSE),"") | F20: =IFERROR(VLOOKUP(A20,ListaIngredientes!$A$5:$F$155,6,FALSE),"") | H20: =IFERROR(E20*F20,"")
B21: =IFERROR(VLOOKUP(A21,ListaIngredientes!$A$5:$F$155,2,FALSE),"") | D21: =IFERROR(VLOOKUP(A21,Tabela2[],3,FALSE),"") | F21: =IFERROR(VLOOKUP(A21,ListaIngredientes!$A$5:$F$155,6,FALSE),"") | H21: =IFERROR(E21*F21,"")
B22: =IFERROR(VLOOKUP(A22,ListaIngredientes!$A$5:$F$155,2,FALSE),"") | D22: =IFERROR(VLOOKUP(A22,Tabela2[],3,FALSE),"") | F22: =IFERROR(VLOOKUP(A22,ListaIngredientes!$A$5:$F$155,6,FALSE),"") | H22: =IFERROR(E22*F22,"")
B23: =IFERROR(VLOOKUP(A23,ListaIngredientes!$A$5:$F$155,2,FALSE),"") | D23: =IFERROR(VLOOKUP(A23,Tabela2[],3,FALSE),"") | F23: =IFERROR(VLOOKUP(A23,ListaIngredientes!$A$5:$F$155,6,FALSE),"") | H23: =IFERROR(E23*F23,"")
B24: =IFERROR(VLOOKUP(A24,ListaIngredientes!$A$5:$F$155,2,FALSE),"") | D24: =IFERROR(VLOOKUP(A24,Tabela2[],3,FALSE),"") | F24: =IFERROR(VLOOKUP(A24,ListaIngredientes!$A$5:$F$155,6,FALSE),"") | H24: =IFERROR(E24*F24,"")
B25: =IFERROR(VLOOKUP(A25,ListaIngredientes!$A$5:$F$155,2,FALSE),"") | D25: =IFERROR(VLOOKUP(A25,Tabela2[],3,FALSE),"") | F25: =IFERROR(VLOOKUP(A25,ListaIngredientes!$A$5:$F$155,6,FALSE),"") | H25: =IFERROR(E25*F25,"")
B26: =IFERROR(VLOOKUP(A26,ListaIngredientes!$A$5:$F$155,2,FALSE),"") | D26: =IFERROR(VLOOKUP(A26,Tabela2[],3,FALSE),"") | F26: =IFERROR(VLOOKUP(A26,ListaIngredientes!$A$5:$F$155,6,FALSE),"") | H26: =IFERROR(E26*F26,"")
F27: soma | H27: =IFERROR(E27*F27,"")
H28: =SUM(H8:H27) -> 33.021133

Sheet BOLO DE PRESTIGIO
A1: cod | B1: 501 | C1: =VLOOKUP(B1,PRODUTOS!$A$7:$E$204,2,FALSE) -> P A S T E L | E1: =C3 -> 28.226138 | G1: SOBREMESA/DOCE
A2: Despesas Fixas | C2: 0.2 | E2: Preço Venda Unit | G2: =IFERROR(C3/(1-C2-C5),"") -> 94.087128
A3: Custo Unitário | C3: =IFERROR(C6/C4,"") -> 28.226138 | E3: Luro s/Venda | G3: =G2*C5 -> 47.043564
A4: Quantidade Produzida | C4: 13 | E4: Preço Praticado | G4: 15
A5: Lucro s/Venda | C5: 0.5 | E5: Lucro Praticado | G5: =1-C3/G4-C2 -> -1.0817426
A6: Gasto Total | C6: =SUM(H8:H28) -> 366.9398 | E6: Lucro Praticado | G6: =G5*G4 -> -16.226138
A7: cod Prod | B7: Descrição ingredientes | D7: unid | E7: quantiadade | F7: valor $ | H7: Subtotal
A8: 101 | B8: =IFERROR(VLOOKUP(A8,ListaIngredientes!$A$5:$F$155,2,FALSE),"") | D8: =IFERROR(VLOOKUP(A8,Tabela2[],3,FALSE),"") | E8: 2 | F8: =IFERROR(VLOOKUP(A8,ListaIngredientes!$A$5:$F$155,6,FALSE),"") | H8: =IFERROR(E8*F8,"")
A9: 105 | B9: =IFERROR(VLOOKUP(A9,ListaIngredientes!$A$5:$F$155,2,FALSE),"") -> Bananas | D9: =IFERROR(VLOOKUP(A9,Tabela2[],3,FALSE),"") -> duzias | E9: 20 | F9: =IFERROR(VLOOKUP(A9,ListaIngredientes!$A$5:$F$155,6,FALSE),"") -> 0.5 | H9: =IFERROR(E9*F9,"") -> 10
A10: 202 | B10: =IFERROR(VLOOKUP(A10,ListaIngredientes!$A$5:$F$155,2,FALSE),"") -> 0 | D10: =IFERROR(VLOOKUP(A10,Tabela2[],3,FALSE),"") -> 0 | E10: 100 | F10: =IFERROR(VLOOKUP(A10,ListaIngredientes!$A$5:$F$155,6,FALSE),"") -> 0 | H10: =IFERROR(E10*F10,"") -> 0
A11: 230 | B11: =IFERROR(VLOOKUP(A11,ListaIngredientes!$A$5:$F$155,2,FALSE),"") -> 0 | D11: =IFERROR(VLOOKUP(A11,Tabela2[],3,FALSE),"") -> u | E11: 85 | F11: =IFERROR(VLOOKUP(A11,ListaIngredientes!$A$5:$F$155,6,FALSE),"") -> 0.149 | H11: =IFERROR(E11*F11,"") -> 12.665
A12: 163 | B12: =IFERROR(VLOOKUP(A12,ListaIngredientes!$A$5:$F$155,2,FALSE),"") -> fermento biologico | D12: =IFERROR(VLOOKUP(A12,Tabela2[],3,FALSE),"") -> kg | E12: 15 | F12: =IFERROR(VLOOKUP(A12,ListaIngredientes!$A$5:$F$155,6,FALSE),"") -> 0.05512 | H12: =IFERROR(E12*F12,"") -> 0.8268
A13: 243 | B13: =IFERROR(VLOOKUP(A13,ListaIngredientes!$A$5:$F$155,2,FALSE),"") -> Tomate | D13: =IFERROR(VLOOKUP(A13,Tabela2[],3,FALSE),"") -> KG | E13: 2 | F13: =IFERROR(VLOOKUP(A13,ListaIngredientes!$A$5:$F$155,6,FALSE),"") -> 0.004 | H13: =IFERROR(E13*F13,"") -> 0.008
A14: 188 | B14: =IFERROR(VLOOKUP(A14,ListaIngredientes!$A$5:$F$155,2,FALSE),"") -> LATA PALHA ITALIANA | D14: =IFERROR(VLOOKUP(A14,Tabela2[],3,FALSE),"") -> U | E14: 200 | F14: =IFERROR(VLOOKUP(A14,ListaIngredientes!$A$5:$F$155,6,FALSE),"") -> 1.59 | H14: =IFERROR(E14*F14,"") -> 318
A15: 203 | B15: =IFERROR(VLOOKUP(A15,ListaIngredientes!$A$5:$F$155,2,FALSE),"") -> 0 | D15: =IFERROR(VLOOKUP(A15,Tabela2[],3,FALSE),"") -> 0 | E15: 4 | F15: =IFERROR(VLOOKUP(A15,ListaIngredientes!$A$5:$F$155,6,FALSE),"") -> 0 | H15: =IFERROR(E15*F15,"") -> 0
B16: =IFERROR(VLOOKUP(A16,ListaIngredientes!$A$5:$F$155,2,FALSE),"") | D16: =IFERROR(VLOOKUP(A16,Tabela2[],3,FALSE),"") | F16: =IFERROR(VLOOKUP(A16,ListaIngredientes!$A$5:$F$155,6,FALSE),"") | H16: =IFERROR(E16*F16,"")
A17: 126 | B17: =IFERROR(VLOOKUP(A17,ListaIngredientes!$A$5:$F$155,2,FALSE),"") -> CHOCOLTE BRANCO | D17: =IFERROR(VLOOKUP(A17,Tabela2[],3,FALSE),"") -> KG | E17: 160 | F17: =IFERROR(VLOOKUP(A17,ListaIngredientes!$A$5:$F$155,6,FALSE),"") -> 0.159 | H17: =IFERROR(E17*F17,"") -> 25.44
B18: =IFERROR(VLOOKUP(A18,ListaIngredientes!$A$5:$F$155,2,FALSE),"") | D18: =IFERROR(VLOOKUP(A18,Tabela2[],3,FALSE),"") | F18: =IFERROR(VLOOKUP(A18,ListaIngredientes!$A$5:$F$155,6,FALSE),"") | H18: =IFERROR(E18*F18,"")
B19: =IFERROR(VLOOKUP(A19,ListaIngredientes!$A$5:$F$155,2,FALSE),"") | D19: =IFERROR(VLOOKUP(A19,Tabela2[],3,FALSE),"") | F19: =IFERROR(VLOOKUP(A19,ListaIngredientes!$A$5:$F$155,6,FALSE),"") | H19: =IFERROR(E19*F19,"")
B20: =IFERROR(VLOOKUP(A20,ListaIngredientes!$A$5:$F$155,2,FALSE),"") | D20: =IFERROR(VLOOKUP(A20,Tabela2[],3,FALSE),"") | F20: =IFERROR(VLOOKUP(A20,ListaIngredientes!$A$5:$F$155,6,FALSE),"") | H20: =IFERROR(E20*F20,"")
B21: =IFERROR(VLOOKUP(A21,ListaIngredientes!$A$5:$F$155,2,FALSE),"") | D21: =IFERROR(VLOOKUP(A21,Tabela2[],3,FALSE),"") | F21: =IFERROR(VLOOKUP(A21,ListaIngredientes!$A$5:$F$155,6,FALSE),"") | H21: =IFERROR(E21*F21,"")
B22: =IFERROR(VLOOKUP(A22,ListaIngredientes!$A$5:$F$155,2,FALSE),"") | D22: =IFERROR(VLOOKUP(A22,Tabela2[],3,FALSE),"") | F22: =IFERROR(VLOOKUP(A22,ListaIngredientes!$A$5:$F$155,6,FALSE),"") | H22: =IFERROR(E22*F22,"")
B23: =IFERROR(VLOOKUP(A23,ListaIngredientes!$A$5:$F$155,2,FALSE),"") | D23: =IFERROR(VLOOKUP(A23,Tabela2[],3,FALSE),"") | F23: =IFERROR(VLOOKUP(A23,ListaIngredientes!$A$5:$F$155,6,FALSE),"") | H23: =IFERROR(E23*F23,"")
B24: =IFERROR(VLOOKUP(A24,ListaIngredientes!$A$5:$F$155,2,FALSE),"") | D24: =IFERROR(VLOOKUP(A24,Tabela2[],3,FALSE),"") | F24: =IFERROR(VLOOKUP(A24,ListaIngredientes!$A$5:$F$155,6,FALSE),"") | H24: =IFERROR(E24*F24,"")
B25: =IFERROR(VLOOKUP(A25,ListaIngredientes!$A$5:$F$155,2,FALSE),"") | D25: =IFERROR(VLOOKUP(A25,Tabela2[],3,FALSE),"") | F25: =IFERROR(VLOOKUP(A25,ListaIngredientes!$A$5:$F$155,6,FALSE),"") | H25: =IFERROR(E25*F25,"")
B26: =IFERROR(VLOOKUP(A26,ListaIngredientes!$A$5:$F$155,2,FALSE),"") | D26: =IFERROR(VLOOKUP(A26,Tabela2[],3,FALSE),"") | F26: =IFERROR(VLOOKUP(A26,ListaIngredientes!$A$5:$F$155,6,FALSE),"") | H26: =IFERROR(E26*F26,"")
B27: =IFERROR(VLOOKUP(A27,ListaIngredientes!$A$5:$F$155,2,FALSE),"") | D27: =IFERROR(VLOOKUP(A27,Tabela2[],3,FALSE),"") | F27: =IFERROR(VLOOKUP(A27,ListaIngredientes!$A$5:$F$155,6,FALSE),"") | H27: =IFERROR(E27*F27,"")
F28: soma | H28: =IFERROR(E28*F28,"")
H29: =SUM(H8:H27) -> 366.9398

Sheet TORTA SONHO DE VALSA
A1: cod | B1: 501 | C1: =VLOOKUP(B1,PRODUTOS!$A$7:$E$204,2,FALSE) -> P A S T E L | E1: =C3 -> 34.108108 | G1: SOBREMESA/DOCE
A2: Despesas Fixas | C2: 0.2 | E2: Preço Venda Unit | G2: =IFERROR(C3/(1-C2-C5),"") -> 113.69369
A3: Custo Unitário | C3: =IFERROR(C6/C4,"") -> 34.108108 | E3: Luro s/Venda | G3: =G2*C5 -> 56.846847
A4: Quantidade Produzida | C4: 13 | E4: Preço Praticado | G4: 15
A5: Lucro s/Venda | C5: 0.5 | E5: Lucro Praticado | G5: =1-C3/G4-C2 -> -1.4738739
A6: Gasto Total | C6: =SUM(H8:H28) -> 443.40541 | E6: Lucro Praticado | G6: =G5*G4 -> -22.108108
A7: cod Prod | B7: Descrição ingredientes | D7: unid | E7: quantiadade | F7: valor $ | H7: Subtotal
A8: 203 | B8: =IFERROR(VLOOKUP(A8,ListaIngredientes!$A$5:$F$155,2,FALSE),"") -> 0 | D8: =IFERROR(VLOOKUP(A8,Tabela2[],3,FALSE),"") -> 0 | E8: 4 | F8: =IFERROR(VLOOKUP(A8,ListaIngredientes!$A$5:$F$155,6,FALSE),"") -> 0 | H8: =IFERROR(E8*F8,"") -> 0
A9: 230 | B9: =IFERROR(VLOOKUP(A9,ListaIngredientes!$A$5:$F$155,2,FALSE),"") -> 0 | D9: =IFERROR(VLOOKUP(A9,Tabela2[],3,FALSE),"") -> u | E9: 110 | F9: =IFERROR(VLOOKUP(A9,ListaIngredientes!$A$5:$F$155,6,FALSE),"") -> 0.149 | H9: =IFERROR(E9*F9,"") -> 16.39
A10: 188 | B10: =IFERROR(VLOOKUP(A10,ListaIngredientes!$A$5:$F$155,2,FALSE),"") -> LATA PALHA ITALIANA | D10: =IFERROR(VLOOKUP(A10,Tabela2[],3,FALSE),"") -> U | E10: 200 | F10: =IFERROR(VLOOKUP(A10,ListaIngredientes!$A$5:$F$155,6,FALSE),"") -> 1.59 | H10: =IFERROR(E10*F10,"") -> 318
A11: 105 | B11: =IFERROR(VLOOKUP(A11,ListaIngredientes!$A$5:$F$155,2,FALSE),"") -> Bananas | D11: =IFERROR(VLOOKUP(A11,Tabela2[],3,FALSE),"") -> duzias | E11: 20 | F11: =IFERROR(VLOOKUP(A11,ListaIngredientes!$A$5:$F$155,6,FALSE),"") -> 0.5 | H11: =IFERROR(E11*F11,"") -> 10
A12: 182 | B12: =IFERROR(VLOOKUP(A12,ListaIngredientes!$A$5:$F$155,2,FALSE),"") -> GERGILIM | D12: =IFERROR(VLOOKUP(A12,Tabela2[],3,FALSE),"") -> KG | E12: 1 | F12: =IFERROR(VLOOKUP(A12,ListaIngredientes!$A$5:$F$155,6,FALSE),"") -> 0.029 | H12: =IFERROR(E12*F12,"") -> 0.029
A13: 158 | B13: =IFERROR(VLOOKUP(A13,ListaIngredientes!$A$5:$F$155,2,FALSE),"") -> ESSENCIA DE BAUNILHA | D13: =IFERROR(VLOOKUP(A13,Tabela2[],3,FALSE),"") -> ML | E13: 130 | F13: =IFERROR(VLOOKUP(A13,ListaIngredientes!$A$5:$F$155,6,FALSE),"") -> 0.099666667 | H13: =IFERROR(E13*F13,"") -> 12.956667
A14: 163 | B14: =IFERROR(VLOOKUP(A14,ListaIngredientes!$A$5:$F$155,2,FALSE),"") -> fermento biologico | D14: =IFERROR(VLOOKUP(A14,Tabela2[],3,FALSE),"") -> kg | E14: 15 | F14: =IFERROR(VLOOKUP(A14,ListaIngredientes!$A$5:$F$155,6,FALSE),"") -> 0.05512 | H14: =IFERROR(E14*F14,"") -> 0.8268
A15: 159 | B15: =IFERROR(VLOOKUP(A15,ListaIngredientes!$A$5:$F$155,2,FALSE),"") -> essencia de mel | D15: =IFERROR(VLOOKUP(A15,Tabela2[],3,FALSE),"") -> u | E15: 30 | F15: =IFERROR(VLOOKUP(A15,ListaIngredientes!$A$5:$F$155,6,FALSE),"") -> 2.59 | H15: =IFERROR(E15*F15,"") -> 77.7
A16: 139 | B16: =IFERROR(VLOOKUP(A16,ListaIngredientes!$A$5:$F$155,2,FALSE),"") -> cravo da india | D16: =IFERROR(VLOOKUP(A16,Tabela2[],3,FALSE),"") -> g | E16: 600 | F16: =IFERROR(VLOOKUP(A16,ListaIngredientes!$A$5:$F$155,6,FALSE),"") -> 0.00058823529 | H16: =IFERROR(E16*F16,"") -> 0.35294118
A17: 125 | B17: =IFERROR(VLOOKUP(A17,ListaIngredientes!$A$5:$F$155,2,FALSE),"") -> 0 | D17: =IFERROR(VLOOKUP(A17,Tabela2[],3,FALSE),"") -> 0 | E17: 150 | F17: =IFERROR(VLOOKUP(A17,ListaIngredientes!$A$5:$F$155,6,FALSE),"") -> 0 | H17: =IFERROR(E17*F17,"") -> 0
A18: 108 | B18: =IFERROR(VLOOKUP(A18,ListaIngredientes!$A$5:$F$155,2,FALSE),"") -> CANELA | D18: =IFERROR(VLOOKUP(A18,Tabela2[],3,FALSE),"") -> KG | E18: 130 | F18: =IFERROR(VLOOKUP(A18,ListaIngredientes!$A$5:$F$155,6,FALSE),"") -> 0.055 | H18: =IFERROR(E18*F18,"") -> 7.15
A19: 131 | B19: =IFERROR(VLOOKUP(A19,ListaIngredientes!$A$5:$F$155,2,FALSE),"") -> 0 | D19: =IFERROR(VLOOKUP(A19,Tabela2[],3,FALSE),"") -> 0 | E19: 1 | F19: =IFERROR(VLOOKUP(A19,ListaIngredientes!$A$5:$F$155,6,FALSE),"") -> 0 | H19: =IFERROR(E19*F19,"") -> 0
B20: =IFERROR(VLOOKUP(A20,ListaIngredientes!$A$5:$F$155,2,FALSE),"") | D20: =IFERROR(VLOOKUP(A20,Tabela2[],3,FALSE),"") | F20: =IFERROR(VLOOKUP(A20,ListaIngredientes!$A$5:$F$155,6,FALSE),"") | H20: =IFERROR(E20*F20,"")
B21: =IFERROR(VLOOKUP(A21,ListaIngredientes!$A$5:$F$155,2,FALSE),"") | D21: =IFERROR(VLOOKUP(A21,Tabela2[],3,FALSE),"") | F21: =IFERROR(VLOOKUP(A21,ListaIngredientes!$A$5:$F$155,6,FALSE),"") | H21: =IFERROR(E21*F21,"")
B22: =IFERROR(VLOOKUP(A22,ListaIngredientes!$A$5:$F$155,2,FALSE),"") | D22: =IFERROR(VLOOKUP(A22,Tabela2[],3,FALSE),"") | F22: =IFERROR(VLOOKUP(A22,ListaIngredientes!$A$5:$F$155,6,FALSE),"") | H22: =IFERROR(E22*F22,"")
B23: =IFERROR(VLOOKUP(A23,ListaIngredientes!$A$5:$F$155,2,FALSE),"") | D23: =IFERROR(VLOOKUP(A23,Tabela2[],3,FALSE),"") | F23: =IFERROR(VLOOKUP(A23,ListaIngredientes!$A$5:$F$155,6,FALSE),"") | H23: =IFERROR(E23*F23,"")
B24: =IFERROR(VLOOKUP(A24,ListaIngredientes!$A$5:$F$155,2,FALSE),"") | D24: =IFERROR(VLOOKUP(A24,Tabela2[],3,FALSE),"") | F24: =IFERROR(VLOOKUP(A24,ListaIngredientes!$A$5:$F$155,6,FALSE),"") | H24: =IFERROR(E24*F24,"")
B25: =IFERROR(VLOOKUP(A25,ListaIngredientes!$A$5:$F$155,2,FALSE),"") | D25: =IFERROR(VLOOKUP(A25,Tabela2[],3,FALSE),"") | F25: =IFERROR(VLOOKUP(A25,ListaIngredientes!$A$5:$F$155,6,FALSE),"") | H25: =IFERROR(E25*F25,"")
B26: =IFERROR(VLOOKUP(A26,ListaIngredientes!$A$5:$F$155,2,FALSE),"") | D26: =IFERROR(VLOOKUP(A26,Tabela2[],3,FALSE),"") | F26: =IFERROR(VLOOKUP(A26,ListaIngredientes!$A$5:$F$155,6,FALSE),"") | H26: =IFERROR(E26*F26,"")
B27: =IFERROR(VLOOKUP(A27,ListaIngredientes!$A$5:$F$155,2,FALSE),"") | D27: =IFERROR(VLOOKUP(A27,Tabela2[],3,FALSE),"") | F27: =IFERROR(VLOOKUP(A27,ListaIngredientes!$A$5:$F$155,6,FALSE),"") | H27: =IFERROR(E27*F27,"")
F28: soma

Sheet NAKED P
A1: cod | B1: 501 | C1: =VLOOKUP(B1,PRODUTOS!$A$7:$E$204,2,FALSE) -> P A S T E L | E1: =C3 -> 32.450185 | G1: SOBREMESA/DOCE
A2: Despesas Fixas | C2: 0.2 | E2: Preço Venda Unit | G2: =IFERROR(C3/(1-C2-C5),"") -> 108.16728
A3: Custo Unitário | C3: =IFERROR(C6/C4,"") -> 32.450185 | E3: Luro s/Venda | G3: =G2*C5 -> 54.083642
A4: Quantidade Produzida | C4: 13 | E4: Preço Praticado | G4: 15
A5: Lucro s/Venda | C5: 0.5 | E5: Lucro Praticado | G5: =1-C3/G4-C2 -> -1.3633457
A6: Gasto Total | C6: =SUM(H8:H28) -> 421.85241 | E6: Lucro Praticado | G6: =G5*G4 -> -20.450185
A7: cod Prod | B7: Descrição ingredientes | D7: unid | E7: quantiadade | F7: valor $ | H7: Subtotal
A8: 203 | B8: =IFERROR(VLOOKUP(A8,ListaIngredientes!$A$5:$F$155,2,FALSE),"") -> 0 | D8: =IFERROR(VLOOKUP(A8,Tabela2[],3,FALSE),"") -> 0 | E8: 4 | F8: =IFERROR(VLOOKUP(A8,ListaIngredientes!$A$5:$F$155,6,FALSE),"") -> 0 | H8: =IFERROR(E8*F8,"") -> 0
A9: 188 | B9: =IFERROR(VLOOKUP(A9,ListaIngredientes!$A$5:$F$155,2,FALSE),"") -> LATA PALHA ITALIANA | D9: =IFERROR(VLOOKUP(A9,Tabela2[],3,FALSE),"") -> U | E9: 200 | F9: =IFERROR(VLOOKUP(A9,ListaIngredientes!$A$5:$F$155,6,FALSE),"") -> 1.59 | H9: =IFERROR(E9*F9,"") -> 318
A10: 230 | B10: =IFERROR(VLOOKUP(A10,ListaIngredientes!$A$5:$F$155,2,FALSE),"") -> 0 | D10: =IFERROR(VLOOKUP(A10,Tabela2[],3,FALSE),"") -> u | E10: 85 | F10: =IFERROR(VLOOKUP(A10,ListaIngredientes!$A$5:$F$155,6,FALSE),"") -> 0.149 | H10: =IFERROR(E10*F10,"") -> 12.665
A11: 182 | B11: =IFERROR(VLOOKUP(A11,ListaIngredientes!$A$5:$F$155,2,FALSE),"") -> GERGILIM | D11: =IFERROR(VLOOKUP(A11,Tabela2[],3,FALSE),"") -> KG | E11: 1 | F11: =IFERROR(VLOOKUP(A11,ListaIngredientes!$A$5:$F$155,6,FALSE),"") -> 0.029 | H11: =IFERROR(E11*F11,"") -> 0.029
A12: 156 | B12: =IFERROR(VLOOKUP(A12,ListaIngredientes!$A$5:$F$155,2,FALSE),"") -> embalagem quiche | D12: =IFERROR(VLOOKUP(A12,Tabela2[],3,FALSE),"") -> u | E12: 8 | F12: =IFERROR(VLOOKUP(A12,ListaIngredientes!$A$5:$F$155,6,FALSE),"") -> 0.599 | H12: =IFERROR(E12*F12,"") -> 4.792
A13: 158 | B13: =IFERROR(VLOOKUP(A13,ListaIngredientes!$A$5:$F$155,2,FALSE),"") -> ESSENCIA DE BAUNILHA | D13: =IFERROR(VLOOKUP(A13,Tabela2[],3,FALSE),"") -> ML | E13: 130 | F13: =IFERROR(VLOOKUP(A13,ListaIngredientes!$A$5:$F$155,6,FALSE),"") -> 0.099666667 | H13: =IFERROR(E13*F13,"") -> 12.956667
A14: 159 | B14: =IFERROR(VLOOKUP(A14,ListaIngredientes!$A$5:$F$155,2,FALSE),"") -> essencia de mel | D14: =IFERROR(VLOOKUP(A14,Tabela2[],3,FALSE),"") -> u | E14: 20 | F14: =IFERROR(VLOOKUP(A14,ListaIngredientes!$A$5:$F$155,6,FALSE),"") -> 2.59 | H14: =IFERROR(E14*F14,"") -> 51.8
A15: 163 | B15: =IFERROR(VLOOKUP(A15,ListaIngredientes!$A$5:$F$155,2,FALSE),"") -> fermento biologico | D15: =IFERROR(VLOOKUP(A15,Tabela2[],3,FALSE),"") -> kg | E15: 15 | F15: =IFERROR(VLOOKUP(A15,ListaIngredientes!$A$5:$F$155,6,FALSE),"") -> 0.05512 | H15: =IFERROR(E15*F15,"") -> 0.8268
A16: 230 | B16: =IFERROR(VLOOKUP(A16,ListaIngredientes!$A$5:$F$155,2,FALSE),"") -> 0 | D16: =IFERROR(VLOOKUP(A16,Tabela2[],3,FALSE),"") -> u | E16: 70 | F16: =IFERROR(VLOOKUP(A16,ListaIngredientes!$A$5:$F$155,6,FALSE),"") -> 0.149 | H16: =IFERROR(E16*F16,"") -> 10.43
A17: 139 | B17: =IFERROR(VLOOKUP(A17,ListaIngredientes!$A$5:$F$155,2,FALSE),"") -> cravo da india | D17: =IFERROR(VLOOKUP(A17,Tabela2[],3,FALSE),"") -> g | E17: 600 | F17: =IFERROR(VLOOKUP(A17,ListaIngredientes!$A$5:$F$155,6,FALSE),"") -> 0.00058823529 | H17: =IFERROR(E17*F17,"") -> 0.35294118
A18: 105 | B18: =IFERROR(VLOOKUP(A18,ListaIngredientes!$A$5:$F$155,2,FALSE),"") -> Bananas | D18: =IFERROR(VLOOKUP(A18,Tabela2[],3,FALSE),"") -> duzias | E18: 20 | F18: =IFERROR(VLOOKUP(A18,ListaIngredientes!$A$5:$F$155,6,FALSE),"") -> 0.5 | H18: =IFERROR(E18*F18,"") -> 10
A19: 125 | B19: =IFERROR(VLOOKUP(A19,ListaIngredientes!$A$5:$F$155,2,FALSE),"") -> 0 | D19: =IFERROR(VLOOKUP(A19,Tabela2[],3,FALSE),"") -> 0 | E19: 40 | F19: =IFERROR(VLOOKUP(A19,ListaIngredientes!$A$5:$F$155,6,FALSE),"") -> 0 | H19: =IFERROR(E19*F19,"") -> 0
A20: 131 | B20: =IFERROR(VLOOKUP(A20,ListaIngredientes!$A$5:$F$155,2,FALSE),"") -> 0 | D20: =IFERROR(VLOOKUP(A20,Tabela2[],3,FALSE),"") -> 0 | E20: 1 | F20: =IFERROR(VLOOKUP(A20,ListaIngredientes!$A$5:$F$155,6,FALSE),"") -> 0 | H20: =IFERROR(E20*F20,"") -> 0
B21: =IFERROR(VLOOKUP(A21,ListaIngredientes!$A$5:$F$155,2,FALSE),"") | D21: =IFERROR(VLOOKUP(A21,Tabela2[],3,FALSE),"") | F21: =IFERROR(VLOOKUP(A21,ListaIngredientes!$A$5:$F$155,6,FALSE),"") | H21: =IFERROR(E21*F21,"")
B22: =IFERROR(VLOOKUP(A22,ListaIngredientes!$A$5:$F$155,2,FALSE),"") | D22: =IFERROR(VLOOKUP(A22,Tabela2[],3,FALSE),"") | F22: =IFERROR(VLOOKUP(A22,ListaIngredientes!$A$5:$F$155,6,FALSE),"") | H22: =IFERROR(E22*F22,"")
B23: =IFERROR(VLOOKUP(A23,ListaIngredientes!$A$5:$F$155,2,FALSE),"") | D23: =IFERROR(VLOOKUP(A23,Tabela2[],3,FALSE),"") | F23: =IFERROR(VLOOKUP(A23,ListaIngredientes!$A$5:$F$155,6,FALSE),"") | H23: =IFERROR(E23*F23,"")
B24: =IFERROR(VLOOKUP(A24,ListaIngredientes!$A$5:$F$155,2,FALSE),"") | D24: =IFERROR(VLOOKUP(A24,Tabela2[],3,FALSE),"") | F24: =IFERROR(VLOOKUP(A24,ListaIngredientes!$A$5:$F$155,6,FALSE),"") | H24: =IFERROR(E24*F24,"")
B25: =IFERROR(VLOOKUP(A25,ListaIngredientes!$A$5:$F$155,2,FALSE),"") | D25: =IFERROR(VLOOKUP(A25,Tabela2[],3,FALSE),"") | F25: =IFERROR(VLOOKUP(A25,ListaIngredientes!$A$5:$F$155,6,FALSE),"") | H25: =IFERROR(E25*F25,"")
B26: =IFERROR(VLOOKUP(A26,ListaIngredientes!$A$5:$F$155,2,FALSE),"") | D26: =IFERROR(VLOOKUP(A26,Tabela2[],3,FALSE),"") | F26: =IFERROR(VLOOKUP(A26,ListaIngredientes!$A$5:$F$155,6,FALSE),"") | H26: =IFERROR(E26*F26,"")
B27: =IFERROR(VLOOKUP(A27,ListaIngredientes!$A$5:$F$155,2,FALSE),"") | D27: =IFERROR(VLOOKUP(A27,Tabela2[],3,FALSE),"") | F27: =IFERROR(VLOOKUP(A27,ListaIngredientes!$A$5:$F$155,6,FALSE),"") | H27: =IFERROR(E27*F27,"")
F28: soma | H28: =IFERROR(E28*F28,"")

Sheet NAKED M
A1: cod | B1: 501 | C1: =VLOOKUP(B1,PRODUTOS!$A$7:$E$204,2,FALSE) -> P A S T E L | E1: =C3 -> 63.935809 | G1: SOBREMESA/DOCE
A2: Despesas Fixas | C2: 0.2 | E2: Preço Venda Unit | G2: =IFERROR(C3/(1-C2-C5),"") -> 213.11936
A3: Custo Unitário | C3: =IFERROR(C6/C4,"") -> 63.935809 | E3: Luro s/Venda | G3: =G2*C5 -> 106.55968
A4: Quantidade Produzida | C4: 13 | E4: Preço Praticado | G4: 15
A5: Lucro s/Venda | C5: 0.5 | E5: Lucro Praticado | G5: =1-C3/G4-C2 -> -3.4623873
A6: Gasto Total | C6: =SUM(H8:H28) -> 831.16552 | E6: Lucro Praticado | G6: =G5*G4 -> -51.935809
A7: cod Prod | B7: Descrição ingredientes | D7: unid | E7: quantiadade | F7: valor $ | H7: Subtotal
A8: 203 | B8: =IFERROR(VLOOKUP(A8,ListaIngredientes!$A$5:$F$155,2,FALSE),"") -> 0 | D8: =IFERROR(VLOOKUP(A8,Tabela2[],3,FALSE),"") -> 0 | E8: 8 | F8: =IFERROR(VLOOKUP(A8,ListaIngredientes!$A$5:$F$155,6,FALSE),"") -> 0 | H8: =IFERROR(E8*F8,"") -> 0
A9: 188 | B9: =IFERROR(VLOOKUP(A9,ListaIngredientes!$A$5:$F$155,2,FALSE),"") -> LATA PALHA ITALIANA | D9: =IFERROR(VLOOKUP(A9,Tabela2[],3,FALSE),"") -> U | E9: 400 | F9: =IFERROR(VLOOKUP(A9,ListaIngredientes!$A$5:$F$155,6,FALSE),"") -> 1.59 | H9: =IFERROR(E9*F9,"") -> 636
A10: 230 | B10: =IFERROR(VLOOKUP(A10,ListaIngredientes!$A$5:$F$155,2,FALSE),"") -> 0 | D10: =IFERROR(VLOOKUP(A10,Tabela2[],3,FALSE),"") -> u | E10: 170 | F10: =IFERROR(VLOOKUP(A10,ListaIngredientes!$A$5:$F$155,6,FALSE),"") -> 0.149 | H10: =IFERROR(E10*F10,"") -> 25.33
A11: 230 | B11: =IFERROR(VLOOKUP(A11,ListaIngredientes!$A$5:$F$155,2,FALSE),"") -> 0 | D11: =IFERROR(VLOOKUP(A11,Tabela2[],3,FALSE),"") -> u | E11: 95 | F11: =IFERROR(VLOOKUP(A11,ListaIngredientes!$A$5:$F$155,6,FALSE),"") -> 0.149 | H11: =IFERROR(E11*F11,"") -> 14.155
A12: 163 | B12: =IFERROR(VLOOKUP(A12,ListaIngredientes!$A$5:$F$155,2,FALSE),"") -> fermento biologico | D12: =IFERROR(VLOOKUP(A12,Tabela2[],3,FALSE),"") -> kg | E12: 30 | F12: =IFERROR(VLOOKUP(A12,ListaIngredientes!$A$5:$F$155,6,FALSE),"") -> 0.05512 | H12: =IFERROR(E12*F12,"") -> 1.6536
A13: 182 | B13: =IFERROR(VLOOKUP(A13,ListaIngredientes!$A$5:$F$155,2,FALSE),"") -> GERGILIM | D13: =IFERROR(VLOOKUP(A13,Tabela2[],3,FALSE),"") -> KG | E13: 2 | F13: =IFERROR(VLOOKUP(A13,ListaIngredientes!$A$5:$F$155,6,FALSE),"") -> 0.029 | H13: =IFERROR(E13*F13,"") -> 0.058
A14: 156 | B14: =IFERROR(VLOOKUP(A14,ListaIngredientes!$A$5:$F$155,2,FALSE),"") -> embalagem quiche | D14: =IFERROR(VLOOKUP(A14,Tabela2[],3,FALSE),"") -> u | E14: 15 | F14: =IFERROR(VLOOKUP(A14,ListaIngredientes!$A$5:$F$155,6,FALSE),"") -> 0.599 | H14: =IFERROR(E14*F14,"") -> 8.985
A15: 158 | B15: =IFERROR(VLOOKUP(A15,ListaIngredientes!$A$5:$F$155,2,FALSE),"") -> ESSENCIA DE BAUNILHA | D15: =IFERROR(VLOOKUP(A15,Tabela2[],3,FALSE),"") -> ML | E15: 260 | F15: =IFERROR(VLOOKUP(A15,ListaIngredientes!$A$5:$F$155,6,FALSE),"") -> 0.099666667 | H15: =IFERROR(E15*F15,"") -> 25.913333
A16: 159 | B16: =IFERROR(VLOOKUP(A16,ListaIngredientes!$A$5:$F$155,2,FALSE),"") -> essencia de mel | D16: =IFERROR(VLOOKUP(A16,Tabela2[],3,FALSE),"") -> u | E16: 40 | F16: =IFERROR(VLOOKUP(A16,ListaIngredientes!$A$5:$F$155,6,FALSE),"") -> 2.59 | H16: =IFERROR(E16*F16,"") -> 103.6
A17: 139 | B17: =IFERROR(VLOOKUP(A17,ListaIngredientes!$A$5:$F$155,2,FALSE),"") -> cravo da india | D17: =IFERROR(VLOOKUP(A17,Tabela2[],3,FALSE),"") -> g | E17: 800 | F17: =IFERROR(VLOOKUP(A17,ListaIngredientes!$A$5:$F$155,6,FALSE),"") -> 0.00058823529 | H17: =IFERROR(E17*F17,"") -> 0.47058824
A18: 105 | B18: =IFERROR(VLOOKUP(A18,ListaIngredientes!$A$5:$F$155,2,FALSE),"") -> Bananas | D18: =IFERROR(VLOOKUP(A18,Tabela2[],3,FALSE),"") -> duzias | E18: 30 | F18: =IFERROR(VLOOKUP(A18,ListaIngredientes!$A$5:$F$155,6,FALSE),"") -> 0.5 | H18: =IFERROR(E18*F18,"") -> 15
A19: 125 | B19: =IFERROR(VLOOKUP(A19,ListaIngredientes!$A$5:$F$155,2,FALSE),"") -> 0 | D19: =IFERROR(VLOOKUP(A19,Tabela2[],3,FALSE),"") -> 0 | E19: 55 | F19: =IFERROR(VLOOKUP(A19,ListaIngredientes!$A$5:$F$155,6,FALSE),"") -> 0 | H19: =IFERROR(E19*F19,"") -> 0
A20: 131 | B20: =IFERROR(VLOOKUP(A20,ListaIngredientes!$A$5:$F$155,2,FALSE),"") -> 0 | D20: =IFERROR(VLOOKUP(A20,Tabela2[],3,FALSE),"") -> 0 | E20: 1 | F20: =IFERROR(VLOOKUP(A20,ListaIngredientes!$A$5:$F$155,6,FALSE),"") -> 0 | H20: =IFERROR(E20*F20,"") -> 0
B21: =IFERROR(VLOOKUP(A21,ListaIngredientes!$A$5:$F$155,2,FALSE),"") | D21: =IFERROR(VLOOKUP(A21,Tabela2[],3,FALSE),"") | F21: =IFERROR(VLOOKUP(A21,ListaIngredientes!$A$5:$F$155,6,FALSE),"") | H21: =IFERROR(E21*F21,"")
B22: =IFERROR(VLOOKUP(A22,ListaIngredientes!$A$5:$F$155,2,FALSE),"") | D22: =IFERROR(VLOOKUP(A22,Tabela2[],3,FALSE),"") | F22: =IFERROR(VLOOKUP(A22,ListaIngredientes!$A$5:$F$155,6,FALSE),"") | H22: =IFERROR(E22*F22,"")
B23: =IFERROR(VLOOKUP(A23,ListaIngredientes!$A$5:$F$155,2,FALSE),"") | D23: =IFERROR(VLOOKUP(A23,Tabela2[],3,FALSE),"") | F23: =IFERROR(VLOOKUP(A23,ListaIngredientes!$A$5:$F$155,6,FALSE),"") | H23: =IFERROR(E23*F23,"")
B24: =IFERROR(VLOOKUP(A24,ListaIngredientes!$A$5:$F$155,2,FALSE),"") | D24: =IFERROR(VLOOKUP(A24,Tabela2[],3,FALSE),"") | F24: =IFERROR(VLOOKUP(A24,ListaIngredientes!$A$5:$F$155,6,FALSE),"") | H24: =IFERROR(E24*F24,"")
B25: =IFERROR(VLOOKUP(A25,ListaIngredientes!$A$5:$F$155,2,FALSE),"") | D25: =IFERROR(VLOOKUP(A25,Tabela2[],3,FALSE),"") | F25: =IFERROR(VLOOKUP(A25,ListaIngredientes!$A$5:$F$155,6,FALSE),"") | H25: =IFERROR(E25*F25,"")
B26: =IFERROR(VLOOKUP(A26,ListaIngredientes!$A$5:$F$155,2,FALSE),"") | D26: =IFERROR(VLOOKUP(A26,Tabela2[],3,FALSE),"") | F26: =IFERROR(VLOOKUP(A26,ListaIngredientes!$A$5:$F$155,6,FALSE),"") | H26: =IFERROR(E26*F26,"")
B27: =IFERROR(VLOOKUP(A27,ListaIngredientes!$A$5:$F$155,2,FALSE),"") | D27: =IFERROR(VLOOKUP(A27,Tabela2[],3,FALSE),"") | F27: =IFERROR(VLOOKUP(A27,ListaIngredientes!$A$5:$F$155,6,FALSE),"") | H27: =IFERROR(E27*F27,"")
F28: soma | H28: =IFERROR(E28*F28,"")
H29: =SUM(H8:H27) -> 831.16552

Sheet NAKED G
A1: cod | B1: 501 | C1: =VLOOKUP(B1,PRODUTOS!$A$7:$E$204,2,FALSE) -> P A S T E L | E1: =C3 -> 63.935809 | G1: SOBREMESA/DOCE
A2: Despesas Fixas | C2: 0.2 | E2: Preço Venda Unit | G2: =IFERROR(C3/(1-C2-C5),"") -> 213.11936
